Workbook

Sheet Data Info
A1: Days | B1: Days Number | C1: Weekend/day
A2: Monday | B2: {=SEQUENCE(7,1)} -> 1 | C2: Weekday
A3: Tuesday | B3: 2 | C3: Weekday
A4: Wednesday | B4: 3 | C4: Weekday
A5: Thursday | B5: 4 | C5: Weekday
A6: Friday | B6: 5 | C6: Weekday
A7: Saturday | B7: 6 | C7: Weekend
A8: Sunday | B8: 7 | C8: Weekend
A10: Months | B10: Months Number
A11: January | B11: {=SEQUENCE(12,1)} -> 1
A12: February | B12: 2
A13: March | B13: 3
A14: April | B14: 4
A15: May | B15: 5
A16: June | B16: 6
A17: July | B17: 7
A18: August | B18: 8
A19: September | B19: 9
A20: October | B20: 10
A21: November | B21: 11
A22: December | B22: 12

Sheet Raw Data
A1: Date,Receipt number,Receipt type,Category,SKU,Item,Variant,Modifiers applied,Quantity,Gross sales,Discounts,Net sales,Cost of goods,Gross profit,Taxes,Dining option,POS,Store,Cashier name,Customer name,Customer contacts,Comment,Status | B1: =IFERROR(__xludf.DUMMYFUNCTION("SPLIT(A1,"","")"),"Date") -> Date | C1: =IFERROR(__xludf.DUMMYFUNCTION("""COMPUTED_VALUE"""),"Receipt number") -> Receipt number | D1: =IFERROR(__xludf.DUMMYFUNCTION("""COMPUTED_VALUE"""),"Receipt type") -> Receipt type | E1: =IFERROR(__xludf.DUMMYFUNCTION("""COMPUTED_VALUE"""),"Category") -> Category | F1: =IFERROR(__xludf.DUMMYFUNCTION("""COMPUTED_VALUE"""),"SKU") -> SKU | G1: =IFERROR(__xludf.DUMMYFUNCTION("""COMPUTED_VALUE"""),"Item") -> Item | H1: =IFERROR(__xludf.DUMMYFUNCTION("""COMPUTED_VALUE"""),"Variant") -> Variant | I1: =IFERROR(__xludf.DUMMYFUNCTION("""COMPUTED_VALUE"""),"Modifiers applied") -> Modifiers applied | J1: =IFERROR(__xludf.DUMMYFUNCTION("""COMPUTED_VALUE"""),"Quantity") -> Quantity | K1: =IFERROR(__xludf.DUMMYFUNCTION("""COMPUTED_VALUE"""),"Gross sales") -> Gross sales | L1: =IFERROR(__xludf.DUMMYFUNCTION("""COMPUTED_VALUE"""),"Discounts") -> Discounts | M1: =IFERROR(__xludf.DUMMYFUNCTION("""COMPUTED_VALUE"""),"Net sales") -> Net sales | N1: =IFERROR(__xludf.DUMMYFUNCTION("""COMPUTED_VALUE"""),"Cost of goods") -> Cost of goods | O1: =IFERROR(__xludf.DUMMYFUNCTION("""COMPUTED_VALUE"""),"Gross profit") -> Gross profit | P1: =IFERROR(__xludf.DUMMYFUNCTION("""COMPUTED_VALUE"""),"Taxes") -> Taxes | Q1: =IFERROR(__xludf.DUMMYFUNCTION("""COMPUTED_VALUE"""),"Dining option") -> Dining option | R1: =IFERROR(__xludf.DUMMYFUNCTION("""COMPUTED_VALUE"""),"POS") -> POS | S1: =IFERROR(__xludf.DUMMYFUNCTION("""COMPUTED_VALUE"""),"Store") -> Store | T1: =IFERROR(__xludf.DUMMYFUNCTION("""COMPUTED_VALUE"""),"Cashier name") -> Cashier name | U1: =IFERROR(__xludf.DUMMYFUNCTION("""COMPUTED_VALUE"""),"Customer name") -> Customer name | V1: =IFERROR(__xludf.DUMMYFUNCTION("""COMPUTED_VALUE"""),"Customer contacts") -> Customer contacts | W1: =IFERROR(__xludf.DUMMYFUNCTION("""COMPUTED_VALUE"""),"Comment") -> Comment | X1: =IFERROR(__xludf.DUMMYFUNCTION("""COMPUTED_VALUE"""),"Status") -> Status
A2: 29/09/2024 20:25,2-9570,Refund,Roti,10000,Roti Bawang Saus Keju,,,-1.000,-29524.00,0.00,-29524.00,-0.00,-29524.00,-1476.00,Take Away,Kedai,Temu Roti,Owner,,,,Closed | B2: =IFERROR(__xludf.DUMMYFUNCTION("SPLIT(A2,"","",0,0)"),45564.850694444445) -> 45564.851 | C2: =IFERROR(__xludf.DUMMYFUNCTION("""COMPUTED_VALUE"""),2801443.0) -> 2801443 | D2: =IFERROR(__xludf.DUMMYFUNCTION("""COMPUTED_VALUE"""),"Refund") -> Refund | E2: =IFERROR(__xludf.DUMMYFUNCTION("""COMPUTED_VALUE"""),"Roti") -> Roti | F2: =IFERROR(__xludf.DUMMYFUNCTION("""COMPUTED_VALUE"""),10000.0) -> 10000 | G2: =IFERROR(__xludf.DUMMYFUNCTION("""COMPUTED_VALUE"""),"Roti Bawang Saus Keju") -> Roti Bawang Saus Keju | J2: =IFERROR(__xludf.DUMMYFUNCTION("""COMPUTED_VALUE"""),-1.0) -> -1 | K2: =IFERROR(__xludf.DUMMYFUNCTION("""COMPUTED_VALUE"""),-29524.0) -> -29524 | L2: =IFERROR(__xludf.DUMMYFUNCTION("""COMPUTED_VALUE"""),0.0) -> 0 | M2: =IFERROR(__xludf.DUMMYFUNCTION("""COMPUTED_VALUE"""),-29524.0) -> -29524 | N2: =IFERROR(__xludf.DUMMYFUNCTION("""COMPUTED_VALUE"""),0.0) -> 0 | O2: =IFERROR(__xludf.DUMMYFUNCTION("""COMPUTED_VALUE"""),-29524.0) -> -29524 | P2: =IFERROR(__xludf.DUMMYFUNCTION("""COMPUTED_VALUE"""),-1476.0) -> -1476 | Q2: =IFERROR(__xludf.DUMMYFUNCTION("""COMPUTED_VALUE"""),"Take Away") -> Take Away | R2: =IFERROR(__xludf.DUMMYFUNCTION("""COMPUTED_VALUE"""),"Kedai") -> Kedai | S2: =IFERROR(__xludf.DUMMYFUNCTION("""COMPUTED_VALUE"""),"Temu Roti") -> Temu Roti | T2: =IFERROR(__xludf.DUMMYFUNCTION("""COMPUTED_VALUE"""),"Owner") -> Owner | X2: =IFERROR(__xludf.DUMMYFUNCTION("""COMPUTED_VALUE"""),"Closed") -> Closed
A3: 29/09/2024 20:24,2-9569,Refund,Minuman,10112,Air mineral,,,-2.000,-13334.00,0.00,-13334.00,-0.00,-13334.00,-667.00,Dine In,Kedai,Temu Roti,Owner,,,,Closed | B3: =IFERROR(__xludf.DUMMYFUNCTION("SPLIT(A3,"","",0,0)"),45564.85) -> 45564.85 | C3: =IFERROR(__xludf.DUMMYFUNCTION("""COMPUTED_VALUE"""),2801078.0) -> 2801078 | D3: =IFERROR(__xludf.DUMMYFUNCTION("""COMPUTED_VALUE"""),"Refund") -> Refund | E3: =IFERROR(__xludf.DUMMYFUNCTION("""COMPUTED_VALUE"""),"Minuman") -> Minuman | F3: =IFERROR(__xludf.DUMMYFUNCTION("""COMPUTED_VALUE"""),10112.0) -> 10112 | G3: =IFERROR(__xludf.DUMMYFUNCTION("""COMPUTED_VALUE"""),"Air mineral") -> Air mineral | J3: =IFERROR(__xludf.DUMMYFUNCTION("""COMPUTED_VALUE"""),-2.0) -> -2 | K3: =IFERROR(__xludf.DUMMYFUNCTION("""COMPUTED_VALUE"""),-13334.0) -> -13334 | L3: =IFERROR(__xludf.DUMMYFUNCTION("""COMPUTED_VALUE"""),0.0) -> 0 | M3: =IFERROR(__xludf.DUMMYFUNCTION("""COMPUTED_VALUE"""),-13334.0) -> -13334 | N3: =IFERROR(__xludf.DUMMYFUNCTION("""COMPUTED_VALUE"""),0.0) -> 0 | O3: =IFERROR(__xludf.DUMMYFUNCTION("""COMPUTED_VALUE"""),-13334.0) -> -13334 | P3: =IFERROR(__xludf.DUMMYFUNCTION("""COMPUTED_VALUE"""),-667.0) -> -667 | Q3: =IFERROR(__xludf.DUMMYFUNCTION("""COMPUTED_VALUE"""),"Dine In") -> Dine In | R3: =IFERROR(__xludf.DUMMYFUNCTION("""COMPUTED_VALUE"""),"Kedai") -> Kedai | S3: =IFERROR(__xludf.DUMMYFUNCTION("""COMPUTED_VALUE"""),"Temu Roti") -> Temu Roti | T3: =IFERROR(__xludf.DUMMYFUNCTION("""COMPUTED_VALUE"""),"Owner") -> Owner | X3: =IFERROR(__xludf.DUMMYFUNCTION("""COMPUTED_VALUE"""),"Closed") -> Closed
A4: 29/09/2024 20:16,2-9568,Sale,Roti,10002,Roti Cranberry,,,1.000,18571.00,0.00,18571.00,0.00,18571.00,929.00,Dine In,Kedai,Temu Roti,Owner,,,,Closed | B4: =IFERROR(__xludf.DUMMYFUNCTION("SPLIT(A4,"","",0,0)"),45564.84444444445) -> 45564.844 | C4: =IFERROR(__xludf.DUMMYFUNCTION("""COMPUTED_VALUE"""),2800712.0) -> 2800712 | D4: =IFERROR(__xludf.DUMMYFUNCTION("""COMPUTED_VALUE"""),"Sale") -> Sale | E4: =IFERROR(__xludf.DUMMYFUNCTION("""COMPUTED_VALUE"""),"Roti") -> Roti | F4: =IFERROR(__xludf.DUMMYFUNCTION("""COMPUTED_VALUE"""),10002.0) -> 10002 | G4: =IFERROR(__xludf.DUMMYFUNCTION("""COMPUTED_VALUE"""),"Roti Cranberry") -> Roti Cranberry | J4: =IFERROR(__xludf.DUMMYFUNCTION("""COMPUTED_VALUE"""),1.0) -> 1 | K4: =IFERROR(__xludf.DUMMYFUNCTION("""COMPUTED_VALUE"""),18571.0) -> 18571 | L4: =IFERROR(__xludf.DUMMYFUNCTION("""COMPUTED_VALUE"""),0.0) -> 0 | M4: =IFERROR(__xludf.DUMMYFUNCTION("""COMPUTED_VALUE"""),18571.0) -> 18571 | N4: =IFERROR(__xludf.DUMMYFUNCTION("""COMPUTED_VALUE"""),0.0) -> 0 | O4: =IFERROR(__xludf.DUMMYFUNCTION("""COMPUTED_VALUE"""),18571.0) -> 18571 | P4: =IFERROR(__xludf.DUMMYFUNCTION("""COMPUTED_VALUE"""),929.0) -> 929 | Q4: =IFERROR(__xludf.DUMMYFUNCTION("""COMPUTED_VALUE"""),"Dine In") -> Dine In | R4: =IFERROR(__xludf.DUMMYFUNCTION("""COMPUTED_VALUE"""),"Kedai") -> Kedai | S4: =IFERROR(__xludf.DUMMYFUNCTION("""COMPUTED_VALUE"""),"Temu Roti") -> Temu Roti | T4: =IFERROR(__xludf.DUMMYFUNCTION("""COMPUTED_VALUE"""),"Owner") -> Owner | X4: =IFERROR(__xludf.DUMMYFUNCTION("""COMPUTED_VALUE"""),"Closed") -> Closed
A5: 29/09/2024 18:40,2-9567,Sale,Minuman,10122,Rempah Madu Panas,,,2.000,43810.00,0.00,43810.00,0.00,43810.00,2191.00,Dine In,Kedai,Temu Roti,Owner,,,,Closed | B5: =IFERROR(__xludf.DUMMYFUNCTION("SPLIT(A5,"","",0,0)"),45564.77777777778) -> 45564.778 | C5: =IFERROR(__xludf.DUMMYFUNCTION("""COMPUTED_VALUE"""),2800347.0) -> 2800347 | D5: =IFERROR(__xludf.DUMMYFUNCTION("""COMPUTED_VALUE"""),"Sale") -> Sale | E5: =IFERROR(__xludf.DUMMYFUNCTION("""COMPUTED_VALUE"""),"Minuman") -> Minuman | F5: =IFERROR(__xludf.DUMMYFUNCTION("""COMPUTED_VALUE"""),10122.0) -> 10122 | G5: =IFERROR(__xludf.DUMMYFUNCTION("""COMPUTED_VALUE"""),"Rempah Madu Panas") -> Rempah Madu Panas | J5: =IFERROR(__xludf.DUMMYFUNCTION("""COMPUTED_VALUE"""),2.0) -> 2 | K5: =IFERROR(__xludf.DUMMYFUNCTION("""COMPUTED_VALUE"""),43810.0) -> 43810 | L5: =IFERROR(__xludf.DUMMYFUNCTION("""COMPUTED_VALUE"""),0.0) -> 0 | M5: =IFERROR(__xludf.DUMMYFUNCTION("""COMPUTED_VALUE"""),43810.0) -> 43810 | N5: =IFERROR(__xludf.DUMMYFUNCTION("""COMPUTED_VALUE"""),0.0) -> 0 | O5: =IFERROR(__xludf.DUMMYFUNCTION("""COMPUTED_VALUE"""),43810.0) -> 43810 | P5: =IFERROR(__xludf.DUMMYFUNCTION("""COMPUTED_VALUE"""),2191.0) -> 2191 | Q5: =IFERROR(__xludf.DUMMYFUNCTION("""COMPUTED_VALUE"""),"Dine In") -> Dine In | R5: =IFERROR(__xludf.DUMMYFUNCTION("""COMPUTED_VALUE"""),"Kedai") -> Kedai | S5: =IFERROR(__xludf.DUMMYFUNCTION("""COMPUTED_VALUE"""),"Temu Roti") -> Temu Roti | T5: =IFERROR(__xludf.DUMMYFUNCTION("""COMPUTED_VALUE"""),"Owner") -> Owner | X5: =IFERROR(__xludf.DUMMYFUNCTION("""COMPUTED_VALUE"""),"Closed") -> Closed
A6: 29/09/2024 18:40,2-9567,Sale,Kudapan,10051,Tahu baso,,,1.000,25238.00,0.00,25238.00,0.00,25238.00,1261.00,Dine In,Kedai,Temu Roti,Owner,,,,Closed | B6: =IFERROR(__xludf.DUMMYFUNCTION("SPLIT(A6,"","",0,0)"),45564.77777777778) -> 45564.778 | C6: =IFERROR(__xludf.DUMMYFUNCTION("""COMPUTED_VALUE"""),2800347.0) -> 2800347 | D6: =IFERROR(__xludf.DUMMYFUNCTION("""COMPUTED_VALUE"""),"Sale") -> Sale | E6: =IFERROR(__xludf.DUMMYFUNCTION("""COMPUTED_VALUE"""),"Kudapan") -> Kudapan | F6: =IFERROR(__xludf.DUMMYFUNCTION("""COMPUTED_VALUE"""),10051.0) -> 10051 | G6: =IFERROR(__xludf.DUMMYFUNCTION("""COMPUTED_VALUE"""),"Tahu baso") -> Tahu baso | J6: =IFERROR(__xludf.DUMMYFUNCTION("""COMPUTED_VALUE"""),1.0) -> 1 | K6: =IFERROR(__xludf.DUMMYFUNCTION("""COMPUTED_VALUE"""),25238.0) -> 25238 | L6: =IFERROR(__xludf.DUMMYFUNCTION("""COMPUTED_VALUE"""),0.0) -> 0 | M6: =IFERROR(__xludf.DUMMYFUNCTION("""COMPUTED_VALUE"""),25238.0) -> 25238 | N6: =IFERROR(__xludf.DUMMYFUNCTION("""COMPUTED_VALUE"""),0.0) -> 0 | O6: =IFERROR(__xludf.DUMMYFUNCTION("""COMPUTED_VALUE"""),25238.0) -> 25238 | P6: =IFERROR(__xludf.DUMMYFUNCTION("""COMPUTED_VALUE"""),1261.0) -> 1261 | Q6: =IFERROR(__xludf.DUMMYFUNCTION("""COMPUTED_VALUE"""),"Dine In") -> Dine In | R6: =IFERROR(__xludf.DUMMYFUNCTION("""COMPUTED_VALUE"""),"Kedai") -> Kedai | S6: =IFERROR(__xludf.DUMMYFUNCTION("""COMPUTED_VALUE"""),"Temu Roti") -> Temu Roti | T6: =IFERROR(__xludf.DUMMYFUNCTION("""COMPUTED_VALUE"""),"Owner") -> Owner | X6: =IFERROR(__xludf.DUMMYFUNCTION("""COMPUTED_VALUE"""),"Closed") -> Closed
A7: 29/09/2024 18:40,2-9566,Refund,Minuman,10122,Rempah Madu Panas,,,-1.000,-21905.00,0.00,-21905.00,-0.00,-21905.00,-1095.00,Dine In,Kedai,Temu Roti,Owner,,,,Closed | B7: =IFERROR(__xludf.DUMMYFUNCTION("SPLIT(A7,"","",0,0)"),45564.77777777778) -> 45564.778 | C7: =IFERROR(__xludf.DUMMYFUNCTION("""COMPUTED_VALUE"""),2799982.0) -> 2799982 | D7: =IFERROR(__xludf.DUMMYFUNCTION("""COMPUTED_VALUE"""),"Refund") -> Refund | E7: =IFERROR(__xludf.DUMMYFUNCTION("""COMPUTED_VALUE"""),"Minuman") -> Minuman | F7: =IFERROR(__xludf.DUMMYFUNCTION("""COMPUTED_VALUE"""),10122.0) -> 10122 | G7: =IFERROR(__xludf.DUMMYFUNCTION("""COMPUTED_VALUE"""),"Rempah Madu Panas") -> Rempah Madu Panas | J7: =IFERROR(__xludf.DUMMYFUNCTION("""COMPUTED_VALUE"""),-1.0) -> -1 | K7: =IFERROR(__xludf.DUMMYFUNCTION("""COMPUTED_VALUE"""),-21905.0) -> -21905 | L7: =IFERROR(__xludf.DUMMYFUNCTION("""COMPUTED_VALUE"""),0.0) -> 0 | M7: =IFERROR(__xludf.DUMMYFUNCTION("""COMPUTED_VALUE"""),-21905.0) -> -21905 | N7: =IFERROR(__xludf.DUMMYFUNCTION("""COMPUTED_VALUE"""),0.0) -> 0 | O7: =IFERROR(__xludf.DUMMYFUNCTION("""COMPUTED_VALUE"""),-21905.0) -> -21905 | P7: =IFERROR(__xludf.DUMMYFUNCTION("""COMPUTED_VALUE"""),-1095.0) -> -1095 | Q7: =IFERROR(__xludf.DUMMYFUNCTION("""COMPUTED_VALUE"""),"Dine In") -> Dine In | R7: =IFERROR(__xludf.DUMMYFUNCTION("""COMPUTED_VALUE"""),"Kedai") -> Kedai | S7: =IFERROR(__xludf.DUMMYFUNCTION("""COMPUTED_VALUE"""),"Temu Roti") -> Temu Roti | T7: =IFERROR(__xludf.DUMMYFUNCTION("""COMPUTED_VALUE"""),"Owner") -> Owner | X7: =IFERROR(__xludf.DUMMYFUNCTION("""COMPUTED_VALUE"""),"Closed") -> Closed
A8: 29/09/2024 18:40,2-9566,Refund,Kudapan,10051,Tahu baso,,,-2.000,-50476.00,0.00,-50476.00,-0.00,-50476.00,-2524.00,Dine In,Kedai,Temu Roti,Owner,,,,Closed | B8: =IFERROR(__xludf.DUMMYFUNCTION("SPLIT(A8,"","",0,0)"),45564.77777777778) -> 45564.778 | C8: =IFERROR(__xludf.DUMMYFUNCTION("""COMPUTED_VALUE"""),2799982.0) -> 2799982 | D8: =IFERROR(__xludf.DUMMYFUNCTION("""COMPUTED_VALUE"""),"Refund") -> Refund | E8: =IFERROR(__xludf.DUMMYFUNCTION("""COMPUTED_VALUE"""),"Kudapan") -> Kudapan | F8: =IFERROR(__xludf.DUMMYFUNCTION("""COMPUTED_VALUE"""),10051.0) -> 10051 | G8: =IFERROR(__xludf.DUMMYFUNCTION("""COMPUTED_VALUE"""),"Tahu baso") -> Tahu baso | J8: =IFERROR(__xludf.DUMMYFUNCTION("""COMPUTED_VALUE"""),-2.0) -> -2 | K8: =IFERROR(__xludf.DUMMYFUNCTION("""COMPUTED_VALUE"""),-50476.0) -> -50476 | L8: =IFERROR(__xludf.DUMMYFUNCTION("""COMPUTED_VALUE"""),0.0) -> 0 | M8: =IFERROR(__xludf.DUMMYFUNCTION("""COMPUTED_VALUE"""),-50476.0) -> -50476 | N8: =IFERROR(__xludf.DUMMYFUNCTION("""COMPUTED_VALUE"""),0.0) -> 0 | O8: =IFERROR(__xludf.DUMMYFUNCTION("""COMPUTED_VALUE"""),-50476.0) -> -50476 | P8: =IFERROR(__xludf.DUMMYFUNCTION("""COMPUTED_VALUE"""),-2524.0) -> -2524 | Q8: =IFERROR(__xludf.DUMMYFUNCTION("""COMPUTED_VALUE"""),"Dine In") -> Dine In | R8: =IFERROR(__xludf.DUMMYFUNCTION("""COMPUTED_VALUE"""),"Kedai") -> Kedai | S8: =IFERROR(__xludf.DUMMYFUNCTION("""COMPUTED_VALUE"""),"Temu Roti") -> Temu Roti | T8: =IFERROR(__xludf.DUMMYFUNCTION("""COMPUTED_VALUE"""),"Owner") -> Owner | X8: =IFERROR(__xludf.DUMMYFUNCTION("""COMPUTED_VALUE"""),"Closed") -> Closed
A9: 29/09/2024 18:40,2-9566,Refund,Minuman,10122,Rempah Madu Panas,,,-1.000,-21905.00,0.00,-21905.00,-0.00,-21905.00,-1095.00,Dine In,Kedai,Temu Roti,Owner,,,,Closed | B9: =IFERROR(__xludf.DUMMYFUNCTION("SPLIT(A9,"","",0,0)"),45564.77777777778) -> 45564.778 | C9: =IFERROR(__xludf.DUMMYFUNCTION("""COMPUTED_VALUE"""),2799982.0) -> 2799982 | D9: =IFERROR(__xludf.DUMMYFUNCTION("""COMPUTED_VALUE"""),"Refund") -> Refund | E9: =IFERROR(__xludf.DUMMYFUNCTION("""COMPUTED_VALUE"""),"Minuman") -> Minuman | F9: =IFERROR(__xludf.DUMMYFUNCTION("""COMPUTED_VALUE"""),10122.0) -> 10122 | G9: =IFERROR(__xludf.DUMMYFUNCTION("""COMPUTED_VALUE"""),"Rempah Madu Panas") -> Rempah Madu Panas | J9: =IFERROR(__xludf.DUMMYFUNCTION("""COMPUTED_VALUE"""),-1.0) -> -1 | K9: =IFERROR(__xludf.DUMMYFUNCTION("""COMPUTED_VALUE"""),-21905.0) -> -21905 | L9: =IFERROR(__xludf.DUMMYFUNCTION("""COMPUTED_VALUE"""),0.0) -> 0 | M9: =IFERROR(__xludf.DUMMYFUNCTION("""COMPUTED_VALUE"""),-21905.0) -> -21905 | N9: =IFERROR(__xludf.DUMMYFUNCTION("""COMPUTED_VALUE"""),0.0) -> 0 | O9: =IFERROR(__xludf.DUMMYFUNCTION("""COMPUTED_VALUE"""),-21905.0) -> -21905 | P9: =IFERROR(__xludf.DUMMYFUNCTION("""COMPUTED_VALUE"""),-1095.0) -> -1095 | Q9: =IFERROR(__xludf.DUMMYFUNCTION("""COMPUTED_VALUE"""),"Dine In") -> Dine In | R9: =IFERROR(__xludf.DUMMYFUNCTION("""COMPUTED_VALUE"""),"Kedai") -> Kedai | S9: =IFERROR(__xludf.DUMMYFUNCTION("""COMPUTED_VALUE"""),"Temu Roti") -> Temu Roti | T9: =IFERROR(__xludf.DUMMYFUNCTION("""COMPUTED_VALUE"""),"Owner") -> Owner | X9: =IFERROR(__xludf.DUMMYFUNCTION("""COMPUTED_VALUE"""),"Closed") -> Closed
A10: 29/09/2024 18:36,2-9565,Sale,Minuman,10122,Rempah Madu Panas,,,1.000,21905.00,0.00,21905.00,0.00,21905.00,1095.00,Dine In,Kedai,Temu Roti,Owner,,,,Closed | B10: =IFERROR(__xludf.DUMMYFUNCTION("SPLIT(A10,"","",0,0)"),45564.775) -> 45564.775 | C10: =IFERROR(__xludf.DUMMYFUNCTION("""COMPUTED_VALUE"""),2799617.0) -> 2799617 | D10: =IFERROR(__xludf.DUMMYFUNCTION("""COMPUTED_VALUE"""),"Sale") -> Sale | E10: =IFERROR(__xludf.DUMMYFUNCTION("""COMPUTED_VALUE"""),"Minuman") -> Minuman | F10: =IFERROR(__xludf.DUMMYFUNCTION("""COMPUTED_VALUE"""),10122.0) -> 10122 | G10: =IFERROR(__xludf.DUMMYFUNCTION("""COMPUTED_VALUE"""),"Rempah Madu Panas") -> Rempah Madu Panas | J10: =IFERROR(__xludf.DUMMYFUNCTION("""COMPUTED_VALUE"""),1.0) -> 1 | K10: =IFERROR(__xludf.DUMMYFUNCTION("""COMPUTED_VALUE"""),21905.0) -> 21905 | L10: =IFERROR(__xludf.DUMMYFUNCTION("""COMPUTED_VALUE"""),0.0) -> 0 | M10: =IFERROR(__xludf.DUMMYFUNCTION("""COMPUTED_VALUE"""),21905.0) -> 21905 | N10: =IFERROR(__xludf.DUMMYFUNCTION("""COMPUTED_VALUE"""),0.0) -> 0 | O10: =IFERROR(__xludf.DUMMYFUNCTION("""COMPUTED_VALUE"""),21905.0) -> 21905 | P10: =IFERROR(__xludf.DUMMYFUNCTION("""COMPUTED_VALUE"""),1095.0) -> 1095 | Q10: =IFERROR(__xludf.DUMMYFUNCTION("""COMPUTED_VALUE"""),"Dine In") -> Dine In | R10: =IFERROR(__xludf.DUMMYFUNCTION("""COMPUTED_VALUE"""),"Kedai") -> Kedai | S10: =IFERROR(__xludf.DUMMYFUNCTION("""COMPUTED_VALUE"""),"Temu Roti") -> Temu Roti | T10: =IFERROR(__xludf.DUMMYFUNCTION("""COMPUTED_VALUE"""),"Owner") -> Owner | X10: =IFERROR(__xludf.DUMMYFUNCTION("""COMPUTED_VALUE"""),"Closed") -> Closed
A11: 29/09/2024 18:36,2-9565,Sale,Kudapan,10051,Tahu baso,,,2.000,50476.00,0.00,50476.00,0.00,50476.00,2524.00,Dine In,Kedai,Temu Roti,Owner,,,,Closed | B11: =IFERROR(__xludf.DUMMYFUNCTION("SPLIT(A11,"","",0,0)"),45564.775) -> 45564.775 | C11: =IFERROR(__xludf.DUMMYFUNCTION("""COMPUTED_VALUE"""),2799617.0) -> 2799617 | D11: =IFERROR(__xludf.DUMMYFUNCTION("""COMPUTED_VALUE"""),"Sale") -> Sale | E11: =IFERROR(__xludf.DUMMYFUNCTION("""COMPUTED_VALUE"""),"Kudapan") -> Kudapan | F11: =IFERROR(__xludf.DUMMYFUNCTION("""COMPUTED_VALUE"""),10051.0) -> 10051 | G11: =IFERROR(__xludf.DUMMYFUNCTION("""COMPUTED_VALUE"""),"Tahu baso") -> Tahu baso | J11: =IFERROR(__xludf.DUMMYFUNCTION("""COMPUTED_VALUE"""),2.0) -> 2 | K11: =IFERROR(__xludf.DUMMYFUNCTION("""COMPUTED_VALUE"""),50476.0) -> 50476 | L11: =IFERROR(__xludf.DUMMYFUNCTION("""COMPUTED_VALUE"""),0.0) -> 0 | M11: =IFERROR(__xludf.DUMMYFUNCTION("""COMPUTED_VALUE"""),50476.0) -> 50476 | N11: =IFERROR(__xludf.DUMMYFUNCTION("""COMPUTED_VALUE"""),0.0) -> 0 | O11: =IFERROR(__xludf.DUMMYFUNCTION("""COMPUTED_VALUE"""),50476.0) -> 50476 | P11: =IFERROR(__xludf.DUMMYFUNCTION("""COMPUTED_VALUE"""),2524.0) -> 2524 | Q11: =IFERROR(__xludf.DUMMYFUNCTION("""COMPUTED_VALUE"""),"Dine In") -> Dine In | R11: =IFERROR(__xludf.DUMMYFUNCTION("""COMPUTED_VALUE"""),"Kedai") -> Kedai | S11: =IFERROR(__xludf.DUMMYFUNCTION("""COMPUTED_VALUE"""),"Temu Roti") -> Temu Roti | T11: =IFERROR(__xludf.DUMMYFUNCTION("""COMPUTED_VALUE"""),"Owner") -> Owner | X11: =IFERROR(__xludf.DUMMYFUNCTION("""COMPUTED_VALUE"""),"Closed") -> Closed
A12: 29/09/2024 18:36,2-9565,Sale,Minuman,10122,Rempah Madu Panas,,,1.000,21905.00,0.00,21905.00,0.00,21905.00,1095.00,Dine In,Kedai,Temu Roti,Owner,,,,Closed | B12: =IFERROR(__xludf.DUMMYFUNCTION("SPLIT(A12,"","",0,0)"),45564.775) -> 45564.775 | C12: =IFERROR(__xludf.DUMMYFUNCTION("""COMPUTED_VALUE"""),2799617.0) -> 2799617 | D12: =IFERROR(__xludf.DUMMYFUNCTION("""COMPUTED_VALUE"""),"Sale") -> Sale | E12: =IFERROR(__xludf.DUMMYFUNCTION("""COMPUTED_VALUE"""),"Minuman") -> Minuman | F12: =IFERROR(__xludf.DUMMYFUNCTION("""COMPUTED_VALUE"""),10122.0) -> 10122 | G12: =IFERROR(__xludf.DUMMYFUNCTION("""COMPUTED_VALUE"""),"Rempah Madu Panas") -> Rempah Madu Panas | J12: =IFERROR(__xludf.DUMMYFUNCTION("""COMPUTED_VALUE"""),1.0) -> 1 | K12: =IFERROR(__xludf.DUMMYFUNCTION("""COMPUTED_VALUE"""),21905.0) -> 21905 | L12: =IFERROR(__xludf.DUMMYFUNCTION("""COMPUTED_VALUE"""),0.0) -> 0 | M12: =IFERROR(__xludf.DUMMYFUNCTION("""COMPUTED_VALUE"""),21905.0) -> 21905 | N12: =IFERROR(__xludf.DUMMYFUNCTION("""COMPUTED_VALUE"""),0.0) -> 0 | O12: =IFERROR(__xludf.DUMMYFUNCTION("""COMPUTED_VALUE"""),21905.0) -> 21905 | P12: =IFERROR(__xludf.DUMMYFUNCTION("""COMPUTED_VALUE"""),1095.0) -> 1095 | Q12: =IFERROR(__xludf.DUMMYFUNCTION("""COMPUTED_VALUE"""),"Dine In") -> Dine In | R12: =IFERROR(__xludf.DUMMYFUNCTION("""COMPUTED_VALUE"""),"Kedai") -> Kedai | S12: =IFERROR(__xludf.DUMMYFUNCTION("""COMPUTED_VALUE"""),"Temu Roti") -> Temu Roti | T12: =IFERROR(__xludf.DUMMYFUNCTION("""COMPUTED_VALUE"""),"Owner") -> Owner | X12: =IFERROR(__xludf.DUMMYFUNCTION("""COMPUTED_VALUE"""),"Closed") -> Closed
A13: 29/09/2024 18:32,2-9564,Sale,Hidangan Utama,10104,Chicken Claypot Rice,,,1.000,34762.00,0.00,34762.00,0.00,34762.00,1738.00,Dine In,Kedai,Temu Roti,Owner,,,,Closed | B13: =IFERROR(__xludf.DUMMYFUNCTION("SPLIT(A13,"","",0,0)"),45564.77222222222) -> 45564.772 | C13: =IFERROR(__xludf.DUMMYFUNCTION("""COMPUTED_VALUE"""),2799251.0) -> 2799251 | D13: =IFERROR(__xludf.DUMMYFUNCTION("""COMPUTED_VALUE"""),"Sale") -> Sale | E13: =IFERROR(__xludf.DUMMYFUNCTION("""COMPUTED_VALUE"""),"Hidangan Utama") -> Hidangan Utama | F13: =IFERROR(__xludf.DUMMYFUNCTION("""COMPUTED_VALUE"""),10104.0) -> 10104 | G13: =IFERROR(__xludf.DUMMYFUNCTION("""COMPUTED_VALUE"""),"Chicken Claypot Rice") -> Chicken Claypot Rice | J13: =IFERROR(__xludf.DUMMYFUNCTION("""COMPUTED_VALUE"""),1.0) -> 1 | K13: =IFERROR(__xludf.DUMMYFUNCTION("""COMPUTED_VALUE"""),34762.0) -> 34762 | L13: =IFERROR(__xludf.DUMMYFUNCTION("""COMPUTED_VALUE"""),0.0) -> 0 | M13: =IFERROR(__xludf.DUMMYFUNCTION("""COMPUTED_VALUE"""),34762.0) -> 34762 | N13: =IFERROR(__xludf.DUMMYFUNCTION("""COMPUTED_VALUE"""),0.0) -> 0 | O13: =IFERROR(__xludf.DUMMYFUNCTION("""COMPUTED_VALUE"""),34762.0) -> 34762 | P13: =IFERROR(__xludf.DUMMYFUNCTION("""COMPUTED_VALUE"""),1738.0) -> 1738 | Q13: =IFERROR(__xludf.DUMMYFUNCTION("""COMPUTED_VALUE"""),"Dine In") -> Dine In | R13: =IFERROR(__xludf.DUMMYFUNCTION("""COMPUTED_VALUE"""),"Kedai") -> Kedai | S13: =IFERROR(__xludf.DUMMYFUNCTION("""COMPUTED_VALUE"""),"Temu Roti") -> Temu Roti | T13: =IFERROR(__xludf.DUMMYFUNCTION("""COMPUTED_VALUE"""),"Owner") -> Owner | X13: =IFERROR(__xludf.DUMMYFUNCTION("""COMPUTED_VALUE"""),"Closed") -> Closed
A14: 29/09/2024 18:32,2-9564,Sale,Minuman,10119,Teh Tawar Dingin,,,1.000,7143.00,0.00,7143.00,0.00,7143.00,357.00,Dine In,Kedai,Temu Roti,Owner,,,,Closed | B14: =IFERROR(__xludf.DUMMYFUNCTION("SPLIT(A14,"","",0,0)"),45564.77222222222) -> 45564.772 | C14: =IFERROR(__xludf.DUMMYFUNCTION("""COMPUTED_VALUE"""),2799251.0) -> 2799251 | D14: =IFERROR(__xludf.DUMMYFUNCTION("""COMPUTED_VALUE"""),"Sale") -> Sale | E14: =IFERROR(__xludf.DUMMYFUNCTION("""COMPUTED_VALUE"""),"Minuman") -> Minuman | F14: =IFERROR(__xludf.DUMMYFUNCTION("""COMPUTED_VALUE"""),10119.0) -> 10119 | G14: =IFERROR(__xludf.DUMMYFUNCTION("""COMPUTED_VALUE"""),"Teh Tawar Dingin") -> Teh Tawar Dingin | J14: =IFERROR(__xludf.DUMMYFUNCTION("""COMPUTED_VALUE"""),1.0) -> 1 | K14: =IFERROR(__xludf.DUMMYFUNCTION("""COMPUTED_VALUE"""),7143.0) -> 7143 | L14: =IFERROR(__xludf.DUMMYFUNCTION("""COMPUTED_VALUE"""),0.0) -> 0 | M14: =IFERROR(__xludf.DUMMYFUNCTION("""COMPUTED_VALUE"""),7143.0) -> 7143 | N14: =IFERROR(__xludf.DUMMYFUNCTION("""COMPUTED_VALUE"""),0.0) -> 0 | O14: =IFERROR(__xludf.DUMMYFUNCTION("""COMPUTED_VALUE"""),7143.0) -> 7143 | P14: =IFERROR(__xludf.DUMMYFUNCTION("""COMPUTED_VALUE"""),357.0) -> 357 | Q14: =IFERROR(__xludf.DUMMYFUNCTION("""COMPUTED_VALUE"""),"Dine In") -> Dine In | R14: =IFERROR(__xludf.DUMMYFUNCTION("""COMPUTED_VALUE"""),"Kedai") -> Kedai | S14: =IFERROR(__xludf.DUMMYFUNCTION("""COMPUTED_VALUE"""),"Temu Roti") -> Temu Roti | T14: =IFERROR(__xludf.DUMMYFUNCTION("""COMPUTED_VALUE"""),"Owner") -> Owner | X14: =IFERROR(__xludf.DUMMYFUNCTION("""COMPUTED_VALUE"""),"Closed") -> Closed
A15: 29/09/2024 18:16,2-9563,Sale,Minuman,10026,Es Kopi Lemon,,,1.000,21905.00,0.00,21905.00,0.00,21905.00,1095.00,Dine In,Kedai,Temu Roti,Owner,,,,Closed | B15: =IFERROR(__xludf.DUMMYFUNCTION("SPLIT(A15,"","",0,0)"),45564.76111111111) -> 45564.761 | C15: =IFERROR(__xludf.DUMMYFUNCTION("""COMPUTED_VALUE"""),2798886.0) -> 2798886 | D15: =IFERROR(__xludf.DUMMYFUNCTION("""COMPUTED_VALUE"""),"Sale") -> Sale | E15: =IFERROR(__xludf.DUMMYFUNCTION("""COMPUTED_VALUE"""),"Minuman") -> Minuman | F15: =IFERROR(__xludf.DUMMYFUNCTION("""COMPUTED_VALUE"""),10026.0) -> 10026 | G15: =IFERROR(__xludf.DUMMYFUNCTION("""COMPUTED_VALUE"""),"Es Kopi Lemon") -> Es Kopi Lemon | J15: =IFERROR(__xludf.DUMMYFUNCTION("""COMPUTED_VALUE"""),1.0) -> 1 | K15: =IFERROR(__xludf.DUMMYFUNCTION("""COMPUTED_VALUE"""),21905.0) -> 21905 | L15: =IFERROR(__xludf.DUMMYFUNCTION("""COMPUTED_VALUE"""),0.0) -> 0 | M15: =IFERROR(__xludf.DUMMYFUNCTION("""COMPUTED_VALUE"""),21905.0) -> 21905 | N15: =IFERROR(__xludf.DUMMYFUNCTION("""COMPUTED_VALUE"""),0.0) -> 0 | O15: =IFERROR(__xludf.DUMMYFUNCTION("""COMPUTED_VALUE"""),21905.0) -> 21905 | P15: =IFERROR(__xludf.DUMMYFUNCTION("""COMPUTED_VALUE"""),1095.0) -> 1095 | Q15: =IFERROR(__xludf.DUMMYFUNCTION("""COMPUTED_VALUE"""),"Dine In") -> Dine In | R15: =IFERROR(__xludf.DUMMYFUNCTION("""COMPUTED_VALUE"""),"Kedai") -> Kedai | S15: =IFERROR(__xludf.DUMMYFUNCTION("""COMPUTED_VALUE"""),"Temu Roti") -> Temu Roti | T15: =IFERROR(__xludf.DUMMYFUNCTION("""COMPUTED_VALUE"""),"Owner") -> Owner | X15: =IFERROR(__xludf.DUMMYFUNCTION("""COMPUTED_VALUE"""),"Closed") -> Closed
A16: 29/09/2024 18:16,2-9563,Sale,Minuman,10107,Korean Mango Fresh Milk,,,1.000,26667.00,0.00,26667.00,0.00,26667.00,1334.00,Dine In,Kedai,Temu Roti,Owner,,,,Closed | B16: =IFERROR(__xludf.DUMMYFUNCTION("SPLIT(A16,"","",0,0)"),45564.76111111111) -> 45564.761 | C16: =IFERROR(__xludf.DUMMYFUNCTION("""COMPUTED_VALUE"""),2798886.0) -> 2798886 | D16: =IFERROR(__xludf.DUMMYFUNCTION("""COMPUTED_VALUE"""),"Sale") -> Sale | E16: =IFERROR(__xludf.DUMMYFUNCTION("""COMPUTED_VALUE"""),"Minuman") -> Minuman | F16: =IFERROR(__xludf.DUMMYFUNCTION("""COMPUTED_VALUE"""),10107.0) -> 10107 | G16: =IFERROR(__xludf.DUMMYFUNCTION("""COMPUTED_VALUE"""),"Korean Mango Fresh Milk") -> Korean Mango Fresh Milk | J16: =IFERROR(__xludf.DUMMYFUNCTION("""COMPUTED_VALUE"""),1.0) -> 1 | K16: =IFERROR(__xludf.DUMMYFUNCTION("""COMPUTED_VALUE"""),26667.0) -> 26667 | L16: =IFERROR(__xludf.DUMMYFUNCTION("""COMPUTED_VALUE"""),0.0) -> 0 | M16: =IFERROR(__xludf.DUMMYFUNCTION("""COMPUTED_VALUE"""),26667.0) -> 26667 | N16: =IFERROR(__xludf.DUMMYFUNCTION("""COMPUTED_VALUE"""),0.0) -> 0 | O16: =IFERROR(__xludf.DUMMYFUNCTION("""COMPUTED_VALUE"""),26667.0) -> 26667 | P16: =IFERROR(__xludf.DUMMYFUNCTION("""COMPUTED_VALUE"""),1334.0) -> 1334 | Q16: =IFERROR(__xludf.DUMMYFUNCTION("""COMPUTED_VALUE"""),"Dine In") -> Dine In | R16: =IFERROR(__xludf.DUMMYFUNCTION("""COMPUTED_VALUE"""),"Kedai") -> Kedai | S16: =IFERROR(__xludf.DUMMYFUNCTION("""COMPUTED_VALUE"""),"Temu Roti") -> Temu Roti | T16: =IFERROR(__xludf.DUMMYFUNCTION("""COMPUTED_VALUE"""),"Owner") -> Owner | X16: =IFERROR(__xludf.DUMMYFUNCTION("""COMPUTED_VALUE"""),"Closed") -> Closed
A17: 29/09/2024 18:12,2-9562,Sale,Minuman,10056,Susu murni moca,,,1.000,19524.00,0.00,19524.00,0.00,19524.00,976.00,Dine In,Kedai,Temu Roti,Owner,,,,Closed | B17: =IFERROR(__xludf.DUMMYFUNCTION("SPLIT(A17,"","",0,0)"),45564.75833333333) -> 45564.758 | C17: =IFERROR(__xludf.DUMMYFUNCTION("""COMPUTED_VALUE"""),2798521.0) -> 2798521 | D17: =IFERROR(__xludf.DUMMYFUNCTION("""COMPUTED_VALUE"""),"Sale") -> Sale | E17: =IFERROR(__xludf.DUMMYFUNCTION("""COMPUTED_VALUE"""),"Minuman") -> Minuman | F17: =IFERROR(__xludf.DUMMYFUNCTION("""COMPUTED_VALUE"""),10056.0) -> 10056 | G17: =IFERROR(__xludf.DUMMYFUNCTION("""COMPUTED_VALUE"""),"Susu murni moca") -> Susu murni moca | J17: =IFERROR(__xludf.DUMMYFUNCTION("""COMPUTED_VALUE"""),1.0) -> 1 | K17: =IFERROR(__xludf.DUMMYFUNCTION("""COMPUTED_VALUE"""),19524.0) -> 19524 | L17: =IFERROR(__xludf.DUMMYFUNCTION("""COMPUTED_VALUE"""),0.0) -> 0 | M17: =IFERROR(__xludf.DUMMYFUNCTION("""COMPUTED_VALUE"""),19524.0) -> 19524 | N17: =IFERROR(__xludf.DUMMYFUNCTION("""COMPUTED_VALUE"""),0.0) -> 0 | O17: =IFERROR(__xludf.DUMMYFUNCTION("""COMPUTED_VALUE"""),19524.0) -> 19524 | P17: =IFERROR(__xludf.DUMMYFUNCTION("""COMPUTED_VALUE"""),976.0) -> 976 | Q17: =IFERROR(__xludf.DUMMYFUNCTION("""COMPUTED_VALUE"""),"Dine In") -> Dine In | R17: =IFERROR(__xludf.DUMMYFUNCTION("""COMPUTED_VALUE"""),"Kedai") -> Kedai | S17: =IFERROR(__xludf.DUMMYFUNCTION("""COMPUTED_VALUE"""),"Temu Roti") -> Temu Roti | T17: =IFERROR(__xludf.DUMMYFUNCTION("""COMPUTED_VALUE"""),"Owner") -> Owner | X17: =IFERROR(__xludf.DUMMYFUNCTION("""COMPUTED_VALUE"""),"Closed") -> Closed
A18: 29/09/2024 17:59,2-9561,Sale,Kudapan,10009,Jamur Enoki Krispi,,,1.000,26667.00,0.00,26667.00,0.00,26667.00,1333.00,Dine In,Kedai,Temu Roti,Owner,,,,Closed | B18: =IFERROR(__xludf.DUMMYFUNCTION("SPLIT(A18,"","",0,0)"),45564.74930555555) -> 45564.749 | C18: =IFERROR(__xludf.DUMMYFUNCTION("""COMPUTED_VALUE"""),2798156.0) -> 2798156 | D18: =IFERROR(__xludf.DUMMYFUNCTION("""COMPUTED_VALUE"""),"Sale") -> Sale | E18: =IFERROR(__xludf.DUMMYFUNCTION("""COMPUTED_VALUE"""),"Kudapan") -> Kudapan | F18: =IFERROR(__xludf.DUMMYFUNCTION("""COMPUTED_VALUE"""),10009.0) -> 10009 | G18: =IFERROR(__xludf.DUMMYFUNCTION("""COMPUTED_VALUE"""),"Jamur Enoki Krispi") -> Jamur Enoki Krispi | J18: =IFERROR(__xludf.DUMMYFUNCTION("""COMPUTED_VALUE"""),1.0) -> 1 | K18: =IFERROR(__xludf.DUMMYFUNCTION("""COMPUTED_VALUE"""),26667.0) -> 26667 | L18: =IFERROR(__xludf.DUMMYFUNCTION("""COMPUTED_VALUE"""),0.0) -> 0 | M18: =IFERROR(__xludf.DUMMYFUNCTION("""COMPUTED_VALUE"""),26667.0) -> 26667 | N18: =IFERROR(__xludf.DUMMYFUNCTION("""COMPUTED_VALUE"""),0.0) -> 0 | O18: =IFERROR(__xludf.DUMMYFUNCTION("""COMPUTED_VALUE"""),26667.0) -> 26667 | P18: =IFERROR(__xludf.DUMMYFUNCTION("""COMPUTED_VALUE"""),1333.0) -> 1333 | Q18: =IFERROR(__xludf.DUMMYFUNCTION("""COMPUTED_VALUE"""),"Dine In") -> Dine In | R18: =IFERROR(__xludf.DUMMYFUNCTION("""COMPUTED_VALUE"""),"Kedai") -> Kedai | S18: =IFERROR(__xludf.DUMMYFUNCTION("""COMPUTED_VALUE"""),"Temu Roti") -> Temu Roti | T18: =IFERROR(__xludf.DUMMYFUNCTION("""COMPUTED_VALUE"""),"Owner") -> Owner | X18: =IFERROR(__xludf.DUMMYFUNCTION("""COMPUTED_VALUE"""),"Closed") -> Closed
A19: 29/09/2024 17:53,2-9560,Sale,Hidangan Utama,10104,Chicken Claypot Rice,,,1.000,34762.00,0.00,34762.00,0.00,34762.00,1738.00,Dine In,Kedai,Temu Roti,Owner,,,,Closed | B19: =IFERROR(__xludf.DUMMYFUNCTION("SPLIT(A19,"","",0,0)"),45564.74513888889) -> 45564.745 | C19: =IFERROR(__xludf.DUMMYFUNCTION("""COMPUTED_VALUE"""),2797790.0) -> 2797790 | D19: =IFERROR(__xludf.DUMMYFUNCTION("""COMPUTED_VALUE"""),"Sale") -> Sale | E19: =IFERROR(__xludf.DUMMYFUNCTION("""COMPUTED_VALUE"""),"Hidangan Utama") -> Hidangan Utama | F19: =IFERROR(__xludf.DUMMYFUNCTION("""COMPUTED_VALUE"""),10104.0) -> 10104 | G19: =IFERROR(__xludf.DUMMYFUNCTION("""COMPUTED_VALUE"""),"Chicken Claypot Rice") -> Chicken Claypot Rice | J19: =IFERROR(__xludf.DUMMYFUNCTION("""COMPUTED_VALUE"""),1.0) -> 1 | K19: =IFERROR(__xludf.DUMMYFUNCTION("""COMPUTED_VALUE"""),34762.0) -> 34762 | L19: =IFERROR(__xludf.DUMMYFUNCTION("""COMPUTED_VALUE"""),0.0) -> 0 | M19: =IFERROR(__xludf.DUMMYFUNCTION("""COMPUTED_VALUE"""),34762.0) -> 34762 | N19: =IFERROR(__xludf.DUMMYFUNCTION("""COMPUTED_VALUE"""),0.0) -> 0 | O19: =IFERROR(__xludf.DUMMYFUNCTION("""COMPUTED_VALUE"""),34762.0) -> 34762 | P19: =IFERROR(__xludf.DUMMYFUNCTION("""COMPUTED_VALUE"""),1738.0) -> 1738 | Q19: =IFERROR(__xludf.DUMMYFUNCTION("""COMPUTED_VALUE"""),"Dine In") -> Dine In | R19: =IFERROR(__xludf.DUMMYFUNCTION("""COMPUTED_VALUE"""),"Kedai") -> Kedai | S19: =IFERROR(__xludf.DUMMYFUNCTION("""COMPUTED_VALUE"""),"Temu Roti") -> Temu Roti | T19: =IFERROR(__xludf.DUMMYFUNCTION("""COMPUTED_VALUE"""),"Owner") -> Owner | X19: =IFERROR(__xludf.DUMMYFUNCTION("""COMPUTED_VALUE"""),"Closed") -> Closed
A20: 29/09/2024 17:44,2-9559,Sale,Kudapan,10015,Tahu Lada Garam,,,1.000,25238.00,0.00,25238.00,0.00,25238.00,1262.00,Dine In,Kedai,Temu Roti,Owner,,,,Closed | B20: =IFERROR(__xludf.DUMMYFUNCTION("SPLIT(A20,"","",0,0)"),45564.73888888889) -> 45564.739 | C20: =IFERROR(__xludf.DUMMYFUNCTION("""COMPUTED_VALUE"""),2797425.0) -> 2797425 | D20: =IFERROR(__xludf.DUMMYFUNCTION("""COMPUTED_VALUE"""),"Sale") -> Sale | E20: =IFERROR(__xludf.DUMMYFUNCTION("""COMPUTED_VALUE"""),"Kudapan") -> Kudapan | F20: =IFERROR(__xludf.DUMMYFUNCTION("""COMPUTED_VALUE"""),10015.0) -> 10015 | G20: =IFERROR(__xludf.DUMMYFUNCTION("""COMPUTED_VALUE"""),"Tahu Lada Garam") -> Tahu Lada Garam | J20: =IFERROR(__xludf.DUMMYFUNCTION("""COMPUTED_VALUE"""),1.0) -> 1 | K20: =IFERROR(__xludf.DUMMYFUNCTION("""COMPUTED_VALUE"""),25238.0) -> 25238 | L20: =IFERROR(__xludf.DUMMYFUNCTION("""COMPUTED_VALUE"""),0.0) -> 0 | M20: =IFERROR(__xludf.DUMMYFUNCTION("""COMPUTED_VALUE"""),25238.0) -> 25238 | N20: =IFERROR(__xludf.DUMMYFUNCTION("""COMPUTED_VALUE"""),0.0) -> 0 | O20: =IFERROR(__xludf.DUMMYFUNCTION("""COMPUTED_VALUE"""),25238.0) -> 25238 | P20: =IFERROR(__xludf.DUMMYFUNCTION("""COMPUTED_VALUE"""),1262.0) -> 1262 | Q20: =IFERROR(__xludf.DUMMYFUNCTION("""COMPUTED_VALUE"""),"Dine In") -> Dine In | R20: =IFERROR(__xludf.DUMMYFUNCTION("""COMPUTED_VALUE"""),"Kedai") -> Kedai | S20: =IFERROR(__xludf.DUMMYFUNCTION("""COMPUTED_VALUE"""),"Temu Roti") -> Temu Roti | T20: =IFERROR(__xludf.DUMMYFUNCTION("""COMPUTED_VALUE"""),"Owner") -> Owner | X20: =IFERROR(__xludf.DUMMYFUNCTION("""COMPUTED_VALUE"""),"Closed") -> Closed
A21: 29/09/2024 17:40,2-9558,Sale,Minuman,10128,Es Kopi Susu,,,1.000,23333.00,0.00,23333.00,0.00,23333.00,1167.00,Dine In,Kedai,Temu Roti,Owner,,,,Closed | B21: =IFERROR(__xludf.DUMMYFUNCTION("SPLIT(A21,"","",0,0)"),45564.73611111111) -> 45564.736 | C21: =IFERROR(__xludf.DUMMYFUNCTION("""COMPUTED_VALUE"""),2797060.0) -> 2797060 | D21: =IFERROR(__xludf.DUMMYFUNCTION("""COMPUTED_VALUE"""),"Sale") -> Sale | E21: =IFERROR(__xludf.DUMMYFUNCTION("""COMPUTED_VALUE"""),"Minuman") -> Minuman | F21: =IFERROR(__xludf.DUMMYFUNCTION("""COMPUTED_VALUE"""),10128.0) -> 10128 | G21: =IFERROR(__xludf.DUMMYFUNCTION("""COMPUTED_VALUE"""),"Es Kopi Susu") -> Es Kopi Susu | J21: =IFERROR(__xludf.DUMMYFUNCTION("""COMPUTED_VALUE"""),1.0) -> 1 | K21: =IFERROR(__xludf.DUMMYFUNCTION("""COMPUTED_VALUE"""),23333.0) -> 23333 | L21: =IFERROR(__xludf.DUMMYFUNCTION("""COMPUTED_VALUE"""),0.0) -> 0 | M21: =IFERROR(__xludf.DUMMYFUNCTION("""COMPUTED_VALUE"""),23333.0) -> 23333 | N21: =IFERROR(__xludf.DUMMYFUNCTION("""COMPUTED_VALUE"""),0.0) -> 0 | O21: =IFERROR(__xludf.DUMMYFUNCTION("""COMPUTED_VALUE"""),23333.0) -> 23333 | P21: =IFERROR(__xludf.DUMMYFUNCTION("""COMPUTED_VALUE"""),1167.0) -> 1167 | Q21: =IFERROR(__xludf.DUMMYFUNCTION("""COMPUTED_VALUE"""),"Dine In") -> Dine In | R21: =IFERROR(__xludf.DUMMYFUNCTION("""COMPUTED_VALUE"""),"Kedai") -> Kedai | S21: =IFERROR(__xludf.DUMMYFUNCTION("""COMPUTED_VALUE"""),"Temu Roti") -> Temu Roti | T21: =IFERROR(__xludf.DUMMYFUNCTION("""COMPUTED_VALUE"""),"Owner") -> Owner | X21: =IFERROR(__xludf.DUMMYFUNCTION("""COMPUTED_VALUE"""),"Closed") -> Closed
A22: 29/09/2024 17:40,2-9558,Sale,Roti,10000,Roti Bawang Saus Keju,,,1.000,29524.00,0.00,29524.00,0.00,29524.00,1476.00,Dine In,Kedai,Temu Roti,Owner,,,,Closed | B22: =IFERROR(__xludf.DUMMYFUNCTION("SPLIT(A22,"","",0,0)"),45564.73611111111) -> 45564.736 | C22: =IFERROR(__xludf.DUMMYFUNCTION("""COMPUTED_VALUE"""),2797060.0) -> 2797060 | D22: =IFERROR(__xludf.DUMMYFUNCTION("""COMPUTED_VALUE"""),"Sale") -> Sale | E22: =IFERROR(__xludf.DUMMYFUNCTION("""COMPUTED_VALUE"""),"Roti") -> Roti | F22: =IFERROR(__xludf.DUMMYFUNCTION("""COMPUTED_VALUE"""),10000.0) -> 10000 | G22: =IFERROR(__xludf.DUMMYFUNCTION("""COMPUTED_VALUE"""),"Roti Bawang Saus Keju") -> Roti Bawang Saus Keju | J22: =IFERROR(__xludf.DUMMYFUNCTION("""COMPUTED_VALUE"""),1.0) -> 1 | K22: =IFERROR(__xludf.DUMMYFUNCTION("""COMPUTED_VALUE"""),29524.0) -> 29524 | L22: =IFERROR(__xludf.DUMMYFUNCTION("""COMPUTED_VALUE"""),0.0) -> 0 | M22: =IFERROR(__xludf.DUMMYFUNCTION("""COMPUTED_VALUE"""),29524.0) -> 29524 | N22: =IFERROR(__xludf.DUMMYFUNCTION("""COMPUTED_VALUE"""),0.0) -> 0 | O22: =IFERROR(__xludf.DUMMYFUNCTION("""COMPUTED_VALUE"""),29524.0) -> 29524 | P22: =IFERROR(__xludf.DUMMYFUNCTION("""COMPUTED_VALUE"""),1476.0) -> 1476 | Q22: =IFERROR(__xludf.DUMMYFUNCTION("""COMPUTED_VALUE"""),"Dine In") -> Dine In | R22: =IFERROR(__xludf.DUMMYFUNCTION("""COMPUTED_VALUE"""),"Kedai") -> Kedai | S22: =IFERROR(__xludf.DUMMYFUNCTION("""COMPUTED_VALUE"""),"Temu Roti") -> Temu Roti | T22: =IFERROR(__xludf.DUMMYFUNCTION("""COMPUTED_VALUE"""),"Owner") -> Owner | X22: =IFERROR(__xludf.DUMMYFUNCTION("""COMPUTED_VALUE"""),"Closed") -> Closed
A23: 29/09/2024 17:40,2-9558,Sale,Minuman,10117,Teh Manis Dingin,,,1.000,14286.00,0.00,14286.00,0.00,14286.00,714.00,Dine In,Kedai,Temu Roti,Owner,,,,Closed | B23: =IFERROR(__xludf.DUMMYFUNCTION("SPLIT(A23,"","",0,0)"),45564.73611111111) -> 45564.736 | C23: =IFERROR(__xludf.DUMMYFUNCTION("""COMPUTED_VALUE"""),2797060.0) -> 2797060 | D23: =IFERROR(__xludf.DUMMYFUNCTION("""COMPUTED_VALUE"""),"Sale") -> Sale | E23: =IFERROR(__xludf.DUMMYFUNCTION("""COMPUTED_VALUE"""),"Minuman") -> Minuman | F23: =IFERROR(__xludf.DUMMYFUNCTION("""COMPUTED_VALUE"""),10117.0) -> 10117 | G23: =IFERROR(__xludf.DUMMYFUNCTION("""COMPUTED_VALUE"""),"Teh Manis Dingin") -> Teh Manis Dingin | J23: =IFERROR(__xludf.DUMMYFUNCTION("""COMPUTED_VALUE"""),1.0) -> 1 | K23: =IFERROR(__xludf.DUMMYFUNCTION("""COMPUTED_VALUE"""),14286.0) -> 14286 | L23: =IFERROR(__xludf.DUMMYFUNCTION("""COMPUTED_VALUE"""),0.0) -> 0 | M23: =IFERROR(__xludf.DUMMYFUNCTION("""COMPUTED_VALUE"""),14286.0) -> 14286 | N23: =IFERROR(__xludf.DUMMYFUNCTION("""COMPUTED_VALUE"""),0.0) -> 0 | O23: =IFERROR(__xludf.DUMMYFUNCTION("""COMPUTED_VALUE"""),14286.0) -> 14286 | P23: =IFERROR(__xludf.DUMMYFUNCTION("""COMPUTED_VALUE"""),714.0) -> 714 | Q23: =IFERROR(__xludf.DUMMYFUNCTION("""COMPUTED_VALUE"""),"Dine In") -> Dine In | R23: =IFERROR(__xludf.DUMMYFUNCTION("""COMPUTED_VALUE"""),"Kedai") -> Kedai | S23: =IFERROR(__xludf.DUMMYFUNCTION("""COMPUTED_VALUE"""),"Temu Roti") -> Temu Roti | T23: =IFERROR(__xludf.DUMMYFUNCTION("""COMPUTED_VALUE"""),"Owner") -> Owner | X23: =IFERROR(__xludf.DUMMYFUNCTION("""COMPUTED_VALUE"""),"Closed") -> Closed
A24: 29/09/2024 17:34,2-9557,Sale,Roti,10000,Roti Bawang Saus Keju,,,1.000,29524.00,0.00,29524.00,0.00,29524.00,1476.00,Dine In,Kedai,Temu Roti,Owner,,,,Closed | B24: =IFERROR(__xludf.DUMMYFUNCTION("SPLIT(A24,"","",0,0)"),45564.731944444444) -> 45564.732 | C24: =IFERROR(__xludf.DUMMYFUNCTION("""COMPUTED_VALUE"""),2796695.0) -> 2796695 | D24: =IFERROR(__xludf.DUMMYFUNCTION("""COMPUTED_VALUE"""),"Sale") -> Sale | E24: =IFERROR(__xludf.DUMMYFUNCTION("""COMPUTED_VALUE"""),"Roti") -> Roti | F24: =IFERROR(__xludf.DUMMYFUNCTION("""COMPUTED_VALUE"""),10000.0) -> 10000 | G24: =IFERROR(__xludf.DUMMYFUNCTION("""COMPUTED_VALUE"""),"Roti Bawang Saus Keju") -> Roti Bawang Saus Keju | J24: =IFERROR(__xludf.DUMMYFUNCTION("""COMPUTED_VALUE"""),1.0) -> 1 | K24: =IFERROR(__xludf.DUMMYFUNCTION("""COMPUTED_VALUE"""),29524.0) -> 29524 | L24: =IFERROR(__xludf.DUMMYFUNCTION("""COMPUTED_VALUE"""),0.0) -> 0 | M24: =IFERROR(__xludf.DUMMYFUNCTION("""COMPUTED_VALUE"""),29524.0) -> 29524 | N24: =IFERROR(__xludf.DUMMYFUNCTION("""COMPUTED_VALUE"""),0.0) -> 0 | O24: =IFERROR(__xludf.DUMMYFUNCTION("""COMPUTED_VALUE"""),29524.0) -> 29524 | P24: =IFERROR(__xludf.DUMMYFUNCTION("""COMPUTED_VALUE"""),1476.0) -> 1476 | Q24: =IFERROR(__xludf.DUMMYFUNCTION("""COMPUTED_VALUE"""),"Dine In") -> Dine In | R24: =IFERROR(__xludf.DUMMYFUNCTION("""COMPUTED_VALUE"""),"Kedai") -> Kedai | S24: =IFERROR(__xludf.DUMMYFUNCTION("""COMPUTED_VALUE"""),"Temu Roti") -> Temu Roti | T24: =IFERROR(__xludf.DUMMYFUNCTION("""COMPUTED_VALUE"""),"Owner") -> Owner | X24: =IFERROR(__xludf.DUMMYFUNCTION("""COMPUTED_VALUE"""),"Closed") -> Closed
A25: 29/09/2024 17:34,2-9557,Sale,Minuman,10120,Lemon Tea Panas,,,1.000,19524.00,0.00,19524.00,0.00,19524.00,976.00,Dine In,Kedai,Temu Roti,Owner,,,,Closed | B25: =IFERROR(__xludf.DUMMYFUNCTION("SPLIT(A25,"","",0,0)"),45564.731944444444) -> 45564.732 | C25: =IFERROR(__xludf.DUMMYFUNCTION("""COMPUTED_VALUE"""),2796695.0) -> 2796695 | D25: =IFERROR(__xludf.DUMMYFUNCTION("""COMPUTED_VALUE"""),"Sale") -> Sale | E25: =IFERROR(__xludf.DUMMYFUNCTION("""COMPUTED_VALUE"""),"Minuman") -> Minuman | F25: =IFERROR(__xludf.DUMMYFUNCTION("""COMPUTED_VALUE"""),10120.0) -> 10120 | G25: =IFERROR(__xludf.DUMMYFUNCTION("""COMPUTED_VALUE"""),"Lemon Tea Panas") -> Lemon Tea Panas | J25: =IFERROR(__xludf.DUMMYFUNCTION("""COMPUTED_VALUE"""),1.0) -> 1 | K25: =IFERROR(__xludf.DUMMYFUNCTION("""COMPUTED_VALUE"""),19524.0) -> 19524 | L25: =IFERROR(__xludf.DUMMYFUNCTION("""COMPUTED_VALUE"""),0.0) -> 0 | M25: =IFERROR(__xludf.DUMMYFUNCTION("""COMPUTED_VALUE"""),19524.0) -> 19524 | N25: =IFERROR(__xludf.DUMMYFUNCTION("""COMPUTED_VALUE"""),0.0) -> 0 | O25: =IFERROR(__xludf.DUMMYFUNCTION("""COMPUTED_VALUE"""),19524.0) -> 19524 | P25: =IFERROR(__xludf.DUMMYFUNCTION("""COMPUTED_VALUE"""),976.0) -> 976 | Q25: =IFERROR(__xludf.DUMMYFUNCTION("""COMPUTED_VALUE"""),"Dine In") -> Dine In | R25: =IFERROR(__xludf.DUMMYFUNCTION("""COMPUTED_VALUE"""),"Kedai") -> Kedai | S25: =IFERROR(__xludf.DUMMYFUNCTION("""COMPUTED_VALUE"""),"Temu Roti") -> Temu Roti | T25: =IFERROR(__xludf.DUMMYFUNCTION("""COMPUTED_VALUE"""),"Owner") -> Owner | X25: =IFERROR(__xludf.DUMMYFUNCTION("""COMPUTED_VALUE"""),"Closed") -> Closed
A26: 29/09/2024 17:34,2-9557,Sale,Minuman,10122,Rempah Madu Panas,,,1.000,21905.00,0.00,21905.00,0.00,21905.00,1096.00,Dine In,Kedai,Temu Roti,Owner,,,,Closed | B26: =IFERROR(__xludf.DUMMYFUNCTION("SPLIT(A26,"","",0,0)"),45564.731944444444) -> 45564.732 | C26: =IFERROR(__xludf.DUMMYFUNCTION("""COMPUTED_VALUE"""),2796695.0) -> 2796695 | D26: =IFERROR(__xludf.DUMMYFUNCTION("""COMPUTED_VALUE"""),"Sale") -> Sale | E26: =IFERROR(__xludf.DUMMYFUNCTION("""COMPUTED_VALUE"""),"Minuman") -> Minuman | F26: =IFERROR(__xludf.DUMMYFUNCTION("""COMPUTED_VALUE"""),10122.0) -> 10122 | G26: =IFERROR(__xludf.DUMMYFUNCTION("""COMPUTED_VALUE"""),"Rempah Madu Panas") -> Rempah Madu Panas | J26: =IFERROR(__xludf.DUMMYFUNCTION("""COMPUTED_VALUE"""),1.0) -> 1 | K26: =IFERROR(__xludf.DUMMYFUNCTION("""COMPUTED_VALUE"""),21905.0) -> 21905 | L26: =IFERROR(__xludf.DUMMYFUNCTION("""COMPUTED_VALUE"""),0.0) -> 0 | M26: =IFERROR(__xludf.DUMMYFUNCTION("""COMPUTED_VALUE"""),21905.0) -> 21905 | N26: =IFERROR(__xludf.DUMMYFUNCTION("""COMPUTED_VALUE"""),0.0) -> 0 | O26: =IFERROR(__xludf.DUMMYFUNCTION("""COMPUTED_VALUE"""),21905.0) -> 21905 | P26: =IFERROR(__xludf.DUMMYFUNCTION("""COMPUTED_VALUE"""),1096.0) -> 1096 | Q26: =IFERROR(__xludf.DUMMYFUNCTION("""COMPUTED_VALUE"""),"Dine In") -> Dine In | R26: =IFERROR(__xludf.DUMMYFUNCTION("""COMPUTED_VALUE"""),"Kedai") -> Kedai | S26: =IFERROR(__xludf.DUMMYFUNCTION("""COMPUTED_VALUE"""),"Temu Roti") -> Temu Roti | T26: =IFERROR(__xludf.DUMMYFUNCTION("""COMPUTED_VALUE"""),"Owner") -> Owner | X26: =IFERROR(__xludf.DUMMYFUNCTION("""COMPUTED_VALUE"""),"Closed") -> Closed
A27: 29/09/2024 17:30,2-9556,Sale,Minuman,10128,Es Kopi Susu,,,1.000,23333.00,0.00,23333.00,0.00,23333.00,1167.00,Dine In,Kedai,Temu Roti,Owner,,,,Closed | B27: =IFERROR(__xludf.DUMMYFUNCTION("SPLIT(A27,"","",0,0)"),45564.729166666664) -> 45564.729 | C27: =IFERROR(__xludf.DUMMYFUNCTION("""COMPUTED_VALUE"""),2796329.0) -> 2796329 | D27: =IFERROR(__xludf.DUMMYFUNCTION("""COMPUTED_VALUE"""),"Sale") -> Sale | E27: =IFERROR(__xludf.DUMMYFUNCTION("""COMPUTED_VALUE"""),"Minuman") -> Minuman | F27: =IFERROR(__xludf.DUMMYFUNCTION("""COMPUTED_VALUE"""),10128.0) -> 10128 | G27: =IFERROR(__xludf.DUMMYFUNCTION("""COMPUTED_VALUE"""),"Es Kopi Susu") -> Es Kopi Susu | J27: =IFERROR(__xludf.DUMMYFUNCTION("""COMPUTED_VALUE"""),1.0) -> 1 | K27: =IFERROR(__xludf.DUMMYFUNCTION("""COMPUTED_VALUE"""),23333.0) -> 23333 | L27: =IFERROR(__xludf.DUMMYFUNCTION("""COMPUTED_VALUE"""),0.0) -> 0 | M27: =IFERROR(__xludf.DUMMYFUNCTION("""COMPUTED_VALUE"""),23333.0) -> 23333 | N27: =IFERROR(__xludf.DUMMYFUNCTION("""COMPUTED_VALUE"""),0.0) -> 0 | O27: =IFERROR(__xludf.DUMMYFUNCTION("""COMPUTED_VALUE"""),23333.0) -> 23333 | P27: =IFERROR(__xludf.DUMMYFUNCTION("""COMPUTED_VALUE"""),1167.0) -> 1167 | Q27: =IFERROR(__xludf.DUMMYFUNCTION("""COMPUTED_VALUE"""),"Dine In") -> Dine In | R27: =IFERROR(__xludf.DUMMYFUNCTION("""COMPUTED_VALUE"""),"Kedai") -> Kedai | S27: =IFERROR(__xludf.DUMMYFUNCTION("""COMPUTED_VALUE"""),"Temu Roti") -> Temu Roti | T27: =IFERROR(__xludf.DUMMYFUNCTION("""COMPUTED_VALUE"""),"Owner") -> Owner | X27: =IFERROR(__xludf.DUMMYFUNCTION("""COMPUTED_VALUE"""),"Closed") -> Closed
A28: 29/09/2024 17:30,2-9556,Sale,Roti,10002,Roti Cranberry,,,1.000,18571.00,0.00,18571.00,0.00,18571.00,928.00,Dine In,Kedai,Temu Roti,Owner,,,,Closed | B28: =IFERROR(__xludf.DUMMYFUNCTION("SPLIT(A28,"","",0,0)"),45564.729166666664) -> 45564.729 | C28: =IFERROR(__xludf.DUMMYFUNCTION("""COMPUTED_VALUE"""),2796329.0) -> 2796329 | D28: =IFERROR(__xludf.DUMMYFUNCTION("""COMPUTED_VALUE"""),"Sale") -> Sale | E28: =IFERROR(__xludf.DUMMYFUNCTION("""COMPUTED_VALUE"""),"Roti") -> Roti | F28: =IFERROR(__xludf.DUMMYFUNCTION("""COMPUTED_VALUE"""),10002.0) -> 10002 | G28: =IFERROR(__xludf.DUMMYFUNCTION("""COMPUTED_VALUE"""),"Roti Cranberry") -> Roti Cranberry | J28: =IFERROR(__xludf.DUMMYFUNCTION("""COMPUTED_VALUE"""),1.0) -> 1 | K28: =IFERROR(__xludf.DUMMYFUNCTION("""COMPUTED_VALUE"""),18571.0) -> 18571 | L28: =IFERROR(__xludf.DUMMYFUNCTION("""COMPUTED_VALUE"""),0.0) -> 0 | M28: =IFERROR(__xludf.DUMMYFUNCTION("""COMPUTED_VALUE"""),18571.0) -> 18571 | N28: =IFERROR(__xludf.DUMMYFUNCTION("""COMPUTED_VALUE"""),0.0) -> 0 | O28: =IFERROR(__xludf.DUMMYFUNCTION("""COMPUTED_VALUE"""),18571.0) -> 18571 | P28: =IFERROR(__xludf.DUMMYFUNCTION("""COMPUTED_VALUE"""),928.0) -> 928 | Q28: =IFERROR(__xludf.DUMMYFUNCTION("""COMPUTED_VALUE"""),"Dine In") -> Dine In | R28: =IFERROR(__xludf.DUMMYFUNCTION("""COMPUTED_VALUE"""),"Kedai") -> Kedai | S28: =IFERROR(__xludf.DUMMYFUNCTION("""COMPUTED_VALUE"""),"Temu Roti") -> Temu Roti | T28: =IFERROR(__xludf.DUMMYFUNCTION("""COMPUTED_VALUE"""),"Owner") -> Owner | X28: =IFERROR(__xludf.DUMMYFUNCTION("""COMPUTED_VALUE"""),"Closed") -> Closed
A29: 29/09/2024 17:15,2-9555,Sale,Roti,10000,Roti Bawang Saus Keju,,,1.000,29524.00,0.00,29524.00,0.00,29524.00,1476.00,Dine In,Kedai,Temu Roti,Owner,,,,Closed | B29: =IFERROR(__xludf.DUMMYFUNCTION("SPLIT(A29,"","",0,0)"),45564.71875) -> 45564.719 | C29: =IFERROR(__xludf.DUMMYFUNCTION("""COMPUTED_VALUE"""),2795964.0) -> 2795964 | D29: =IFERROR(__xludf.DUMMYFUNCTION("""COMPUTED_VALUE"""),"Sale") -> Sale | E29: =IFERROR(__xludf.DUMMYFUNCTION("""COMPUTED_VALUE"""),"Roti") -> Roti | F29: =IFERROR(__xludf.DUMMYFUNCTION("""COMPUTED_VALUE"""),10000.0) -> 10000 | G29: =IFERROR(__xludf.DUMMYFUNCTION("""COMPUTED_VALUE"""),"Roti Bawang Saus Keju") -> Roti Bawang Saus Keju | J29: =IFERROR(__xludf.DUMMYFUNCTION("""COMPUTED_VALUE"""),1.0) -> 1 | K29: =IFERROR(__xludf.DUMMYFUNCTION("""COMPUTED_VALUE"""),29524.0) -> 29524 | L29: =IFERROR(__xludf.DUMMYFUNCTION("""COMPUTED_VALUE"""),0.0) -> 0 | M29: =IFERROR(__xludf.DUMMYFUNCTION("""COMPUTED_VALUE"""),29524.0) -> 29524 | N29: =IFERROR(__xludf.DUMMYFUNCTION("""COMPUTED_VALUE"""),0.0) -> 0 | O29: =IFERROR(__xludf.DUMMYFUNCTION("""COMPUTED_VALUE"""),29524.0) -> 29524 | P29: =IFERROR(__xludf.DUMMYFUNCTION("""COMPUTED_VALUE"""),1476.0) -> 1476 | Q29: =IFERROR(__xludf.DUMMYFUNCTION("""COMPUTED_VALUE"""),"Dine In") -> Dine In | R29: =IFERROR(__xludf.DUMMYFUNCTION("""COMPUTED_VALUE"""),"Kedai") -> Kedai | S29: =IFERROR(__xludf.DUMMYFUNCTION("""COMPUTED_VALUE"""),"Temu Roti") -> Temu Roti | T29: =IFERROR(__xludf.DUMMYFUNCTION("""COMPUTED_VALUE"""),"Owner") -> Owner | X29: =IFERROR(__xludf.DUMMYFUNCTION("""COMPUTED_VALUE"""),"Closed") -> Closed
A30: 29/09/2024 17:15,2-9555,Sale,Minuman,10013,Kopi cur,,,1.000,23333.00,0.00,23333.00,0.00,23333.00,1167.00,Dine In,Kedai,Temu Roti,Owner,,,,Closed | B30: =IFERROR(__xludf.DUMMYFUNCTION("SPLIT(A30,"","",0,0)"),45564.71875) -> 45564.719 | C30: =IFERROR(__xludf.DUMMYFUNCTION("""COMPUTED_VALUE"""),2795964.0) -> 2795964 | D30: =IFERROR(__xludf.DUMMYFUNCTION("""COMPUTED_VALUE"""),"Sale") -> Sale | E30: =IFERROR(__xludf.DUMMYFUNCTION("""COMPUTED_VALUE"""),"Minuman") -> Minuman | F30: =IFERROR(__xludf.DUMMYFUNCTION("""COMPUTED_VALUE"""),10013.0) -> 10013 | G30: =IFERROR(__xludf.DUMMYFUNCTION("""COMPUTED_VALUE"""),"Kopi cur") -> Kopi cur | J30: =IFERROR(__xludf.DUMMYFUNCTION("""COMPUTED_VALUE"""),1.0) -> 1 | K30: =IFERROR(__xludf.DUMMYFUNCTION("""COMPUTED_VALUE"""),23333.0) -> 23333 | L30: =IFERROR(__xludf.DUMMYFUNCTION("""COMPUTED_VALUE"""),0.0) -> 0 | M30: =IFERROR(__xludf.DUMMYFUNCTION("""COMPUTED_VALUE"""),23333.0) -> 23333 | N30: =IFERROR(__xludf.DUMMYFUNCTION("""COMPUTED_VALUE"""),0.0) -> 0 | O30: =IFERROR(__xludf.DUMMYFUNCTION("""COMPUTED_VALUE"""),23333.0) -> 23333 | P30: =IFERROR(__xludf.DUMMYFUNCTION("""COMPUTED_VALUE"""),1167.0) -> 1167 | Q30: =IFERROR(__xludf.DUMMYFUNCTION("""COMPUTED_VALUE"""),"Dine In") -> Dine In | R30: =IFERROR(__xludf.DUMMYFUNCTION("""COMPUTED_VALUE"""),"Kedai") -> Kedai | S30: =IFERROR(__xludf.DUMMYFUNCTION("""COMPUTED_VALUE"""),"Temu Roti") -> Temu Roti | T30: =IFERROR(__xludf.DUMMYFUNCTION("""COMPUTED_VALUE"""),"Owner") -> Owner | X30: =IFERROR(__xludf.DUMMYFUNCTION("""COMPUTED_VALUE"""),"Closed") -> Closed
A31: 29/09/2024 17:15,2-9555,Sale,Minuman,10127,Kopi Tubruk Panas,,,1.000,18571.00,0.00,18571.00,0.00,18571.00,928.00,Dine In,Kedai,Temu Roti,Owner,,,,Closed | B31: =IFERROR(__xludf.DUMMYFUNCTION("SPLIT(A31,"","",0,0)"),45564.71875) -> 45564.719 | C31: =IFERROR(__xludf.DUMMYFUNCTION("""COMPUTED_VALUE"""),2795964.0) -> 2795964 | D31: =IFERROR(__xludf.DUMMYFUNCTION("""COMPUTED_VALUE"""),"Sale") -> Sale | E31: =IFERROR(__xludf.DUMMYFUNCTION("""COMPUTED_VALUE"""),"Minuman") -> Minuman | F31: =IFERROR(__xludf.DUMMYFUNCTION("""COMPUTED_VALUE"""),10127.0) -> 10127 | G31: =IFERROR(__xludf.DUMMYFUNCTION("""COMPUTED_VALUE"""),"Kopi Tubruk Panas") -> Kopi Tubruk Panas | J31: =IFERROR(__xludf.DUMMYFUNCTION("""COMPUTED_VALUE"""),1.0) -> 1 | K31: =IFERROR(__xludf.DUMMYFUNCTION("""COMPUTED_VALUE"""),18571.0) -> 18571 | L31: =IFERROR(__xludf.DUMMYFUNCTION("""COMPUTED_VALUE"""),0.0) -> 0 | M31: =IFERROR(__xludf.DUMMYFUNCTION("""COMPUTED_VALUE"""),18571.0) -> 18571 | N31: =IFERROR(__xludf.DUMMYFUNCTION("""COMPUTED_VALUE"""),0.0) -> 0 | O31: =IFERROR(__xludf.DUMMYFUNCTION("""COMPUTED_VALUE"""),18571.0) -> 18571 | P31: =IFERROR(__xludf.DUMMYFUNCTION("""COMPUTED_VALUE"""),928.0) -> 928 | Q31: =IFERROR(__xludf.DUMMYFUNCTION("""COMPUTED_VALUE"""),"Dine In") -> Dine In | R31: =IFERROR(__xludf.DUMMYFUNCTION("""COMPUTED_VALUE"""),"Kedai") -> Kedai | S31: =IFERROR(__xludf.DUMMYFUNCTION("""COMPUTED_VALUE"""),"Temu Roti") -> Temu Roti | T31: =IFERROR(__xludf.DUMMYFUNCTION("""COMPUTED_VALUE"""),"Owner") -> Owner | X31: =IFERROR(__xludf.DUMMYFUNCTION("""COMPUTED_VALUE"""),"Closed") -> Closed
A32: 29/09/2024 17:15,2-9555,Sale,Minuman,10070,Wedang laut,,,1.000,24762.00,0.00,24762.00,0.00,24762.00,1239.00,Dine In,Kedai,Temu Roti,Owner,,,,Closed | B32: =IFERROR(__xludf.DUMMYFUNCTION("SPLIT(A32,"","",0,0)"),45564.71875) -> 45564.719 | C32: =IFERROR(__xludf.DUMMYFUNCTION("""COMPUTED_VALUE"""),2795964.0) -> 2795964 | D32: =IFERROR(__xludf.DUMMYFUNCTION("""COMPUTED_VALUE"""),"Sale") -> Sale | E32: =IFERROR(__xludf.DUMMYFUNCTION("""COMPUTED_VALUE"""),"Minuman") -> Minuman | F32: =IFERROR(__xludf.DUMMYFUNCTION("""COMPUTED_VALUE"""),10070.0) -> 10070 | G32: =IFERROR(__xludf.DUMMYFUNCTION("""COMPUTED_VALUE"""),"Wedang laut") -> Wedang laut | J32: =IFERROR(__xludf.DUMMYFUNCTION("""COMPUTED_VALUE"""),1.0) -> 1 | K32: =IFERROR(__xludf.DUMMYFUNCTION("""COMPUTED_VALUE"""),24762.0) -> 24762 | L32: =IFERROR(__xludf.DUMMYFUNCTION("""COMPUTED_VALUE"""),0.0) -> 0 | M32: =IFERROR(__xludf.DUMMYFUNCTION("""COMPUTED_VALUE"""),24762.0) -> 24762 | N32: =IFERROR(__xludf.DUMMYFUNCTION("""COMPUTED_VALUE"""),0.0) -> 0 | O32: =IFERROR(__xludf.DUMMYFUNCTION("""COMPUTED_VALUE"""),24762.0) -> 24762 | P32: =IFERROR(__xludf.DUMMYFUNCTION("""COMPUTED_VALUE"""),1239.0) -> 1239 | Q32: =IFERROR(__xludf.DUMMYFUNCTION("""COMPUTED_VALUE"""),"Dine In") -> Dine In | R32: =IFERROR(__xludf.DUMMYFUNCTION("""COMPUTED_VALUE"""),"Kedai") -> Kedai | S32: =IFERROR(__xludf.DUMMYFUNCTION("""COMPUTED_VALUE"""),"Temu Roti") -> Temu Roti | T32: =IFERROR(__xludf.DUMMYFUNCTION("""COMPUTED_VALUE"""),"Owner") -> Owner | X32: =IFERROR(__xludf.DUMMYFUNCTION("""COMPUTED_VALUE"""),"Closed") -> Closed
A33: 29/09/2024 17:13,2-9554,Sale,Minuman,10128,Es Kopi Susu,,,1.000,23333.00,0.00,23333.00,0.00,23333.00,1167.00,Dine In,Kedai,Temu Roti,Owner,,,,Closed | B33: =IFERROR(__xludf.DUMMYFUNCTION("SPLIT(A33,"","",0,0)"),45564.717361111114) -> 45564.717 | C33: =IFERROR(__xludf.DUMMYFUNCTION("""COMPUTED_VALUE"""),2795599.0) -> 2795599 | D33: =IFERROR(__xludf.DUMMYFUNCTION("""COMPUTED_VALUE"""),"Sale") -> Sale | E33: =IFERROR(__xludf.DUMMYFUNCTION("""COMPUTED_VALUE"""),"Minuman") -> Minuman | F33: =IFERROR(__xludf.DUMMYFUNCTION("""COMPUTED_VALUE"""),10128.0) -> 10128 | G33: =IFERROR(__xludf.DUMMYFUNCTION("""COMPUTED_VALUE"""),"Es Kopi Susu") -> Es Kopi Susu | J33: =IFERROR(__xludf.DUMMYFUNCTION("""COMPUTED_VALUE"""),1.0) -> 1 | K33: =IFERROR(__xludf.DUMMYFUNCTION("""COMPUTED_VALUE"""),23333.0) -> 23333 | L33: =IFERROR(__xludf.DUMMYFUNCTION("""COMPUTED_VALUE"""),0.0) -> 0 | M33: =IFERROR(__xludf.DUMMYFUNCTION("""COMPUTED_VALUE"""),23333.0) -> 23333 | N33: =IFERROR(__xludf.DUMMYFUNCTION("""COMPUTED_VALUE"""),0.0) -> 0 | O33: =IFERROR(__xludf.DUMMYFUNCTION("""COMPUTED_VALUE"""),23333.0) -> 23333 | P33: =IFERROR(__xludf.DUMMYFUNCTION("""COMPUTED_VALUE"""),1167.0) -> 1167 | Q33: =IFERROR(__xludf.DUMMYFUNCTION("""COMPUTED_VALUE"""),"Dine In") -> Dine In | R33: =IFERROR(__xludf.DUMMYFUNCTION("""COMPUTED_VALUE"""),"Kedai") -> Kedai | S33: =IFERROR(__xludf.DUMMYFUNCTION("""COMPUTED_VALUE"""),"Temu Roti") -> Temu Roti | T33: =IFERROR(__xludf.DUMMYFUNCTION("""COMPUTED_VALUE"""),"Owner") -> Owner | X33: =IFERROR(__xludf.DUMMYFUNCTION("""COMPUTED_VALUE"""),"Closed") -> Closed
A34: 29/09/2024 16:58,2-9553,Sale,Minuman,10128,Es Kopi Susu,,,2.000,46666.00,0.00,46666.00,0.00,46666.00,2333.00,Dine In,Kedai,Temu Roti,Owner,,,,Closed | B34: =IFERROR(__xludf.DUMMYFUNCTION("SPLIT(A34,"","",0,0)"),45564.70694444444) -> 45564.707 | C34: =IFERROR(__xludf.DUMMYFUNCTION("""COMPUTED_VALUE"""),2795234.0) -> 2795234 | D34: =IFERROR(__xludf.DUMMYFUNCTION("""COMPUTED_VALUE"""),"Sale") -> Sale | E34: =IFERROR(__xludf.DUMMYFUNCTION("""COMPUTED_VALUE"""),"Minuman") -> Minuman | F34: =IFERROR(__xludf.DUMMYFUNCTION("""COMPUTED_VALUE"""),10128.0) -> 10128 | G34: =IFERROR(__xludf.DUMMYFUNCTION("""COMPUTED_VALUE"""),"Es Kopi Susu") -> Es Kopi Susu | J34: =IFERROR(__xludf.DUMMYFUNCTION("""COMPUTED_VALUE"""),2.0) -> 2 | K34: =IFERROR(__xludf.DUMMYFUNCTION("""COMPUTED_VALUE"""),46666.0) -> 46666 | L34: =IFERROR(__xludf.DUMMYFUNCTION("""COMPUTED_VALUE"""),0.0) -> 0 | M34: =IFERROR(__xludf.DUMMYFUNCTION("""COMPUTED_VALUE"""),46666.0) -> 46666 | N34: =IFERROR(__xludf.DUMMYFUNCTION("""COMPUTED_VALUE"""),0.0) -> 0 | O34: =IFERROR(__xludf.DUMMYFUNCTION("""COMPUTED_VALUE"""),46666.0) -> 46666 | P34: =IFERROR(__xludf.DUMMYFUNCTION("""COMPUTED_VALUE"""),2333.0) -> 2333 | Q34: =IFERROR(__xludf.DUMMYFUNCTION("""COMPUTED_VALUE"""),"Dine In") -> Dine In | R34: =IFERROR(__xludf.DUMMYFUNCTION("""COMPUTED_VALUE"""),"Kedai") -> Kedai | S34: =IFERROR(__xludf.DUMMYFUNCTION("""COMPUTED_VALUE"""),"Temu Roti") -> Temu Roti | T34: =IFERROR(__xludf.DUMMYFUNCTION("""COMPUTED_VALUE"""),"Owner") -> Owner | X34: =IFERROR(__xludf.DUMMYFUNCTION("""COMPUTED_VALUE"""),"Closed") -> Closed
A35: 29/09/2024 16:47,2-9552,Sale,Minuman,10063,Wedang Bulan,,,1.000,24762.00,0.00,24762.00,0.00,24762.00,1238.00,Dine In,Kedai,Temu Roti,Owner,,,,Closed | B35: =IFERROR(__xludf.DUMMYFUNCTION("SPLIT(A35,"","",0,0)"),45564.69930555556) -> 45564.699 | C35: =IFERROR(__xludf.DUMMYFUNCTION("""COMPUTED_VALUE"""),2794868.0) -> 2794868 | D35: =IFERROR(__xludf.DUMMYFUNCTION("""COMPUTED_VALUE"""),"Sale") -> Sale | E35: =IFERROR(__xludf.DUMMYFUNCTION("""COMPUTED_VALUE"""),"Minuman") -> Minuman | F35: =IFERROR(__xludf.DUMMYFUNCTION("""COMPUTED_VALUE"""),10063.0) -> 10063 | G35: =IFERROR(__xludf.DUMMYFUNCTION("""COMPUTED_VALUE"""),"Wedang Bulan") -> Wedang Bulan | J35: =IFERROR(__xludf.DUMMYFUNCTION("""COMPUTED_VALUE"""),1.0) -> 1 | K35: =IFERROR(__xludf.DUMMYFUNCTION("""COMPUTED_VALUE"""),24762.0) -> 24762 | L35: =IFERROR(__xludf.DUMMYFUNCTION("""COMPUTED_VALUE"""),0.0) -> 0 | M35: =IFERROR(__xludf.DUMMYFUNCTION("""COMPUTED_VALUE"""),24762.0) -> 24762 | N35: =IFERROR(__xludf.DUMMYFUNCTION("""COMPUTED_VALUE"""),0.0) -> 0 | O35: =IFERROR(__xludf.DUMMYFUNCTION("""COMPUTED_VALUE"""),24762.0) -> 24762 | P35: =IFERROR(__xludf.DUMMYFUNCTION("""COMPUTED_VALUE"""),1238.0) -> 1238 | Q35: =IFERROR(__xludf.DUMMYFUNCTION("""COMPUTED_VALUE"""),"Dine In") -> Dine In | R35: =IFERROR(__xludf.DUMMYFUNCTION("""COMPUTED_VALUE"""),"Kedai") -> Kedai | S35: =IFERROR(__xludf.DUMMYFUNCTION("""COMPUTED_VALUE"""),"Temu Roti") -> Temu Roti | T35: =IFERROR(__xludf.DUMMYFUNCTION("""COMPUTED_VALUE"""),"Owner") -> Owner | X35: =IFERROR(__xludf.DUMMYFUNCTION("""COMPUTED_VALUE"""),"Closed") -> Closed
A36: 29/09/2024 16:47,2-9552,Sale,Minuman,10107,Korean Mango Fresh Milk,,,1.000,26667.00,0.00,26667.00,0.00,26667.00,1333.00,Dine In,Kedai,Temu Roti,Owner,,,,Closed | B36: =IFERROR(__xludf.DUMMYFUNCTION("SPLIT(A36,"","",0,0)"),45564.69930555556) -> 45564.699 | C36: =IFERROR(__xludf.DUMMYFUNCTION("""COMPUTED_VALUE"""),2794868.0) -> 2794868 | D36: =IFERROR(__xludf.DUMMYFUNCTION("""COMPUTED_VALUE"""),"Sale") -> Sale | E36: =IFERROR(__xludf.DUMMYFUNCTION("""COMPUTED_VALUE"""),"Minuman") -> Minuman | F36: =IFERROR(__xludf.DUMMYFUNCTION("""COMPUTED_VALUE"""),10107.0) -> 10107 | G36: =IFERROR(__xludf.DUMMYFUNCTION("""COMPUTED_VALUE"""),"Korean Mango Fresh Milk") -> Korean Mango Fresh Milk | J36: =IFERROR(__xludf.DUMMYFUNCTION("""COMPUTED_VALUE"""),1.0) -> 1 | K36: =IFERROR(__xludf.DUMMYFUNCTION("""COMPUTED_VALUE"""),26667.0) -> 26667 | L36: =IFERROR(__xludf.DUMMYFUNCTION("""COMPUTED_VALUE"""),0.0) -> 0 | M36: =IFERROR(__xludf.DUMMYFUNCTION("""COMPUTED_VALUE"""),26667.0) -> 26667 | N36: =IFERROR(__xludf.DUMMYFUNCTION("""COMPUTED_VALUE"""),0.0) -> 0 | O36: =IFERROR(__xludf.DUMMYFUNCTION("""COMPUTED_VALUE"""),26667.0) -> 26667 | P36: =IFERROR(__xludf.DUMMYFUNCTION("""COMPUTED_VALUE"""),1333.0) -> 1333 | Q36: =IFERROR(__xludf.DUMMYFUNCTION("""COMPUTED_VALUE"""),"Dine In") -> Dine In | R36: =IFERROR(__xludf.DUMMYFUNCTION("""COMPUTED_VALUE"""),"Kedai") -> Kedai | S36: =IFERROR(__xludf.DUMMYFUNCTION("""COMPUTED_VALUE"""),"Temu Roti") -> Temu Roti | T36: =IFERROR(__xludf.DUMMYFUNCTION("""COMPUTED_VALUE"""),"Owner") -> Owner | X36: =IFERROR(__xludf.DUMMYFUNCTION("""COMPUTED_VALUE"""),"Closed") -> Closed
A37: 29/09/2024 16:47,2-9552,Sale,Roti,10005,Roti Gandum Cokelat,,,1.000,19524.00,0.00,19524.00,0.00,19524.00,977.00,Dine In,Kedai,Temu Roti,Owner,,,,Closed | B37: =IFERROR(__xludf.DUMMYFUNCTION("SPLIT(A37,"","",0,0)"),45564.69930555556) -> 45564.699 | C37: =IFERROR(__xludf.DUMMYFUNCTION("""COMPUTED_VALUE"""),2794868.0) -> 2794868 | D37: =IFERROR(__xludf.DUMMYFUNCTION("""COMPUTED_VALUE"""),"Sale") -> Sale | E37: =IFERROR(__xludf.DUMMYFUNCTION("""COMPUTED_VALUE"""),"Roti") -> Roti | F37: =IFERROR(__xludf.DUMMYFUNCTION("""COMPUTED_VALUE"""),10005.0) -> 10005 | G37: =IFERROR(__xludf.DUMMYFUNCTION("""COMPUTED_VALUE"""),"Roti Gandum Cokelat") -> Roti Gandum Cokelat | J37: =IFERROR(__xludf.DUMMYFUNCTION("""COMPUTED_VALUE"""),1.0) -> 1 | K37: =IFERROR(__xludf.DUMMYFUNCTION("""COMPUTED_VALUE"""),19524.0) -> 19524 | L37: =IFERROR(__xludf.DUMMYFUNCTION("""COMPUTED_VALUE"""),0.0) -> 0 | M37: =IFERROR(__xludf.DUMMYFUNCTION("""COMPUTED_VALUE"""),19524.0) -> 19524 | N37: =IFERROR(__xludf.DUMMYFUNCTION("""COMPUTED_VALUE"""),0.0) -> 0 | O37: =IFERROR(__xludf.DUMMYFUNCTION("""COMPUTED_VALUE"""),19524.0) -> 19524 | P37: =IFERROR(__xludf.DUMMYFUNCTION("""COMPUTED_VALUE"""),977.0) -> 977 | Q37: =IFERROR(__xludf.DUMMYFUNCTION("""COMPUTED_VALUE"""),"Dine In") -> Dine In | R37: =IFERROR(__xludf.DUMMYFUNCTION("""COMPUTED_VALUE"""),"Kedai") -> Kedai | S37: =IFERROR(__xludf.DUMMYFUNCTION("""COMPUTED_VALUE"""),"Temu Roti") -> Temu Roti | T37: =IFERROR(__xludf.DUMMYFUNCTION("""COMPUTED_VALUE"""),"Owner") -> Owner | X37: =IFERROR(__xludf.DUMMYFUNCTION("""COMPUTED_VALUE"""),"Closed") -> Closed
A38: 29/09/2024 16:47,2-9552,Sale,Roti,10002,Roti Cranberry,,,1.000,18571.00,0.00,18571.00,0.00,18571.00,928.00,Dine In,Kedai,Temu Roti,Owner,,,,Closed | B38: =IFERROR(__xludf.DUMMYFUNCTION("SPLIT(A38,"","",0,0)"),45564.69930555556) -> 45564.699 | C38: =IFERROR(__xludf.DUMMYFUNCTION("""COMPUTED_VALUE"""),2794868.0) -> 2794868 | D38: =IFERROR(__xludf.DUMMYFUNCTION("""COMPUTED_VALUE"""),"Sale") -> Sale | E38: =IFERROR(__xludf.DUMMYFUNCTION("""COMPUTED_VALUE"""),"Roti") -> Roti | F38: =IFERROR(__xludf.DUMMYFUNCTION("""COMPUTED_VALUE"""),10002.0) -> 10002 | G38: =IFERROR(__xludf.DUMMYFUNCTION("""COMPUTED_VALUE"""),"Roti Cranberry") -> Roti Cranberry | J38: =IFERROR(__xludf.DUMMYFUNCTION("""COMPUTED_VALUE"""),1.0) -> 1 | K38: =IFERROR(__xludf.DUMMYFUNCTION("""COMPUTED_VALUE"""),18571.0) -> 18571 | L38: =IFERROR(__xludf.DUMMYFUNCTION("""COMPUTED_VALUE"""),0.0) -> 0 | M38: =IFERROR(__xludf.DUMMYFUNCTION("""COMPUTED_VALUE"""),18571.0) -> 18571 | N38: =IFERROR(__xludf.DUMMYFUNCTION("""COMPUTED_VALUE"""),0.0) -> 0 | O38: =IFERROR(__xludf.DUMMYFUNCTION("""COMPUTED_VALUE"""),18571.0) -> 18571 | P38: =IFERROR(__xludf.DUMMYFUNCTION("""COMPUTED_VALUE"""),928.0) -> 928 | Q38: =IFERROR(__xludf.DUMMYFUNCTION("""COMPUTED_VALUE"""),"Dine In") -> Dine In | R38: =IFERROR(__xludf.DUMMYFUNCTION("""COMPUTED_VALUE"""),"Kedai") -> Kedai | S38: =IFERROR(__xludf.DUMMYFUNCTION("""COMPUTED_VALUE"""),"Temu Roti") -> Temu Roti | T38: =IFERROR(__xludf.DUMMYFUNCTION("""COMPUTED_VALUE"""),"Owner") -> Owner | X38: =IFERROR(__xludf.DUMMYFUNCTION("""COMPUTED_VALUE"""),"Closed") -> Closed
A39: 29/09/2024 15:27,2-9551,Refund,Roti,10007,Roti cranberry 2 pcs,,,-1.000,-33810.00,0.00,-33810.00,-0.00,-33810.00,-1691.00,Dine In,Kedai,Temu Roti,Owner,,,,Closed | B39: =IFERROR(__xludf.DUMMYFUNCTION("SPLIT(A39,"","",0,0)"),45564.64375) -> 45564.644 | C39: =IFERROR(__xludf.DUMMYFUNCTION("""COMPUTED_VALUE"""),2794503.0) -> 2794503 | D39: =IFERROR(__xludf.DUMMYFUNCTION("""COMPUTED_VALUE"""),"Refund") -> Refund | E39: =IFERROR(__xludf.DUMMYFUNCTION("""COMPUTED_VALUE"""),"Roti") -> Roti | F39: =IFERROR(__xludf.DUMMYFUNCTION("""COMPUTED_VALUE"""),10007.0) -> 10007 | G39: =IFERROR(__xludf.DUMMYFUNCTION("""COMPUTED_VALUE"""),"Roti cranberry 2 pcs") -> Roti cranberry 2 pcs | J39: =IFERROR(__xludf.DUMMYFUNCTION("""COMPUTED_VALUE"""),-1.0) -> -1 | K39: =IFERROR(__xludf.DUMMYFUNCTION("""COMPUTED_VALUE"""),-33810.0) -> -33810 | L39: =IFERROR(__xludf.DUMMYFUNCTION("""COMPUTED_VALUE"""),0.0) -> 0 | M39: =IFERROR(__xludf.DUMMYFUNCTION("""COMPUTED_VALUE"""),-33810.0) -> -33810 | N39: =IFERROR(__xludf.DUMMYFUNCTION("""COMPUTED_VALUE"""),0.0) -> 0 | O39: =IFERROR(__xludf.DUMMYFUNCTION("""COMPUTED_VALUE"""),-33810.0) -> -33810 | P39: =IFERROR(__xludf.DUMMYFUNCTION("""COMPUTED_VALUE"""),-1691.0) -> -1691 | Q39: =IFERROR(__xludf.DUMMYFUNCTION("""COMPUTED_VALUE"""),"Dine In") -> Dine In | R39: =IFERROR(__xludf.DUMMYFUNCTION("""COMPUTED_VALUE"""),"Kedai") -> Kedai | S39: =IFERROR(__xludf.DUMMYFUNCTION("""COMPUTED_VALUE"""),"Temu Roti") -> Temu Roti | T39: =IFERROR(__xludf.DUMMYFUNCTION("""COMPUTED_VALUE"""),"Owner") -> Owner | X39: =IFERROR(__xludf.DUMMYFUNCTION("""COMPUTED_VALUE"""),"Closed") -> Closed
A40: 29/09/2024 15:27,2-9551,Refund,Roti,10055,Roti Gandum Cokelat 2 pcs,,,-1.000,-34762.00,0.00,-34762.00,-0.00,-34762.00,-1738.00,Dine In,Kedai,Temu Roti,Owner,,,,Closed | B40: =IFERROR(__xludf.DUMMYFUNCTION("SPLIT(A40,"","",0,0)"),45564.64375) -> 45564.644 | C40: =IFERROR(__xludf.DUMMYFUNCTION("""COMPUTED_VALUE"""),2794503.0) -> 2794503 | D40: =IFERROR(__xludf.DUMMYFUNCTION("""COMPUTED_VALUE"""),"Refund") -> Refund | E40: =IFERROR(__xludf.DUMMYFUNCTION("""COMPUTED_VALUE"""),"Roti") -> Roti | F40: =IFERROR(__xludf.DUMMYFUNCTION("""COMPUTED_VALUE"""),10055.0) -> 10055 | G40: =IFERROR(__xludf.DUMMYFUNCTION("""COMPUTED_VALUE"""),"Roti Gandum Cokelat 2 pcs") -> Roti Gandum Cokelat 2 pcs | J40: =IFERROR(__xludf.DUMMYFUNCTION("""COMPUTED_VALUE"""),-1.0) -> -1 | K40: =IFERROR(__xludf.DUMMYFUNCTION("""COMPUTED_VALUE"""),-34762.0) -> -34762 | L40: =IFERROR(__xludf.DUMMYFUNCTION("""COMPUTED_VALUE"""),0.0) -> 0 | M40: =IFERROR(__xludf.DUMMYFUNCTION("""COMPUTED_VALUE"""),-34762.0) -> -34762 | N40: =IFERROR(__xludf.DUMMYFUNCTION("""COMPUTED_VALUE"""),0.0) -> 0 | O40: =IFERROR(__xludf.DUMMYFUNCTION("""COMPUTED_VALUE"""),-34762.0) -> -34762 | P40: =IFERROR(__xludf.DUMMYFUNCTION("""COMPUTED_VALUE"""),-1738.0) -> -1738 | Q40: =IFERROR(__xludf.DUMMYFUNCTION("""COMPUTED_VALUE"""),"Dine In") -> Dine In | R40: =IFERROR(__xludf.DUMMYFUNCTION("""COMPUTED_VALUE"""),"Kedai") -> Kedai | S40: =IFERROR(__xludf.DUMMYFUNCTION("""COMPUTED_VALUE"""),"Temu Roti") -> Temu Roti | T40: =IFERROR(__xludf.DUMMYFUNCTION("""COMPUTED_VALUE"""),"Owner") -> Owner | X40: =IFERROR(__xludf.DUMMYFUNCTION("""COMPUTED_VALUE"""),"Closed") -> Closed
A41: 29/09/2024 15:27,2-9551,Refund,Minuman,10107,Korean Mango Fresh Milk,,,-1.000,-26667.00,0.00,-26667.00,-0.00,-26667.00,-1333.00,Dine In,Kedai,Temu Roti,Owner,,,,Closed | B41: =IFERROR(__xludf.DUMMYFUNCTION("SPLIT(A41,"","",0,0)"),45564.64375) -> 45564.644 | C41: =IFERROR(__xludf.DUMMYFUNCTION("""COMPUTED_VALUE"""),2794503.0) -> 2794503 | D41: =IFERROR(__xludf.DUMMYFUNCTION("""COMPUTED_VALUE"""),"Refund") -> Refund | E41: =IFERROR(__xludf.DUMMYFUNCTION("""COMPUTED_VALUE"""),"Minuman") -> Minuman | F41: =IFERROR(__xludf.DUMMYFUNCTION("""COMPUTED_VALUE"""),10107.0) -> 10107 | G41: =IFERROR(__xludf.DUMMYFUNCTION("""COMPUTED_VALUE"""),"Korean Mango Fresh Milk") -> Korean Mango Fresh Milk | J41: =IFERROR(__xludf.DUMMYFUNCTION("""COMPUTED_VALUE"""),-1.0) -> -1 | K41: =IFERROR(__xludf.DUMMYFUNCTION("""COMPUTED_VALUE"""),-26667.0) -> -26667 | L41: =IFERROR(__xludf.DUMMYFUNCTION("""COMPUTED_VALUE"""),0.0) -> 0 | M41: =IFERROR(__xludf.DUMMYFUNCTION("""COMPUTED_VALUE"""),-26667.0) -> -26667 | N41: =IFERROR(__xludf.DUMMYFUNCTION("""COMPUTED_VALUE"""),0.0) -> 0 | O41: =IFERROR(__xludf.DUMMYFUNCTION("""COMPUTED_VALUE"""),-26667.0) -> -26667 | P41: =IFERROR(__xludf.DUMMYFUNCTION("""COMPUTED_VALUE"""),-1333.0) -> -1333 | Q41: =IFERROR(__xludf.DUMMYFUNCTION("""COMPUTED_VALUE"""),"Dine In") -> Dine In | R41: =IFERROR(__xludf.DUMMYFUNCTION("""COMPUTED_VALUE"""),"Kedai") -> Kedai | S41: =IFERROR(__xludf.DUMMYFUNCTION("""COMPUTED_VALUE"""),"Temu Roti") -> Temu Roti | T41: =IFERROR(__xludf.DUMMYFUNCTION("""COMPUTED_VALUE"""),"Owner") -> Owner | X41: =IFERROR(__xludf.DUMMYFUNCTION("""COMPUTED_VALUE"""),"Closed") -> Closed
A42: 29/09/2024 15:27,2-9551,Refund,Minuman,10106,Korean Strawberry Fresh Milk,,,-1.000,-26667.00,0.00,-26667.00,-0.00,-26667.00,-1333.00,Dine In,Kedai,Temu Roti,Owner,,,,Closed | B42: =IFERROR(__xludf.DUMMYFUNCTION("SPLIT(A42,"","",0,0)"),45564.64375) -> 45564.644 | C42: =IFERROR(__xludf.DUMMYFUNCTION("""COMPUTED_VALUE"""),2794503.0) -> 2794503 | D42: =IFERROR(__xludf.DUMMYFUNCTION("""COMPUTED_VALUE"""),"Refund") -> Refund | E42: =IFERROR(__xludf.DUMMYFUNCTION("""COMPUTED_VALUE"""),"Minuman") -> Minuman | F42: =IFERROR(__xludf.DUMMYFUNCTION("""COMPUTED_VALUE"""),10106.0) -> 10106 | G42: =IFERROR(__xludf.DUMMYFUNCTION("""COMPUTED_VALUE"""),"Korean Strawberry Fresh Milk") -> Korean Strawberry Fresh Milk | J42: =IFERROR(__xludf.DUMMYFUNCTION("""COMPUTED_VALUE"""),-1.0) -> -1 | K42: =IFERROR(__xludf.DUMMYFUNCTION("""COMPUTED_VALUE"""),-26667.0) -> -26667 | L42: =IFERROR(__xludf.DUMMYFUNCTION("""COMPUTED_VALUE"""),0.0) -> 0 | M42: =IFERROR(__xludf.DUMMYFUNCTION("""COMPUTED_VALUE"""),-26667.0) -> -26667 | N42: =IFERROR(__xludf.DUMMYFUNCTION("""COMPUTED_VALUE"""),0.0) -> 0 | O42: =IFERROR(__xludf.DUMMYFUNCTION("""COMPUTED_VALUE"""),-26667.0) -> -26667 | P42: =IFERROR(__xludf.DUMMYFUNCTION("""COMPUTED_VALUE"""),-1333.0) -> -1333 | Q42: =IFERROR(__xludf.DUMMYFUNCTION("""COMPUTED_VALUE"""),"Dine In") -> Dine In | R42: =IFERROR(__xludf.DUMMYFUNCTION("""COMPUTED_VALUE"""),"Kedai") -> Kedai | S42: =IFERROR(__xludf.DUMMYFUNCTION("""COMPUTED_VALUE"""),"Temu Roti") -> Temu Roti | T42: =IFERROR(__xludf.DUMMYFUNCTION("""COMPUTED_VALUE"""),"Owner") -> Owner | X42: =IFERROR(__xludf.DUMMYFUNCTION("""COMPUTED_VALUE"""),"Closed") -> Closed
A43: 29/09/2024 15:26,2-9550,Sale,Minuman,10106,Korean Strawberry Fresh Milk,,,1.000,26667.00,0.00,26667.00,0.00,26667.00,1333.00,Dine In,Kedai,Temu Roti,Owner,,,,Closed | B43: =IFERROR(__xludf.DUMMYFUNCTION("SPLIT(A43,"","",0,0)"),45564.643055555556) -> 45564.643 | C43: =IFERROR(__xludf.DUMMYFUNCTION("""COMPUTED_VALUE"""),2794138.0) -> 2794138 | D43: =IFERROR(__xludf.DUMMYFUNCTION("""COMPUTED_VALUE"""),"Sale") -> Sale | E43: =IFERROR(__xludf.DUMMYFUNCTION("""COMPUTED_VALUE"""),"Minuman") -> Minuman | F43: =IFERROR(__xludf.DUMMYFUNCTION("""COMPUTED_VALUE"""),10106.0) -> 10106 | G43: =IFERROR(__xludf.DUMMYFUNCTION("""COMPUTED_VALUE"""),"Korean Strawberry Fresh Milk") -> Korean Strawberry Fresh Milk | J43: =IFERROR(__xludf.DUMMYFUNCTION("""COMPUTED_VALUE"""),1.0) -> 1 | K43: =IFERROR(__xludf.DUMMYFUNCTION("""COMPUTED_VALUE"""),26667.0) -> 26667 | L43: =IFERROR(__xludf.DUMMYFUNCTION("""COMPUTED_VALUE"""),0.0) -> 0 | M43: =IFERROR(__xludf.DUMMYFUNCTION("""COMPUTED_VALUE"""),26667.0) -> 26667 | N43: =IFERROR(__xludf.DUMMYFUNCTION("""COMPUTED_VALUE"""),0.0) -> 0 | O43: =IFERROR(__xludf.DUMMYFUNCTION("""COMPUTED_VALUE"""),26667.0) -> 26667 | P43: =IFERROR(__xludf.DUMMYFUNCTION("""COMPUTED_VALUE"""),1333.0) -> 1333 | Q43: =IFERROR(__xludf.DUMMYFUNCTION("""COMPUTED_VALUE"""),"Dine In") -> Dine In | R43: =IFERROR(__xludf.DUMMYFUNCTION("""COMPUTED_VALUE"""),"Kedai") -> Kedai | S43: =IFERROR(__xludf.DUMMYFUNCTION("""COMPUTED_VALUE"""),"Temu Roti") -> Temu Roti | T43: =IFERROR(__xludf.DUMMYFUNCTION("""COMPUTED_VALUE"""),"Owner") -> Owner | X43: =IFERROR(__xludf.DUMMYFUNCTION("""COMPUTED_VALUE"""),"Closed") -> Closed
A44: 29/09/2024 15:26,2-9550,Sale,Minuman,10107,Korean Mango Fresh Milk,,,1.000,26667.00,0.00,26667.00,0.00,26667.00,1334.00,Dine In,Kedai,Temu Roti,Owner,,,,Closed | B44: =IFERROR(__xludf.DUMMYFUNCTION("SPLIT(A44,"","",0,0)"),45564.643055555556) -> 45564.643 | C44: =IFERROR(__xludf.DUMMYFUNCTION("""COMPUTED_VALUE"""),2794138.0) -> 2794138 | D44: =IFERROR(__xludf.DUMMYFUNCTION("""COMPUTED_VALUE"""),"Sale") -> Sale | E44: =IFERROR(__xludf.DUMMYFUNCTION("""COMPUTED_VALUE"""),"Minuman") -> Minuman | F44: =IFERROR(__xludf.DUMMYFUNCTION("""COMPUTED_VALUE"""),10107.0) -> 10107 | G44: =IFERROR(__xludf.DUMMYFUNCTION("""COMPUTED_VALUE"""),"Korean Mango Fresh Milk") -> Korean Mango Fresh Milk | J44: =IFERROR(__xludf.DUMMYFUNCTION("""COMPUTED_VALUE"""),1.0) -> 1 | K44: =IFERROR(__xludf.DUMMYFUNCTION("""COMPUTED_VALUE"""),26667.0) -> 26667 | L44: =IFERROR(__xludf.DUMMYFUNCTION("""COMPUTED_VALUE"""),0.0) -> 0 | M44: =IFERROR(__xludf.DUMMYFUNCTION("""COMPUTED_VALUE"""),26667.0) -> 26667 | N44: =IFERROR(__xludf.DUMMYFUNCTION("""COMPUTED_VALUE"""),0.0) -> 0 | O44: =IFERROR(__xludf.DUMMYFUNCTION("""COMPUTED_VALUE"""),26667.0) -> 26667 | P44: =IFERROR(__xludf.DUMMYFUNCTION("""COMPUTED_VALUE"""),1334.0) -> 1334 | Q44: =IFERROR(__xludf.DUMMYFUNCTION("""COMPUTED_VALUE"""),"Dine In") -> Dine In | R44: =IFERROR(__xludf.DUMMYFUNCTION("""COMPUTED_VALUE"""),"Kedai") -> Kedai | S44: =IFERROR(__xludf.DUMMYFUNCTION("""COMPUTED_VALUE"""),"Temu Roti") -> Temu Roti | T44: =IFERROR(__xludf.DUMMYFUNCTION("""COMPUTED_VALUE"""),"Owner") -> Owner | X44: =IFERROR(__xludf.DUMMYFUNCTION("""COMPUTED_VALUE"""),"Closed") -> Closed
A45: 29/09/2024 15:26,2-9550,Sale,Roti,10007,Roti cranberry 2 pcs,,,1.000,33810.00,0.00,33810.00,0.00,33810.00,1690.00,Dine In,Kedai,Temu Roti,Owner,,,,Closed | B45: =IFERROR(__xludf.DUMMYFUNCTION("SPLIT(A45,"","",0,0)"),45564.643055555556) -> 45564.643 | C45: =IFERROR(__xludf.DUMMYFUNCTION("""COMPUTED_VALUE"""),2794138.0) -> 2794138 | D45: =IFERROR(__xludf.DUMMYFUNCTION("""COMPUTED_VALUE"""),"Sale") -> Sale | E45: =IFERROR(__xludf.DUMMYFUNCTION("""COMPUTED_VALUE"""),"Roti") -> Roti | F45: =IFERROR(__xludf.DUMMYFUNCTION("""COMPUTED_VALUE"""),10007.0) -> 10007 | G45: =IFERROR(__xludf.DUMMYFUNCTION("""COMPUTED_VALUE"""),"Roti cranberry 2 pcs") -> Roti cranberry 2 pcs | J45: =IFERROR(__xludf.DUMMYFUNCTION("""COMPUTED_VALUE"""),1.0) -> 1 | K45: =IFERROR(__xludf.DUMMYFUNCTION("""COMPUTED_VALUE"""),33810.0) -> 33810 | L45: =IFERROR(__xludf.DUMMYFUNCTION("""COMPUTED_VALUE"""),0.0) -> 0 | M45: =IFERROR(__xludf.DUMMYFUNCTION("""COMPUTED_VALUE"""),33810.0) -> 33810 | N45: =IFERROR(__xludf.DUMMYFUNCTION("""COMPUTED_VALUE"""),0.0) -> 0 | O45: =IFERROR(__xludf.DUMMYFUNCTION("""COMPUTED_VALUE"""),33810.0) -> 33810 | P45: =IFERROR(__xludf.DUMMYFUNCTION("""COMPUTED_VALUE"""),1690.0) -> 1690 | Q45: =IFERROR(__xludf.DUMMYFUNCTION("""COMPUTED_VALUE"""),"Dine In") -> Dine In | R45: =IFERROR(__xludf.DUMMYFUNCTION("""COMPUTED_VALUE"""),"Kedai") -> Kedai | S45: =IFERROR(__xludf.DUMMYFUNCTION("""COMPUTED_VALUE"""),"Temu Roti") -> Temu Roti | T45: =IFERROR(__xludf.DUMMYFUNCTION("""COMPUTED_VALUE"""),"Owner") -> Owner | X45: =IFERROR(__xludf.DUMMYFUNCTION("""COMPUTED_VALUE"""),"Closed") -> Closed
A46: 29/09/2024 15:26,2-9550,Sale,Roti,10055,Roti Gandum Cokelat 2 pcs,,,1.000,34762.00,0.00,34762.00,0.00,34762.00,1738.00,Dine In,Kedai,Temu Roti,Owner,,,,Closed | B46: =IFERROR(__xludf.DUMMYFUNCTION("SPLIT(A46,"","",0,0)"),45564.643055555556) -> 45564.643 | C46: =IFERROR(__xludf.DUMMYFUNCTION("""COMPUTED_VALUE"""),2794138.0) -> 2794138 | D46: =IFERROR(__xludf.DUMMYFUNCTION("""COMPUTED_VALUE"""),"Sale") -> Sale | E46: =IFERROR(__xludf.DUMMYFUNCTION("""COMPUTED_VALUE"""),"Roti") -> Roti | F46: =IFERROR(__xludf.DUMMYFUNCTION("""COMPUTED_VALUE"""),10055.0) -> 10055 | G46: =IFERROR(__xludf.DUMMYFUNCTION("""COMPUTED_VALUE"""),"Roti Gandum Cokelat 2 pcs") -> Roti Gandum Cokelat 2 pcs | J46: =IFERROR(__xludf.DUMMYFUNCTION("""COMPUTED_VALUE"""),1.0) -> 1 | K46: =IFERROR(__xludf.DUMMYFUNCTION("""COMPUTED_VALUE"""),34762.0) -> 34762 | L46: =IFERROR(__xludf.DUMMYFUNCTION("""COMPUTED_VALUE"""),0.0) -> 0 | M46: =IFERROR(__xludf.DUMMYFUNCTION("""COMPUTED_VALUE"""),34762.0) -> 34762 | N46: =IFERROR(__xludf.DUMMYFUNCTION("""COMPUTED_VALUE"""),0.0) -> 0 | O46: =IFERROR(__xludf.DUMMYFUNCTION("""COMPUTED_VALUE"""),34762.0) -> 34762 | P46: =IFERROR(__xludf.DUMMYFUNCTION("""COMPUTED_VALUE"""),1738.0) -> 1738 | Q46: =IFERROR(__xludf.DUMMYFUNCTION("""COMPUTED_VALUE"""),"Dine In") -> Dine In | R46: =IFERROR(__xludf.DUMMYFUNCTION("""COMPUTED_VALUE"""),"Kedai") -> Kedai | S46: =IFERROR(__xludf.DUMMYFUNCTION("""COMPUTED_VALUE"""),"Temu Roti") -> Temu Roti | T46: =IFERROR(__xludf.DUMMYFUNCTION("""COMPUTED_VALUE"""),"Owner") -> Owner | X46: =IFERROR(__xludf.DUMMYFUNCTION("""COMPUTED_VALUE"""),"Closed") -> Closed
A47: 29/09/2024 15:23,2-9549,Sale,Roti,10007,Roti cranberry 2 pcs,,,1.000,33810.00,0.00,33810.00,0.00,33810.00,1691.00,Dine In,Kedai,Temu Roti,Owner,,,,Closed | B47: =IFERROR(__xludf.DUMMYFUNCTION("SPLIT(A47,"","",0,0)"),45564.64097222222) -> 45564.641 | C47: =IFERROR(__xludf.DUMMYFUNCTION("""COMPUTED_VALUE"""),2793773.0) -> 2793773 | D47: =IFERROR(__xludf.DUMMYFUNCTION("""COMPUTED_VALUE"""),"Sale") -> Sale | E47: =IFERROR(__xludf.DUMMYFUNCTION("""COMPUTED_VALUE"""),"Roti") -> Roti | F47: =IFERROR(__xludf.DUMMYFUNCTION("""COMPUTED_VALUE"""),10007.0) -> 10007 | G47: =IFERROR(__xludf.DUMMYFUNCTION("""COMPUTED_VALUE"""),"Roti cranberry 2 pcs") -> Roti cranberry 2 pcs | J47: =IFERROR(__xludf.DUMMYFUNCTION("""COMPUTED_VALUE"""),1.0) -> 1 | K47: =IFERROR(__xludf.DUMMYFUNCTION("""COMPUTED_VALUE"""),33810.0) -> 33810 | L47: =IFERROR(__xludf.DUMMYFUNCTION("""COMPUTED_VALUE"""),0.0) -> 0 | M47: =IFERROR(__xludf.DUMMYFUNCTION("""COMPUTED_VALUE"""),33810.0) -> 33810 | N47: =IFERROR(__xludf.DUMMYFUNCTION("""COMPUTED_VALUE"""),0.0) -> 0 | O47: =IFERROR(__xludf.DUMMYFUNCTION("""COMPUTED_VALUE"""),33810.0) -> 33810 | P47: =IFERROR(__xludf.DUMMYFUNCTION("""COMPUTED_VALUE"""),1691.0) -> 1691 | Q47: =IFERROR(__xludf.DUMMYFUNCTION("""COMPUTED_VALUE"""),"Dine In") -> Dine In | R47: =IFERROR(__xludf.DUMMYFUNCTION("""COMPUTED_VALUE"""),"Kedai") -> Kedai | S47: =IFERROR(__xludf.DUMMYFUNCTION("""COMPUTED_VALUE"""),"Temu Roti") -> Temu Roti | T47: =IFERROR(__xludf.DUMMYFUNCTION("""COMPUTED_VALUE"""),"Owner") -> Owner | X47: =IFERROR(__xludf.DUMMYFUNCTION("""COMPUTED_VALUE"""),"Closed") -> Closed
A48: 29/09/2024 15:23,2-9549,Sale,Roti,10055,Roti Gandum Cokelat 2 pcs,,,1.000,34762.00,0.00,34762.00,0.00,34762.00,1738.00,Dine In,Kedai,Temu Roti,Owner,,,,Closed | B48: =IFERROR(__xludf.DUMMYFUNCTION("SPLIT(A48,"","",0,0)"),45564.64097222222) -> 45564.641 | C48: =IFERROR(__xludf.DUMMYFUNCTION("""COMPUTED_VALUE"""),2793773.0) -> 2793773 | D48: =IFERROR(__xludf.DUMMYFUNCTION("""COMPUTED_VALUE"""),"Sale") -> Sale | E48: =IFERROR(__xludf.DUMMYFUNCTION("""COMPUTED_VALUE"""),"Roti") -> Roti | F48: =IFERROR(__xludf.DUMMYFUNCTION("""COMPUTED_VALUE"""),10055.0) -> 10055 | G48: =IFERROR(__xludf.DUMMYFUNCTION("""COMPUTED_VALUE"""),"Roti Gandum Cokelat 2 pcs") -> Roti Gandum Cokelat 2 pcs | J48: =IFERROR(__xludf.DUMMYFUNCTION("""COMPUTED_VALUE"""),1.0) -> 1 | K48: =IFERROR(__xludf.DUMMYFUNCTION("""COMPUTED_VALUE"""),34762.0) -> 34762 | L48: =IFERROR(__xludf.DUMMYFUNCTION("""COMPUTED_VALUE"""),0.0) -> 0 | M48: =IFERROR(__xludf.DUMMYFUNCTION("""COMPUTED_VALUE"""),34762.0) -> 34762 | N48: =IFERROR(__xludf.DUMMYFUNCTION("""COMPUTED_VALUE"""),0.0) -> 0 | O48: =IFERROR(__xludf.DUMMYFUNCTION("""COMPUTED_VALUE"""),34762.0) -> 34762 | P48: =IFERROR(__xludf.DUMMYFUNCTION("""COMPUTED_VALUE"""),1738.0) -> 1738 | Q48: =IFERROR(__xludf.DUMMYFUNCTION("""COMPUTED_VALUE"""),"Dine In") -> Dine In | R48: =IFERROR(__xludf.DUMMYFUNCTION("""COMPUTED_VALUE"""),"Kedai") -> Kedai | S48: =IFERROR(__xludf.DUMMYFUNCTION("""COMPUTED_VALUE"""),"Temu Roti") -> Temu Roti | T48: =IFERROR(__xludf.DUMMYFUNCTION("""COMPUTED_VALUE"""),"Owner") -> Owner | X48: =IFERROR(__xludf.DUMMYFUNCTION("""COMPUTED_VALUE"""),"Closed") -> Closed
A49: 29/09/2024 15:23,2-9549,Sale,Minuman,10107,Korean Mango Fresh Milk,,,1.000,26667.00,0.00,26667.00,0.00,26667.00,1333.00,Dine In,Kedai,Temu Roti,Owner,,,,Closed | B49: =IFERROR(__xludf.DUMMYFUNCTION("SPLIT(A49,"","",0,0)"),45564.64097222222) -> 45564.641 | C49: =IFERROR(__xludf.DUMMYFUNCTION("""COMPUTED_VALUE"""),2793773.0) -> 2793773 | D49: =IFERROR(__xludf.DUMMYFUNCTION("""COMPUTED_VALUE"""),"Sale") -> Sale | E49: =IFERROR(__xludf.DUMMYFUNCTION("""COMPUTED_VALUE"""),"Minuman") -> Minuman | F49: =IFERROR(__xludf.DUMMYFUNCTION("""COMPUTED_VALUE"""),10107.0) -> 10107 | G49: =IFERROR(__xludf.DUMMYFUNCTION("""COMPUTED_VALUE"""),"Korean Mango Fresh Milk") -> Korean Mango Fresh Milk | J49: =IFERROR(__xludf.DUMMYFUNCTION("""COMPUTED_VALUE"""),1.0) -> 1 | K49: =IFERROR(__xludf.DUMMYFUNCTION("""COMPUTED_VALUE"""),26667.0) -> 26667 | L49: =IFERROR(__xludf.DUMMYFUNCTION("""COMPUTED_VALUE"""),0.0) -> 0 | M49: =IFERROR(__xludf.DUMMYFUNCTION("""COMPUTED_VALUE"""),26667.0) -> 26667 | N49: =IFERROR(__xludf.DUMMYFUNCTION("""COMPUTED_VALUE"""),0.0) -> 0 | O49: =IFERROR(__xludf.DUMMYFUNCTION("""COMPUTED_VALUE"""),26667.0) -> 26667 | P49: =IFERROR(__xludf.DUMMYFUNCTION("""COMPUTED_VALUE"""),1333.0) -> 1333 | Q49: =IFERROR(__xludf.DUMMYFUNCTION("""COMPUTED_VALUE"""),"Dine In") -> Dine In | R49: =IFERROR(__xludf.DUMMYFUNCTION("""COMPUTED_VALUE"""),"Kedai") -> Kedai | S49: =IFERROR(__xludf.DUMMYFUNCTION("""COMPUTED_VALUE"""),"Temu Roti") -> Temu Roti | T49: =IFERROR(__xludf.DUMMYFUNCTION("""COMPUTED_VALUE"""),"Owner") -> Owner | X49: =IFERROR(__xludf.DUMMYFUNCTION("""COMPUTED_VALUE"""),"Closed") -> Closed
A50: 29/09/2024 15:23,2-9549,Sale,Minuman,10106,Korean Strawberry Fresh Milk,,,1.000,26667.00,0.00,26667.00,0.00,26667.00,1333.00,Dine In,Kedai,Temu Roti,Owner,,,,Closed | B50: =IFERROR(__xludf.DUMMYFUNCTION("SPLIT(A50,"","",0,0)"),45564.64097222222) -> 45564.641 | C50: =IFERROR(__xludf.DUMMYFUNCTION("""COMPUTED_VALUE"""),2793773.0) -> 2793773 | D50: =IFERROR(__xludf.DUMMYFUNCTION("""COMPUTED_VALUE"""),"Sale") -> Sale | E50: =IFERROR(__xludf.DUMMYFUNCTION("""COMPUTED_VALUE"""),"Minuman") -> Minuman | F50: =IFERROR(__xludf.DUMMYFUNCTION("""COMPUTED_VALUE"""),10106.0) -> 10106 | G50: =IFERROR(__xludf.DUMMYFUNCTION("""COMPUTED_VALUE"""),"Korean Strawberry Fresh Milk") -> Korean Strawberry Fresh Milk | J50: =IFERROR(__xludf.DUMMYFUNCTION("""COMPUTED_VALUE"""),1.0) -> 1 | K50: =IFERROR(__xludf.DUMMYFUNCTION("""COMPUTED_VALUE"""),26667.0) -> 26667 | L50: =IFERROR(__xludf.DUMMYFUNCTION("""COMPUTED_VALUE"""),0.0) -> 0 | M50: =IFERROR(__xludf.DUMMYFUNCTION("""COMPUTED_VALUE"""),26667.0) -> 26667 | N50: =IFERROR(__xludf.DUMMYFUNCTION("""COMPUTED_VALUE"""),0.0) -> 0 | O50: =IFERROR(__xludf.DUMMYFUNCTION("""COMPUTED_VALUE"""),26667.0) -> 26667 | P50: =IFERROR(__xludf.DUMMYFUNCTION("""COMPUTED_VALUE"""),1333.0) -> 1333 | Q50: =IFERROR(__xludf.DUMMYFUNCTION("""COMPUTED_VALUE"""),"Dine In") -> Dine In | R50: =IFERROR(__xludf.DUMMYFUNCTION("""COMPUTED_VALUE"""),"Kedai") -> Kedai | S50: =IFERROR(__xludf.DUMMYFUNCTION("""COMPUTED_VALUE"""),"Temu Roti") -> Temu Roti | T50: =IFERROR(__xludf.DUMMYFUNCTION("""COMPUTED_VALUE"""),"Owner") -> Owner | X50: =IFERROR(__xludf.DUMMYFUNCTION("""COMPUTED_VALUE"""),"Closed") -> Closed
A51: 29/09/2024 14:35,2-9548,Refund,Roti,10007,Roti cranberry 2 pcs,,,-1.000,-33810.00,0.00,-33810.00,-0.00,-33810.00,-1691.00,Take Away,Kedai,Temu Roti,Owner,,,,Closed | B51: =IFERROR(__xludf.DUMMYFUNCTION("SPLIT(A51,"","",0,0)"),45564.60763888889) -> 45564.608 | C51: =IFERROR(__xludf.DUMMYFUNCTION("""COMPUTED_VALUE"""),2793407.0) -> 2793407 | D51: =IFERROR(__xludf.DUMMYFUNCTION("""COMPUTED_VALUE"""),"Refund") -> Refund | E51: =IFERROR(__xludf.DUMMYFUNCTION("""COMPUTED_VALUE"""),"Roti") -> Roti | F51: =IFERROR(__xludf.DUMMYFUNCTION("""COMPUTED_VALUE"""),10007.0) -> 10007 | G51: =IFERROR(__xludf.DUMMYFUNCTION("""COMPUTED_VALUE"""),"Roti cranberry 2 pcs") -> Roti cranberry 2 pcs | J51: =IFERROR(__xludf.DUMMYFUNCTION("""COMPUTED_VALUE"""),-1.0) -> -1 | K51: =IFERROR(__xludf.DUMMYFUNCTION("""COMPUTED_VALUE"""),-33810.0) -> -33810 | L51: =IFERROR(__xludf.DUMMYFUNCTION("""COMPUTED_VALUE"""),0.0) -> 0 | M51: =IFERROR(__xludf.DUMMYFUNCTION("""COMPUTED_VALUE"""),-33810.0) -> -33810 | N51: =IFERROR(__xludf.DUMMYFUNCTION("""COMPUTED_VALUE"""),0.0) -> 0 | O51: =IFERROR(__xludf.DUMMYFUNCTION("""COMPUTED_VALUE"""),-33810.0) -> -33810 | P51: =IFERROR(__xludf.DUMMYFUNCTION("""COMPUTED_VALUE"""),-1691.0) -> -1691 | Q51: =IFERROR(__xludf.DUMMYFUNCTION("""COMPUTED_VALUE"""),"Take Away") -> Take Away | R51: =IFERROR(__xludf.DUMMYFUNCTION("""COMPUTED_VALUE"""),"Kedai") -> Kedai | S51: =IFERROR(__xludf.DUMMYFUNCTION("""COMPUTED_VALUE"""),"Temu Roti") -> Temu Roti | T51: =IFERROR(__xludf.DUMMYFUNCTION("""COMPUTED_VALUE"""),"Owner") -> Owner | X51: =IFERROR(__xludf.DUMMYFUNCTION("""COMPUTED_VALUE"""),"Closed") -> Closed
A52: 29/09/2024 14:35,2-9548,Refund,Roti,10005,Roti Gandum Cokelat,,,-1.000,-19524.00,0.00,-19524.00,-0.00,-19524.00,-976.00,Take Away,Kedai,Temu Roti,Owner,,,,Closed | B52: =IFERROR(__xludf.DUMMYFUNCTION("SPLIT(A52,"","",0,0)"),45564.60763888889) -> 45564.608 | C52: =IFERROR(__xludf.DUMMYFUNCTION("""COMPUTED_VALUE"""),2793407.0) -> 2793407 | D52: =IFERROR(__xludf.DUMMYFUNCTION("""COMPUTED_VALUE"""),"Refund") -> Refund | E52: =IFERROR(__xludf.DUMMYFUNCTION("""COMPUTED_VALUE"""),"Roti") -> Roti | F52: =IFERROR(__xludf.DUMMYFUNCTION("""COMPUTED_VALUE"""),10005.0) -> 10005 | G52: =IFERROR(__xludf.DUMMYFUNCTION("""COMPUTED_VALUE"""),"Roti Gandum Cokelat") -> Roti Gandum Cokelat | J52: =IFERROR(__xludf.DUMMYFUNCTION("""COMPUTED_VALUE"""),-1.0) -> -1 | K52: =IFERROR(__xludf.DUMMYFUNCTION("""COMPUTED_VALUE"""),-19524.0) -> -19524 | L52: =IFERROR(__xludf.DUMMYFUNCTION("""COMPUTED_VALUE"""),0.0) -> 0 | M52: =IFERROR(__xludf.DUMMYFUNCTION("""COMPUTED_VALUE"""),-19524.0) -> -19524 | N52: =IFERROR(__xludf.DUMMYFUNCTION("""COMPUTED_VALUE"""),0.0) -> 0 | O52: =IFERROR(__xludf.DUMMYFUNCTION("""COMPUTED_VALUE"""),-19524.0) -> -19524 | P52: =IFERROR(__xludf.DUMMYFUNCTION("""COMPUTED_VALUE"""),-976.0) -> -976 | Q52: =IFERROR(__xludf.DUMMYFUNCTION("""COMPUTED_VALUE"""),"Take Away") -> Take Away | R52: =IFERROR(__xludf.DUMMYFUNCTION("""COMPUTED_VALUE"""),"Kedai") -> Kedai | S52: =IFERROR(__xludf.DUMMYFUNCTION("""COMPUTED_VALUE"""),"Temu Roti") -> Temu Roti | T52: =IFERROR(__xludf.DUMMYFUNCTION("""COMPUTED_VALUE"""),"Owner") -> Owner | X52: =IFERROR(__xludf.DUMMYFUNCTION("""COMPUTED_VALUE"""),"Closed") -> Closed
A53: 29/09/2024 14:35,2-9548,Refund,Minuman,10013,Kopi cur,,,-1.000,-23333.00,0.00,-23333.00,-0.00,-23333.00,-1166.00,Take Away,Kedai,Temu Roti,Owner,,,,Closed | B53: =IFERROR(__xludf.DUMMYFUNCTION("SPLIT(A53,"","",0,0)"),45564.60763888889) -> 45564.608 | C53: =IFERROR(__xludf.DUMMYFUNCTION("""COMPUTED_VALUE"""),2793407.0) -> 2793407 | D53: =IFERROR(__xludf.DUMMYFUNCTION("""COMPUTED_VALUE"""),"Refund") -> Refund | E53: =IFERROR(__xludf.DUMMYFUNCTION("""COMPUTED_VALUE"""),"Minuman") -> Minuman | F53: =IFERROR(__xludf.DUMMYFUNCTION("""COMPUTED_VALUE"""),10013.0) -> 10013 | G53: =IFERROR(__xludf.DUMMYFUNCTION("""COMPUTED_VALUE"""),"Kopi cur") -> Kopi cur | J53: =IFERROR(__xludf.DUMMYFUNCTION("""COMPUTED_VALUE"""),-1.0) -> -1 | K53: =IFERROR(__xludf.DUMMYFUNCTION("""COMPUTED_VALUE"""),-23333.0) -> -23333 | L53: =IFERROR(__xludf.DUMMYFUNCTION("""COMPUTED_VALUE"""),0.0) -> 0 | M53: =IFERROR(__xludf.DUMMYFUNCTION("""COMPUTED_VALUE"""),-23333.0) -> -23333 | N53: =IFERROR(__xludf.DUMMYFUNCTION("""COMPUTED_VALUE"""),0.0) -> 0 | O53: =IFERROR(__xludf.DUMMYFUNCTION("""COMPUTED_VALUE"""),-23333.0) -> -23333 | P53: =IFERROR(__xludf.DUMMYFUNCTION("""COMPUTED_VALUE"""),-1166.0) -> -1166 | Q53: =IFERROR(__xludf.DUMMYFUNCTION("""COMPUTED_VALUE"""),"Take Away") -> Take Away | R53: =IFERROR(__xludf.DUMMYFUNCTION("""COMPUTED_VALUE"""),"Kedai") -> Kedai | S53: =IFERROR(__xludf.DUMMYFUNCTION("""COMPUTED_VALUE"""),"Temu Roti") -> Temu Roti | T53: =IFERROR(__xludf.DUMMYFUNCTION("""COMPUTED_VALUE"""),"Owner") -> Owner | X53: =IFERROR(__xludf.DUMMYFUNCTION("""COMPUTED_VALUE"""),"Closed") -> Closed
A54: 29/09/2024 14:13,2-9547,Sale,Roti,10055,Roti Gandum Cokelat 2 pcs,,,1.000,34762.00,0.00,34762.00,0.00,34762.00,1738.00,Dine In,Kedai,Temu Roti,Owner,,,,Closed | B54: =IFERROR(__xludf.DUMMYFUNCTION("SPLIT(A54,"","",0,0)"),45564.592361111114) -> 45564.592 | C54: =IFERROR(__xludf.DUMMYFUNCTION("""COMPUTED_VALUE"""),2793042.0) -> 2793042 | D54: =IFERROR(__xludf.DUMMYFUNCTION("""COMPUTED_VALUE"""),"Sale") -> Sale | E54: =IFERROR(__xludf.DUMMYFUNCTION("""COMPUTED_VALUE"""),"Roti") -> Roti | F54: =IFERROR(__xludf.DUMMYFUNCTION("""COMPUTED_VALUE"""),10055.0) -> 10055 | G54: =IFERROR(__xludf.DUMMYFUNCTION("""COMPUTED_VALUE"""),"Roti Gandum Cokelat 2 pcs") -> Roti Gandum Cokelat 2 pcs | J54: =IFERROR(__xludf.DUMMYFUNCTION("""COMPUTED_VALUE"""),1.0) -> 1 | K54: =IFERROR(__xludf.DUMMYFUNCTION("""COMPUTED_VALUE"""),34762.0) -> 34762 | L54: =IFERROR(__xludf.DUMMYFUNCTION("""COMPUTED_VALUE"""),0.0) -> 0 | M54: =IFERROR(__xludf.DUMMYFUNCTION("""COMPUTED_VALUE"""),34762.0) -> 34762 | N54: =IFERROR(__xludf.DUMMYFUNCTION("""COMPUTED_VALUE"""),0.0) -> 0 | O54: =IFERROR(__xludf.DUMMYFUNCTION("""COMPUTED_VALUE"""),34762.0) -> 34762 | P54: =IFERROR(__xludf.DUMMYFUNCTION("""COMPUTED_VALUE"""),1738.0) -> 1738 | Q54: =IFERROR(__xludf.DUMMYFUNCTION("""COMPUTED_VALUE"""),"Dine In") -> Dine In | R54: =IFERROR(__xludf.DUMMYFUNCTION("""COMPUTED_VALUE"""),"Kedai") -> Kedai | S54: =IFERROR(__xludf.DUMMYFUNCTION("""COMPUTED_VALUE"""),"Temu Roti") -> Temu Roti | T54: =IFERROR(__xludf.DUMMYFUNCTION("""COMPUTED_VALUE"""),"Owner") -> Owner | X54: =IFERROR(__xludf.DUMMYFUNCTION("""COMPUTED_VALUE"""),"Closed") -> Closed
A55: 29/09/2024 14:13,2-9547,Sale,Kudapan,10009,Jamur Enoki Krispi,,,1.000,26667.00,0.00,26667.00,0.00,26667.00,1333.00,Dine In,Kedai,Temu Roti,Owner,,,,Closed | B55: =IFERROR(__xludf.DUMMYFUNCTION("SPLIT(A55,"","",0,0)"),45564.592361111114) -> 45564.592 | C55: =IFERROR(__xludf.DUMMYFUNCTION("""COMPUTED_VALUE"""),2793042.0) -> 2793042 | D55: =IFERROR(__xludf.DUMMYFUNCTION("""COMPUTED_VALUE"""),"Sale") -> Sale | E55: =IFERROR(__xludf.DUMMYFUNCTION("""COMPUTED_VALUE"""),"Kudapan") -> Kudapan | F55: =IFERROR(__xludf.DUMMYFUNCTION("""COMPUTED_VALUE"""),10009.0) -> 10009 | G55: =IFERROR(__xludf.DUMMYFUNCTION("""COMPUTED_VALUE"""),"Jamur Enoki Krispi") -> Jamur Enoki Krispi | J55: =IFERROR(__xludf.DUMMYFUNCTION("""COMPUTED_VALUE"""),1.0) -> 1 | K55: =IFERROR(__xludf.DUMMYFUNCTION("""COMPUTED_VALUE"""),26667.0) -> 26667 | L55: =IFERROR(__xludf.DUMMYFUNCTION("""COMPUTED_VALUE"""),0.0) -> 0 | M55: =IFERROR(__xludf.DUMMYFUNCTION("""COMPUTED_VALUE"""),26667.0) -> 26667 | N55: =IFERROR(__xludf.DUMMYFUNCTION("""COMPUTED_VALUE"""),0.0) -> 0 | O55: =IFERROR(__xludf.DUMMYFUNCTION("""COMPUTED_VALUE"""),26667.0) -> 26667 | P55: =IFERROR(__xludf.DUMMYFUNCTION("""COMPUTED_VALUE"""),1333.0) -> 1333 | Q55: =IFERROR(__xludf.DUMMYFUNCTION("""COMPUTED_VALUE"""),"Dine In") -> Dine In | R55: =IFERROR(__xludf.DUMMYFUNCTION("""COMPUTED_VALUE"""),"Kedai") -> Kedai | S55: =IFERROR(__xludf.DUMMYFUNCTION("""COMPUTED_VALUE"""),"Temu Roti") -> Temu Roti | T55: =IFERROR(__xludf.DUMMYFUNCTION("""COMPUTED_VALUE"""),"Owner") -> Owner | X55: =IFERROR(__xludf.DUMMYFUNCTION("""COMPUTED_VALUE"""),"Closed") -> Closed
A56: 29/09/2024 14:13,2-9547,Sale,Minuman,10117,Teh Manis Dingin,,,1.000,14286.00,0.00,14286.00,0.00,14286.00,715.00,Dine In,Kedai,Temu Roti,Owner,,,,Closed | B56: =IFERROR(__xludf.DUMMYFUNCTION("SPLIT(A56,"","",0,0)"),45564.592361111114) -> 45564.592 | C56: =IFERROR(__xludf.DUMMYFUNCTION("""COMPUTED_VALUE"""),2793042.0) -> 2793042 | D56: =IFERROR(__xludf.DUMMYFUNCTION("""COMPUTED_VALUE"""),"Sale") -> Sale | E56: =IFERROR(__xludf.DUMMYFUNCTION("""COMPUTED_VALUE"""),"Minuman") -> Minuman | F56: =IFERROR(__xludf.DUMMYFUNCTION("""COMPUTED_VALUE"""),10117.0) -> 10117 | G56: =IFERROR(__xludf.DUMMYFUNCTION("""COMPUTED_VALUE"""),"Teh Manis Dingin") -> Teh Manis Dingin | J56: =IFERROR(__xludf.DUMMYFUNCTION("""COMPUTED_VALUE"""),1.0) -> 1 | K56: =IFERROR(__xludf.DUMMYFUNCTION("""COMPUTED_VALUE"""),14286.0) -> 14286 | L56: =IFERROR(__xludf.DUMMYFUNCTION("""COMPUTED_VALUE"""),0.0) -> 0 | M56: =IFERROR(__xludf.DUMMYFUNCTION("""COMPUTED_VALUE"""),14286.0) -> 14286 | N56: =IFERROR(__xludf.DUMMYFUNCTION("""COMPUTED_VALUE"""),0.0) -> 0 | O56: =IFERROR(__xludf.DUMMYFUNCTION("""COMPUTED_VALUE"""),14286.0) -> 14286 | P56: =IFERROR(__xludf.DUMMYFUNCTION("""COMPUTED_VALUE"""),715.0) -> 715 | Q56: =IFERROR(__xludf.DUMMYFUNCTION("""COMPUTED_VALUE"""),"Dine In") -> Dine In | R56: =IFERROR(__xludf.DUMMYFUNCTION("""COMPUTED_VALUE"""),"Kedai") -> Kedai | S56: =IFERROR(__xludf.DUMMYFUNCTION("""COMPUTED_VALUE"""),"Temu Roti") -> Temu Roti | T56: =IFERROR(__xludf.DUMMYFUNCTION("""COMPUTED_VALUE"""),"Owner") -> Owner | X56: =IFERROR(__xludf.DUMMYFUNCTION("""COMPUTED_VALUE"""),"Closed") -> Closed
A57: 29/09/2024 14:13,2-9547,Sale,Minuman,10123,Rempah Madu Dingin,,,1.000,21905.00,0.00,21905.00,0.00,21905.00,1095.00,Dine In,Kedai,Temu Roti,Owner,,,,Closed | B57: =IFERROR(__xludf.DUMMYFUNCTION("SPLIT(A57,"","",0,0)"),45564.592361111114) -> 45564.592 | C57: =IFERROR(__xludf.DUMMYFUNCTION("""COMPUTED_VALUE"""),2793042.0) -> 2793042 | D57: =IFERROR(__xludf.DUMMYFUNCTION("""COMPUTED_VALUE"""),"Sale") -> Sale | E57: =IFERROR(__xludf.DUMMYFUNCTION("""COMPUTED_VALUE"""),"Minuman") -> Minuman | F57: =IFERROR(__xludf.DUMMYFUNCTION("""COMPUTED_VALUE"""),10123.0) -> 10123 | G57: =IFERROR(__xludf.DUMMYFUNCTION("""COMPUTED_VALUE"""),"Rempah Madu Dingin") -> Rempah Madu Dingin | J57: =IFERROR(__xludf.DUMMYFUNCTION("""COMPUTED_VALUE"""),1.0) -> 1 | K57: =IFERROR(__xludf.DUMMYFUNCTION("""COMPUTED_VALUE"""),21905.0) -> 21905 | L57: =IFERROR(__xludf.DUMMYFUNCTION("""COMPUTED_VALUE"""),0.0) -> 0 | M57: =IFERROR(__xludf.DUMMYFUNCTION("""COMPUTED_VALUE"""),21905.0) -> 21905 | N57: =IFERROR(__xludf.DUMMYFUNCTION("""COMPUTED_VALUE"""),0.0) -> 0 | O57: =IFERROR(__xludf.DUMMYFUNCTION("""COMPUTED_VALUE"""),21905.0) -> 21905 | P57: =IFERROR(__xludf.DUMMYFUNCTION("""COMPUTED_VALUE"""),1095.0) -> 1095 | Q57: =IFERROR(__xludf.DUMMYFUNCTION("""COMPUTED_VALUE"""),"Dine In") -> Dine In | R57: =IFERROR(__xludf.DUMMYFUNCTION("""COMPUTED_VALUE"""),"Kedai") -> Kedai | S57: =IFERROR(__xludf.DUMMYFUNCTION("""COMPUTED_VALUE"""),"Temu Roti") -> Temu Roti | T57: =IFERROR(__xludf.DUMMYFUNCTION("""COMPUTED_VALUE"""),"Owner") -> Owner | X57: =IFERROR(__xludf.DUMMYFUNCTION("""COMPUTED_VALUE"""),"Closed") -> Closed
A58: 29/09/2024 14:13,2-9547,Sale,Minuman,10126,Chamomile Lemongrass Hot Artisan Tea,,,1.000,23810.00,0.00,23810.00,0.00,23810.00,1191.00,Dine In,Kedai,Temu Roti,Owner,,,,Closed | B58: =IFERROR(__xludf.DUMMYFUNCTION("SPLIT(A58,"","",0,0)"),45564.592361111114) -> 45564.592 | C58: =IFERROR(__xludf.DUMMYFUNCTION("""COMPUTED_VALUE"""),2793042.0) -> 2793042 | D58: =IFERROR(__xludf.DUMMYFUNCTION("""COMPUTED_VALUE"""),"Sale") -> Sale | E58: =IFERROR(__xludf.DUMMYFUNCTION("""COMPUTED_VALUE"""),"Minuman") -> Minuman | F58: =IFERROR(__xludf.DUMMYFUNCTION("""COMPUTED_VALUE"""),10126.0) -> 10126 | G58: =IFERROR(__xludf.DUMMYFUNCTION("""COMPUTED_VALUE"""),"Chamomile Lemongrass Hot Artisan Tea") -> Chamomile Lemongrass Hot Artisan Tea | J58: =IFERROR(__xludf.DUMMYFUNCTION("""COMPUTED_VALUE"""),1.0) -> 1 | K58: =IFERROR(__xludf.DUMMYFUNCTION("""COMPUTED_VALUE"""),23810.0) -> 23810 | L58: =IFERROR(__xludf.DUMMYFUNCTION("""COMPUTED_VALUE"""),0.0) -> 0 | M58: =IFERROR(__xludf.DUMMYFUNCTION("""COMPUTED_VALUE"""),23810.0) -> 23810 | N58: =IFERROR(__xludf.DUMMYFUNCTION("""COMPUTED_VALUE"""),0.0) -> 0 | O58: =IFERROR(__xludf.DUMMYFUNCTION("""COMPUTED_VALUE"""),23810.0) -> 23810 | P58: =IFERROR(__xludf.DUMMYFUNCTION("""COMPUTED_VALUE"""),1191.0) -> 1191 | Q58: =IFERROR(__xludf.DUMMYFUNCTION("""COMPUTED_VALUE"""),"Dine In") -> Dine In | R58: =IFERROR(__xludf.DUMMYFUNCTION("""COMPUTED_VALUE"""),"Kedai") -> Kedai | S58: =IFERROR(__xludf.DUMMYFUNCTION("""COMPUTED_VALUE"""),"Temu Roti") -> Temu Roti | T58: =IFERROR(__xludf.DUMMYFUNCTION("""COMPUTED_VALUE"""),"Owner") -> Owner | X58: =IFERROR(__xludf.DUMMYFUNCTION("""COMPUTED_VALUE"""),"Closed") -> Closed
A59: 29/09/2024 14:10,2-9546,Refund,Minuman,10125,Gula Asam Dingin,,,-1.000,-20476.00,0.00,-20476.00,-0.00,-20476.00,-1024.00,Dine In,Kedai,Temu Roti,Owner,,,,Closed | B59: =IFERROR(__xludf.DUMMYFUNCTION("SPLIT(A59,"","",0,0)"),45564.59027777778) -> 45564.59 | C59: =IFERROR(__xludf.DUMMYFUNCTION("""COMPUTED_VALUE"""),2792677.0) -> 2792677 | D59: =IFERROR(__xludf.DUMMYFUNCTION("""COMPUTED_VALUE"""),"Refund") -> Refund | E59: =IFERROR(__xludf.DUMMYFUNCTION("""COMPUTED_VALUE"""),"Minuman") -> Minuman | F59: =IFERROR(__xludf.DUMMYFUNCTION("""COMPUTED_VALUE"""),10125.0) -> 10125 | G59: =IFERROR(__xludf.DUMMYFUNCTION("""COMPUTED_VALUE"""),"Gula Asam Dingin") -> Gula Asam Dingin | J59: =IFERROR(__xludf.DUMMYFUNCTION("""COMPUTED_VALUE"""),-1.0) -> -1 | K59: =IFERROR(__xludf.DUMMYFUNCTION("""COMPUTED_VALUE"""),-20476.0) -> -20476 | L59: =IFERROR(__xludf.DUMMYFUNCTION("""COMPUTED_VALUE"""),0.0) -> 0 | M59: =IFERROR(__xludf.DUMMYFUNCTION("""COMPUTED_VALUE"""),-20476.0) -> -20476 | N59: =IFERROR(__xludf.DUMMYFUNCTION("""COMPUTED_VALUE"""),0.0) -> 0 | O59: =IFERROR(__xludf.DUMMYFUNCTION("""COMPUTED_VALUE"""),-20476.0) -> -20476 | P59: =IFERROR(__xludf.DUMMYFUNCTION("""COMPUTED_VALUE"""),-1024.0) -> -1024 | Q59: =IFERROR(__xludf.DUMMYFUNCTION("""COMPUTED_VALUE"""),"Dine In") -> Dine In | R59: =IFERROR(__xludf.DUMMYFUNCTION("""COMPUTED_VALUE"""),"Kedai") -> Kedai | S59: =IFERROR(__xludf.DUMMYFUNCTION("""COMPUTED_VALUE"""),"Temu Roti") -> Temu Roti | T59: =IFERROR(__xludf.DUMMYFUNCTION("""COMPUTED_VALUE"""),"Owner") -> Owner | X59: =IFERROR(__xludf.DUMMYFUNCTION("""COMPUTED_VALUE"""),"Closed") -> Closed
A60: 29/09/2024 14:10,2-9546,Refund,Minuman,10128,Es Kopi Susu,,,-1.000,-23333.00,0.00,-23333.00,-0.00,-23333.00,-1166.00,Dine In,Kedai,Temu Roti,Owner,,,,Closed | B60: =IFERROR(__xludf.DUMMYFUNCTION("SPLIT(A60,"","",0,0)"),45564.59027777778) -> 45564.59 | C60: =IFERROR(__xludf.DUMMYFUNCTION("""COMPUTED_VALUE"""),2792677.0) -> 2792677 | D60: =IFERROR(__xludf.DUMMYFUNCTION("""COMPUTED_VALUE"""),"Refund") -> Refund | E60: =IFERROR(__xludf.DUMMYFUNCTION("""COMPUTED_VALUE"""),"Minuman") -> Minuman | F60: =IFERROR(__xludf.DUMMYFUNCTION("""COMPUTED_VALUE"""),10128.0) -> 10128 | G60: =IFERROR(__xludf.DUMMYFUNCTION("""COMPUTED_VALUE"""),"Es Kopi Susu") -> Es Kopi Susu | J60: =IFERROR(__xludf.DUMMYFUNCTION("""COMPUTED_VALUE"""),-1.0) -> -1 | K60: =IFERROR(__xludf.DUMMYFUNCTION("""COMPUTED_VALUE"""),-23333.0) -> -23333 | L60: =IFERROR(__xludf.DUMMYFUNCTION("""COMPUTED_VALUE"""),0.0) -> 0 | M60: =IFERROR(__xludf.DUMMYFUNCTION("""COMPUTED_VALUE"""),-23333.0) -> -23333 | N60: =IFERROR(__xludf.DUMMYFUNCTION("""COMPUTED_VALUE"""),0.0) -> 0 | O60: =IFERROR(__xludf.DUMMYFUNCTION("""COMPUTED_VALUE"""),-23333.0) -> -23333 | P60: =IFERROR(__xludf.DUMMYFUNCTION("""COMPUTED_VALUE"""),-1166.0) -> -1166 | Q60: =IFERROR(__xludf.DUMMYFUNCTION("""COMPUTED_VALUE"""),"Dine In") -> Dine In | R60: =IFERROR(__xludf.DUMMYFUNCTION("""COMPUTED_VALUE"""),"Kedai") -> Kedai | S60: =IFERROR(__xludf.DUMMYFUNCTION("""COMPUTED_VALUE"""),"Temu Roti") -> Temu Roti | T60: =IFERROR(__xludf.DUMMYFUNCTION("""COMPUTED_VALUE"""),"Owner") -> Owner | X60: =IFERROR(__xludf.DUMMYFUNCTION("""COMPUTED_VALUE"""),"Closed") -> Closed
A61: 29/09/2024 14:10,2-9546,Refund,Roti,10055,Roti Gandum Cokelat 2 pcs,,,-2.000,-69524.00,0.00,-69524.00,-0.00,-69524.00,-3477.00,Dine In,Kedai,Temu Roti,Owner,,,,Closed | B61: =IFERROR(__xludf.DUMMYFUNCTION("SPLIT(A61,"","",0,0)"),45564.59027777778) -> 45564.59 | C61: =IFERROR(__xludf.DUMMYFUNCTION("""COMPUTED_VALUE"""),2792677.0) -> 2792677 | D61: =IFERROR(__xludf.DUMMYFUNCTION("""COMPUTED_VALUE"""),"Refund") -> Refund | E61: =IFERROR(__xludf.DUMMYFUNCTION("""COMPUTED_VALUE"""),"Roti") -> Roti | F61: =IFERROR(__xludf.DUMMYFUNCTION("""COMPUTED_VALUE"""),10055.0) -> 10055 | G61: =IFERROR(__xludf.DUMMYFUNCTION("""COMPUTED_VALUE"""),"Roti Gandum Cokelat 2 pcs") -> Roti Gandum Cokelat 2 pcs | J61: =IFERROR(__xludf.DUMMYFUNCTION("""COMPUTED_VALUE"""),-2.0) -> -2 | K61: =IFERROR(__xludf.DUMMYFUNCTION("""COMPUTED_VALUE"""),-69524.0) -> -69524 | L61: =IFERROR(__xludf.DUMMYFUNCTION("""COMPUTED_VALUE"""),0.0) -> 0 | M61: =IFERROR(__xludf.DUMMYFUNCTION("""COMPUTED_VALUE"""),-69524.0) -> -69524 | N61: =IFERROR(__xludf.DUMMYFUNCTION("""COMPUTED_VALUE"""),0.0) -> 0 | O61: =IFERROR(__xludf.DUMMYFUNCTION("""COMPUTED_VALUE"""),-69524.0) -> -69524 | P61: =IFERROR(__xludf.DUMMYFUNCTION("""COMPUTED_VALUE"""),-3477.0) -> -3477 | Q61: =IFERROR(__xludf.DUMMYFUNCTION("""COMPUTED_VALUE"""),"Dine In") -> Dine In | R61: =IFERROR(__xludf.DUMMYFUNCTION("""COMPUTED_VALUE"""),"Kedai") -> Kedai | S61: =IFERROR(__xludf.DUMMYFUNCTION("""COMPUTED_VALUE"""),"Temu Roti") -> Temu Roti | T61: =IFERROR(__xludf.DUMMYFUNCTION("""COMPUTED_VALUE"""),"Owner") -> Owner | X61: =IFERROR(__xludf.DUMMYFUNCTION("""COMPUTED_VALUE"""),"Closed") -> Closed
A62: 29/09/2024 14:07,2-9545,Sale,Roti,10002,Roti Cranberry,,,1.000,18571.00,0.00,18571.00,0.00,18571.00,929.00,Dine In,Kedai,Temu Roti,Owner,,,,Closed | B62: =IFERROR(__xludf.DUMMYFUNCTION("SPLIT(A62,"","",0,0)"),45564.58819444444) -> 45564.588 | C62: =IFERROR(__xludf.DUMMYFUNCTION("""COMPUTED_VALUE"""),2792312.0) -> 2792312 | D62: =IFERROR(__xludf.DUMMYFUNCTION("""COMPUTED_VALUE"""),"Sale") -> Sale | E62: =IFERROR(__xludf.DUMMYFUNCTION("""COMPUTED_VALUE"""),"Roti") -> Roti | F62: =IFERROR(__xludf.DUMMYFUNCTION("""COMPUTED_VALUE"""),10002.0) -> 10002 | G62: =IFERROR(__xludf.DUMMYFUNCTION("""COMPUTED_VALUE"""),"Roti Cranberry") -> Roti Cranberry | J62: =IFERROR(__xludf.DUMMYFUNCTION("""COMPUTED_VALUE"""),1.0) -> 1 | K62: =IFERROR(__xludf.DUMMYFUNCTION("""COMPUTED_VALUE"""),18571.0) -> 18571 | L62: =IFERROR(__xludf.DUMMYFUNCTION("""COMPUTED_VALUE"""),0.0) -> 0 | M62: =IFERROR(__xludf.DUMMYFUNCTION("""COMPUTED_VALUE"""),18571.0) -> 18571 | N62: =IFERROR(__xludf.DUMMYFUNCTION("""COMPUTED_VALUE"""),0.0) -> 0 | O62: =IFERROR(__xludf.DUMMYFUNCTION("""COMPUTED_VALUE"""),18571.0) -> 18571 | P62: =IFERROR(__xludf.DUMMYFUNCTION("""COMPUTED_VALUE"""),929.0) -> 929 | Q62: =IFERROR(__xludf.DUMMYFUNCTION("""COMPUTED_VALUE"""),"Dine In") -> Dine In | R62: =IFERROR(__xludf.DUMMYFUNCTION("""COMPUTED_VALUE"""),"Kedai") -> Kedai | S62: =IFERROR(__xludf.DUMMYFUNCTION("""COMPUTED_VALUE"""),"Temu Roti") -> Temu Roti | T62: =IFERROR(__xludf.DUMMYFUNCTION("""COMPUTED_VALUE"""),"Owner") -> Owner | X62: =IFERROR(__xludf.DUMMYFUNCTION("""COMPUTED_VALUE"""),"Closed") -> Closed
A63: 29/09/2024 14:07,2-9545,Sale,Roti,10005,Roti Gandum Cokelat,,,1.000,19524.00,0.00,19524.00,0.00,19524.00,976.00,Dine In,Kedai,Temu Roti,Owner,,,,Closed | B63: =IFERROR(__xludf.DUMMYFUNCTION("SPLIT(A63,"","",0,0)"),45564.58819444444) -> 45564.588 | C63: =IFERROR(__xludf.DUMMYFUNCTION("""COMPUTED_VALUE"""),2792312.0) -> 2792312 | D63: =IFERROR(__xludf.DUMMYFUNCTION("""COMPUTED_VALUE"""),"Sale") -> Sale | E63: =IFERROR(__xludf.DUMMYFUNCTION("""COMPUTED_VALUE"""),"Roti") -> Roti | F63: =IFERROR(__xludf.DUMMYFUNCTION("""COMPUTED_VALUE"""),10005.0) -> 10005 | G63: =IFERROR(__xludf.DUMMYFUNCTION("""COMPUTED_VALUE"""),"Roti Gandum Cokelat") -> Roti Gandum Cokelat | J63: =IFERROR(__xludf.DUMMYFUNCTION("""COMPUTED_VALUE"""),1.0) -> 1 | K63: =IFERROR(__xludf.DUMMYFUNCTION("""COMPUTED_VALUE"""),19524.0) -> 19524 | L63: =IFERROR(__xludf.DUMMYFUNCTION("""COMPUTED_VALUE"""),0.0) -> 0 | M63: =IFERROR(__xludf.DUMMYFUNCTION("""COMPUTED_VALUE"""),19524.0) -> 19524 | N63: =IFERROR(__xludf.DUMMYFUNCTION("""COMPUTED_VALUE"""),0.0) -> 0 | O63: =IFERROR(__xludf.DUMMYFUNCTION("""COMPUTED_VALUE"""),19524.0) -> 19524 | P63: =IFERROR(__xludf.DUMMYFUNCTION("""COMPUTED_VALUE"""),976.0) -> 976 | Q63: =IFERROR(__xludf.DUMMYFUNCTION("""COMPUTED_VALUE"""),"Dine In") -> Dine In | R63: =IFERROR(__xludf.DUMMYFUNCTION("""COMPUTED_VALUE"""),"Kedai") -> Kedai | S63: =IFERROR(__xludf.DUMMYFUNCTION("""COMPUTED_VALUE"""),"Temu Roti") -> Temu Roti | T63: =IFERROR(__xludf.DUMMYFUNCTION("""COMPUTED_VALUE"""),"Owner") -> Owner | X63: =IFERROR(__xludf.DUMMYFUNCTION("""COMPUTED_VALUE"""),"Closed") -> Closed
A64: 29/09/2024 14:07,2-9545,Sale,Minuman,10128,Es Kopi Susu,,,1.000,23333.00,0.00,23333.00,0.00,23333.00,1166.00,Dine In,Kedai,Temu Roti,Owner,,,,Closed | B64: =IFERROR(__xludf.DUMMYFUNCTION("SPLIT(A64,"","",0,0)"),45564.58819444444) -> 45564.588 | C64: =IFERROR(__xludf.DUMMYFUNCTION("""COMPUTED_VALUE"""),2792312.0) -> 2792312 | D64: =IFERROR(__xludf.DUMMYFUNCTION("""COMPUTED_VALUE"""),"Sale") -> Sale | E64: =IFERROR(__xludf.DUMMYFUNCTION("""COMPUTED_VALUE"""),"Minuman") -> Minuman | F64: =IFERROR(__xludf.DUMMYFUNCTION("""COMPUTED_VALUE"""),10128.0) -> 10128 | G64: =IFERROR(__xludf.DUMMYFUNCTION("""COMPUTED_VALUE"""),"Es Kopi Susu") -> Es Kopi Susu | J64: =IFERROR(__xludf.DUMMYFUNCTION("""COMPUTED_VALUE"""),1.0) -> 1 | K64: =IFERROR(__xludf.DUMMYFUNCTION("""COMPUTED_VALUE"""),23333.0) -> 23333 | L64: =IFERROR(__xludf.DUMMYFUNCTION("""COMPUTED_VALUE"""),0.0) -> 0 | M64: =IFERROR(__xludf.DUMMYFUNCTION("""COMPUTED_VALUE"""),23333.0) -> 23333 | N64: =IFERROR(__xludf.DUMMYFUNCTION("""COMPUTED_VALUE"""),0.0) -> 0 | O64: =IFERROR(__xludf.DUMMYFUNCTION("""COMPUTED_VALUE"""),23333.0) -> 23333 | P64: =IFERROR(__xludf.DUMMYFUNCTION("""COMPUTED_VALUE"""),1166.0) -> 1166 | Q64: =IFERROR(__xludf.DUMMYFUNCTION("""COMPUTED_VALUE"""),"Dine In") -> Dine In | R64: =IFERROR(__xludf.DUMMYFUNCTION("""COMPUTED_VALUE"""),"Kedai") -> Kedai | S64: =IFERROR(__xludf.DUMMYFUNCTION("""COMPUTED_VALUE"""),"Temu Roti") -> Temu Roti | T64: =IFERROR(__xludf.DUMMYFUNCTION("""COMPUTED_VALUE"""),"Owner") -> Owner | X64: =IFERROR(__xludf.DUMMYFUNCTION("""COMPUTED_VALUE"""),"Closed") -> Closed
A65: 29/09/2024 14:07,2-9545,Sale,Minuman,10125,Gula Asam Dingin,,,1.000,20476.00,0.00,20476.00,0.00,20476.00,1024.00,Dine In,Kedai,Temu Roti,Owner,,,,Closed | B65: =IFERROR(__xludf.DUMMYFUNCTION("SPLIT(A65,"","",0,0)"),45564.58819444444) -> 45564.588 | C65: =IFERROR(__xludf.DUMMYFUNCTION("""COMPUTED_VALUE"""),2792312.0) -> 2792312 | D65: =IFERROR(__xludf.DUMMYFUNCTION("""COMPUTED_VALUE"""),"Sale") -> Sale | E65: =IFERROR(__xludf.DUMMYFUNCTION("""COMPUTED_VALUE"""),"Minuman") -> Minuman | F65: =IFERROR(__xludf.DUMMYFUNCTION("""COMPUTED_VALUE"""),10125.0) -> 10125 | G65: =IFERROR(__xludf.DUMMYFUNCTION("""COMPUTED_VALUE"""),"Gula Asam Dingin") -> Gula Asam Dingin | J65: =IFERROR(__xludf.DUMMYFUNCTION("""COMPUTED_VALUE"""),1.0) -> 1 | K65: =IFERROR(__xludf.DUMMYFUNCTION("""COMPUTED_VALUE"""),20476.0) -> 20476 | L65: =IFERROR(__xludf.DUMMYFUNCTION("""COMPUTED_VALUE"""),0.0) -> 0 | M65: =IFERROR(__xludf.DUMMYFUNCTION("""COMPUTED_VALUE"""),20476.0) -> 20476 | N65: =IFERROR(__xludf.DUMMYFUNCTION("""COMPUTED_VALUE"""),0.0) -> 0 | O65: =IFERROR(__xludf.DUMMYFUNCTION("""COMPUTED_VALUE"""),20476.0) -> 20476 | P65: =IFERROR(__xludf.DUMMYFUNCTION("""COMPUTED_VALUE"""),1024.0) -> 1024 | Q65: =IFERROR(__xludf.DUMMYFUNCTION("""COMPUTED_VALUE"""),"Dine In") -> Dine In | R65: =IFERROR(__xludf.DUMMYFUNCTION("""COMPUTED_VALUE"""),"Kedai") -> Kedai | S65: =IFERROR(__xludf.DUMMYFUNCTION("""COMPUTED_VALUE"""),"Temu Roti") -> Temu Roti | T65: =IFERROR(__xludf.DUMMYFUNCTION("""COMPUTED_VALUE"""),"Owner") -> Owner | X65: =IFERROR(__xludf.DUMMYFUNCTION("""COMPUTED_VALUE"""),"Closed") -> Closed
A66: 29/09/2024 14:04,2-9544,Sale,Minuman,10125,Gula Asam Dingin,,,1.000,20476.00,0.00,20476.00,0.00,20476.00,1024.00,Dine In,Kedai,Temu Roti,Owner,,,,Closed | B66: =IFERROR(__xludf.DUMMYFUNCTION("SPLIT(A66,"","",0,0)"),45564.58611111111) -> 45564.586 | C66: =IFERROR(__xludf.DUMMYFUNCTION("""COMPUTED_VALUE"""),2791946.0) -> 2791946 | D66: =IFERROR(__xludf.DUMMYFUNCTION("""COMPUTED_VALUE"""),"Sale") -> Sale | E66: =IFERROR(__xludf.DUMMYFUNCTION("""COMPUTED_VALUE"""),"Minuman") -> Minuman | F66: =IFERROR(__xludf.DUMMYFUNCTION("""COMPUTED_VALUE"""),10125.0) -> 10125 | G66: =IFERROR(__xludf.DUMMYFUNCTION("""COMPUTED_VALUE"""),"Gula Asam Dingin") -> Gula Asam Dingin | J66: =IFERROR(__xludf.DUMMYFUNCTION("""COMPUTED_VALUE"""),1.0) -> 1 | K66: =IFERROR(__xludf.DUMMYFUNCTION("""COMPUTED_VALUE"""),20476.0) -> 20476 | L66: =IFERROR(__xludf.DUMMYFUNCTION("""COMPUTED_VALUE"""),0.0) -> 0 | M66: =IFERROR(__xludf.DUMMYFUNCTION("""COMPUTED_VALUE"""),20476.0) -> 20476 | N66: =IFERROR(__xludf.DUMMYFUNCTION("""COMPUTED_VALUE"""),0.0) -> 0 | O66: =IFERROR(__xludf.DUMMYFUNCTION("""COMPUTED_VALUE"""),20476.0) -> 20476 | P66: =IFERROR(__xludf.DUMMYFUNCTION("""COMPUTED_VALUE"""),1024.0) -> 1024 | Q66: =IFERROR(__xludf.DUMMYFUNCTION("""COMPUTED_VALUE"""),"Dine In") -> Dine In | R66: =IFERROR(__xludf.DUMMYFUNCTION("""COMPUTED_VALUE"""),"Kedai") -> Kedai | S66: =IFERROR(__xludf.DUMMYFUNCTION("""COMPUTED_VALUE"""),"Temu Roti") -> Temu Roti | T66: =IFERROR(__xludf.DUMMYFUNCTION("""COMPUTED_VALUE"""),"Owner") -> Owner | X66: =IFERROR(__xludf.DUMMYFUNCTION("""COMPUTED_VALUE"""),"Closed") -> Closed
A67: 29/09/2024 14:04,2-9544,Sale,Minuman,10128,Es Kopi Susu,,,1.000,23333.00,0.00,23333.00,0.00,23333.00,1166.00,Dine In,Kedai,Temu Roti,Owner,,,,Closed | B67: =IFERROR(__xludf.DUMMYFUNCTION("SPLIT(A67,"","",0,0)"),45564.58611111111) -> 45564.586 | C67: =IFERROR(__xludf.DUMMYFUNCTION("""COMPUTED_VALUE"""),2791946.0) -> 2791946 | D67: =IFERROR(__xludf.DUMMYFUNCTION("""COMPUTED_VALUE"""),"Sale") -> Sale | E67: =IFERROR(__xludf.DUMMYFUNCTION("""COMPUTED_VALUE"""),"Minuman") -> Minuman | F67: =IFERROR(__xludf.DUMMYFUNCTION("""COMPUTED_VALUE"""),10128.0) -> 10128 | G67: =IFERROR(__xludf.DUMMYFUNCTION("""COMPUTED_VALUE"""),"Es Kopi Susu") -> Es Kopi Susu | J67: =IFERROR(__xludf.DUMMYFUNCTION("""COMPUTED_VALUE"""),1.0) -> 1 | K67: =IFERROR(__xludf.DUMMYFUNCTION("""COMPUTED_VALUE"""),23333.0) -> 23333 | L67: =IFERROR(__xludf.DUMMYFUNCTION("""COMPUTED_VALUE"""),0.0) -> 0 | M67: =IFERROR(__xludf.DUMMYFUNCTION("""COMPUTED_VALUE"""),23333.0) -> 23333 | N67: =IFERROR(__xludf.DUMMYFUNCTION("""COMPUTED_VALUE"""),0.0) -> 0 | O67: =IFERROR(__xludf.DUMMYFUNCTION("""COMPUTED_VALUE"""),23333.0) -> 23333 | P67: =IFERROR(__xludf.DUMMYFUNCTION("""COMPUTED_VALUE"""),1166.0) -> 1166 | Q67: =IFERROR(__xludf.DUMMYFUNCTION("""COMPUTED_VALUE"""),"Dine In") -> Dine In | R67: =IFERROR(__xludf.DUMMYFUNCTION("""COMPUTED_VALUE"""),"Kedai") -> Kedai | S67: =IFERROR(__xludf.DUMMYFUNCTION("""COMPUTED_VALUE"""),"Temu Roti") -> Temu Roti | T67: =IFERROR(__xludf.DUMMYFUNCTION("""COMPUTED_VALUE"""),"Owner") -> Owner | X67: =IFERROR(__xludf.DUMMYFUNCTION("""COMPUTED_VALUE"""),"Closed") -> Closed
A68: 29/09/2024 14:04,2-9544,Sale,Roti,10055,Roti Gandum Cokelat 2 pcs,,,2.000,69524.00,0.00,69524.00,0.00,69524.00,3477.00,Dine In,Kedai,Temu Roti,Owner,,,,Closed | B68: =IFERROR(__xludf.DUMMYFUNCTION("SPLIT(A68,"","",0,0)"),45564.58611111111) -> 45564.586 | C68: =IFERROR(__xludf.DUMMYFUNCTION("""COMPUTED_VALUE"""),2791946.0) -> 2791946 | D68: =IFERROR(__xludf.DUMMYFUNCTION("""COMPUTED_VALUE"""),"Sale") -> Sale | E68: =IFERROR(__xludf.DUMMYFUNCTION("""COMPUTED_VALUE"""),"Roti") -> Roti | F68: =IFERROR(__xludf.DUMMYFUNCTION("""COMPUTED_VALUE"""),10055.0) -> 10055 | G68: =IFERROR(__xludf.DUMMYFUNCTION("""COMPUTED_VALUE"""),"Roti Gandum Cokelat 2 pcs") -> Roti Gandum Cokelat 2 pcs | J68: =IFERROR(__xludf.DUMMYFUNCTION("""COMPUTED_VALUE"""),2.0) -> 2 | K68: =IFERROR(__xludf.DUMMYFUNCTION("""COMPUTED_VALUE"""),69524.0) -> 69524 | L68: =IFERROR(__xludf.DUMMYFUNCTION("""COMPUTED_VALUE"""),0.0) -> 0 | M68: =IFERROR(__xludf.DUMMYFUNCTION("""COMPUTED_VALUE"""),69524.0) -> 69524 | N68: =IFERROR(__xludf.DUMMYFUNCTION("""COMPUTED_VALUE"""),0.0) -> 0 | O68: =IFERROR(__xludf.DUMMYFUNCTION("""COMPUTED_VALUE"""),69524.0) -> 69524 | P68: =IFERROR(__xludf.DUMMYFUNCTION("""COMPUTED_VALUE"""),3477.0) -> 3477 | Q68: =IFERROR(__xludf.DUMMYFUNCTION("""COMPUTED_VALUE"""),"Dine In") -> Dine In | R68: =IFERROR(__xludf.DUMMYFUNCTION("""COMPUTED_VALUE"""),"Kedai") -> Kedai | S68: =IFERROR(__xludf.DUMMYFUNCTION("""COMPUTED_VALUE"""),"Temu Roti") -> Temu Roti | T68: =IFERROR(__xludf.DUMMYFUNCTION("""COMPUTED_VALUE"""),"Owner") -> Owner | X68: =IFERROR(__xludf.DUMMYFUNCTION("""COMPUTED_VALUE"""),"Closed") -> Closed
A69: 29/09/2024 13:54,2-9543,Sale,Roti,10005,Roti Gandum Cokelat,,,1.000,19524.00,0.00,19524.00,0.00,19524.00,976.00,Dine In,Kedai,Temu Roti,Owner,,,,Closed | B69: =IFERROR(__xludf.DUMMYFUNCTION("SPLIT(A69,"","",0,0)"),45564.57916666667) -> 45564.579 | C69: =IFERROR(__xludf.DUMMYFUNCTION("""COMPUTED_VALUE"""),2791581.0) -> 2791581 | D69: =IFERROR(__xludf.DUMMYFUNCTION("""COMPUTED_VALUE"""),"Sale") -> Sale | E69: =IFERROR(__xludf.DUMMYFUNCTION("""COMPUTED_VALUE"""),"Roti") -> Roti | F69: =IFERROR(__xludf.DUMMYFUNCTION("""COMPUTED_VALUE"""),10005.0) -> 10005 | G69: =IFERROR(__xludf.DUMMYFUNCTION("""COMPUTED_VALUE"""),"Roti Gandum Cokelat") -> Roti Gandum Cokelat | J69: =IFERROR(__xludf.DUMMYFUNCTION("""COMPUTED_VALUE"""),1.0) -> 1 | K69: =IFERROR(__xludf.DUMMYFUNCTION("""COMPUTED_VALUE"""),19524.0) -> 19524 | L69: =IFERROR(__xludf.DUMMYFUNCTION("""COMPUTED_VALUE"""),0.0) -> 0 | M69: =IFERROR(__xludf.DUMMYFUNCTION("""COMPUTED_VALUE"""),19524.0) -> 19524 | N69: =IFERROR(__xludf.DUMMYFUNCTION("""COMPUTED_VALUE"""),0.0) -> 0 | O69: =IFERROR(__xludf.DUMMYFUNCTION("""COMPUTED_VALUE"""),19524.0) -> 19524 | P69: =IFERROR(__xludf.DUMMYFUNCTION("""COMPUTED_VALUE"""),976.0) -> 976 | Q69: =IFERROR(__xludf.DUMMYFUNCTION("""COMPUTED_VALUE"""),"Dine In") -> Dine In | R69: =IFERROR(__xludf.DUMMYFUNCTION("""COMPUTED_VALUE"""),"Kedai") -> Kedai | S69: =IFERROR(__xludf.DUMMYFUNCTION("""COMPUTED_VALUE"""),"Temu Roti") -> Temu Roti | T69: =IFERROR(__xludf.DUMMYFUNCTION("""COMPUTED_VALUE"""),"Owner") -> Owner | X69: =IFERROR(__xludf.DUMMYFUNCTION("""COMPUTED_VALUE"""),"Closed") -> Closed
A70: 29/09/2024 13:54,2-9543,Sale,Minuman,10128,Es Kopi Susu,,,1.000,23333.00,0.00,23333.00,0.00,23333.00,1167.00,Dine In,Kedai,Temu Roti,Owner,,,,Closed | B70: =IFERROR(__xludf.DUMMYFUNCTION("SPLIT(A70,"","",0,0)"),45564.57916666667) -> 45564.579 | C70: =IFERROR(__xludf.DUMMYFUNCTION("""COMPUTED_VALUE"""),2791581.0) -> 2791581 | D70: =IFERROR(__xludf.DUMMYFUNCTION("""COMPUTED_VALUE"""),"Sale") -> Sale | E70: =IFERROR(__xludf.DUMMYFUNCTION("""COMPUTED_VALUE"""),"Minuman") -> Minuman | F70: =IFERROR(__xludf.DUMMYFUNCTION("""COMPUTED_VALUE"""),10128.0) -> 10128 | G70: =IFERROR(__xludf.DUMMYFUNCTION("""COMPUTED_VALUE"""),"Es Kopi Susu") -> Es Kopi Susu | J70: =IFERROR(__xludf.DUMMYFUNCTION("""COMPUTED_VALUE"""),1.0) -> 1 | K70: =IFERROR(__xludf.DUMMYFUNCTION("""COMPUTED_VALUE"""),23333.0) -> 23333 | L70: =IFERROR(__xludf.DUMMYFUNCTION("""COMPUTED_VALUE"""),0.0) -> 0 | M70: =IFERROR(__xludf.DUMMYFUNCTION("""COMPUTED_VALUE"""),23333.0) -> 23333 | N70: =IFERROR(__xludf.DUMMYFUNCTION("""COMPUTED_VALUE"""),0.0) -> 0 | O70: =IFERROR(__xludf.DUMMYFUNCTION("""COMPUTED_VALUE"""),23333.0) -> 23333 | P70: =IFERROR(__xludf.DUMMYFUNCTION("""COMPUTED_VALUE"""),1167.0) -> 1167 | Q70: =IFERROR(__xludf.DUMMYFUNCTION("""COMPUTED_VALUE"""),"Dine In") -> Dine In | R70: =IFERROR(__xludf.DUMMYFUNCTION("""COMPUTED_VALUE"""),"Kedai") -> Kedai | S70: =IFERROR(__xludf.DUMMYFUNCTION("""COMPUTED_VALUE"""),"Temu Roti") -> Temu Roti | T70: =IFERROR(__xludf.DUMMYFUNCTION("""COMPUTED_VALUE"""),"Owner") -> Owner | X70: =IFERROR(__xludf.DUMMYFUNCTION("""COMPUTED_VALUE"""),"Closed") -> Closed
A71: 29/09/2024 13:54,2-9543,Sale,Roti,10007,Roti cranberry 2 pcs,,,1.000,33810.00,0.00,33810.00,0.00,33810.00,1690.00,Dine In,Kedai,Temu Roti,Owner,,,,Closed | B71: =IFERROR(__xludf.DUMMYFUNCTION("SPLIT(A71,"","",0,0)"),45564.57916666667) -> 45564.579 | C71: =IFERROR(__xludf.DUMMYFUNCTION("""COMPUTED_VALUE"""),2791581.0) -> 2791581 | D71: =IFERROR(__xludf.DUMMYFUNCTION("""COMPUTED_VALUE"""),"Sale") -> Sale | E71: =IFERROR(__xludf.DUMMYFUNCTION("""COMPUTED_VALUE"""),"Roti") -> Roti | F71: =IFERROR(__xludf.DUMMYFUNCTION("""COMPUTED_VALUE"""),10007.0) -> 10007 | G71: =IFERROR(__xludf.DUMMYFUNCTION("""COMPUTED_VALUE"""),"Roti cranberry 2 pcs") -> Roti cranberry 2 pcs | J71: =IFERROR(__xludf.DUMMYFUNCTION("""COMPUTED_VALUE"""),1.0) -> 1 | K71: =IFERROR(__xludf.DUMMYFUNCTION("""COMPUTED_VALUE"""),33810.0) -> 33810 | L71: =IFERROR(__xludf.DUMMYFUNCTION("""COMPUTED_VALUE"""),0.0) -> 0 | M71: =IFERROR(__xludf.DUMMYFUNCTION("""COMPUTED_VALUE"""),33810.0) -> 33810 | N71: =IFERROR(__xludf.DUMMYFUNCTION("""COMPUTED_VALUE"""),0.0) -> 0 | O71: =IFERROR(__xludf.DUMMYFUNCTION("""COMPUTED_VALUE"""),33810.0) -> 33810 | P71: =IFERROR(__xludf.DUMMYFUNCTION("""COMPUTED_VALUE"""),1690.0) -> 1690 | Q71: =IFERROR(__xludf.DUMMYFUNCTION("""COMPUTED_VALUE"""),"Dine In") -> Dine In | R71: =IFERROR(__xludf.DUMMYFUNCTION("""COMPUTED_VALUE"""),"Kedai") -> Kedai | S71: =IFERROR(__xludf.DUMMYFUNCTION("""COMPUTED_VALUE"""),"Temu Roti") -> Temu Roti | T71: =IFERROR(__xludf.DUMMYFUNCTION("""COMPUTED_VALUE"""),"Owner") -> Owner | X71: =IFERROR(__xludf.DUMMYFUNCTION("""COMPUTED_VALUE"""),"Closed") -> Closed
A72: 29/09/2024 12:52,2-9542,Sale,Roti,10002,Roti Cranberry,,,1.000,18571.00,0.00,18571.00,0.00,18571.00,929.00,Dine In,Kedai,Temu Roti,Owner,,,,Closed | B72: =IFERROR(__xludf.DUMMYFUNCTION("SPLIT(A72,"","",0,0)"),45564.53611111111) -> 45564.536 | C72: =IFERROR(__xludf.DUMMYFUNCTION("""COMPUTED_VALUE"""),2791216.0) -> 2791216 | D72: =IFERROR(__xludf.DUMMYFUNCTION("""COMPUTED_VALUE"""),"Sale") -> Sale | E72: =IFERROR(__xludf.DUMMYFUNCTION("""COMPUTED_VALUE"""),"Roti") -> Roti | F72: =IFERROR(__xludf.DUMMYFUNCTION("""COMPUTED_VALUE"""),10002.0) -> 10002 | G72: =IFERROR(__xludf.DUMMYFUNCTION("""COMPUTED_VALUE"""),"Roti Cranberry") -> Roti Cranberry | J72: =IFERROR(__xludf.DUMMYFUNCTION("""COMPUTED_VALUE"""),1.0) -> 1 | K72: =IFERROR(__xludf.DUMMYFUNCTION("""COMPUTED_VALUE"""),18571.0) -> 18571 | L72: =IFERROR(__xludf.DUMMYFUNCTION("""COMPUTED_VALUE"""),0.0) -> 0 | M72: =IFERROR(__xludf.DUMMYFUNCTION("""COMPUTED_VALUE"""),18571.0) -> 18571 | N72: =IFERROR(__xludf.DUMMYFUNCTION("""COMPUTED_VALUE"""),0.0) -> 0 | O72: =IFERROR(__xludf.DUMMYFUNCTION("""COMPUTED_VALUE"""),18571.0) -> 18571 | P72: =IFERROR(__xludf.DUMMYFUNCTION("""COMPUTED_VALUE"""),929.0) -> 929 | Q72: =IFERROR(__xludf.DUMMYFUNCTION("""COMPUTED_VALUE"""),"Dine In") -> Dine In | R72: =IFERROR(__xludf.DUMMYFUNCTION("""COMPUTED_VALUE"""),"Kedai") -> Kedai | S72: =IFERROR(__xludf.DUMMYFUNCTION("""COMPUTED_VALUE"""),"Temu Roti") -> Temu Roti | T72: =IFERROR(__xludf.DUMMYFUNCTION("""COMPUTED_VALUE"""),"Owner") -> Owner | X72: =IFERROR(__xludf.DUMMYFUNCTION("""COMPUTED_VALUE"""),"Closed") -> Closed
A73: 29/09/2024 12:52,2-9542,Sale,Hidangan Utama,10012,Mie joglo,,,1.000,29524.00,0.00,29524.00,0.00,29524.00,1476.00,Dine In,Kedai,Temu Roti,Owner,,,,Closed | B73: =IFERROR(__xludf.DUMMYFUNCTION("SPLIT(A73,"","",0,0)"),45564.53611111111) -> 45564.536 | C73: =IFERROR(__xludf.DUMMYFUNCTION("""COMPUTED_VALUE"""),2791216.0) -> 2791216 | D73: =IFERROR(__xludf.DUMMYFUNCTION("""COMPUTED_VALUE"""),"Sale") -> Sale | E73: =IFERROR(__xludf.DUMMYFUNCTION("""COMPUTED_VALUE"""),"Hidangan Utama") -> Hidangan Utama | F73: =IFERROR(__xludf.DUMMYFUNCTION("""COMPUTED_VALUE"""),10012.0) -> 10012 | G73: =IFERROR(__xludf.DUMMYFUNCTION("""COMPUTED_VALUE"""),"Mie joglo") -> Mie joglo | J73: =IFERROR(__xludf.DUMMYFUNCTION("""COMPUTED_VALUE"""),1.0) -> 1 | K73: =IFERROR(__xludf.DUMMYFUNCTION("""COMPUTED_VALUE"""),29524.0) -> 29524 | L73: =IFERROR(__xludf.DUMMYFUNCTION("""COMPUTED_VALUE"""),0.0) -> 0 | M73: =IFERROR(__xludf.DUMMYFUNCTION("""COMPUTED_VALUE"""),29524.0) -> 29524 | N73: =IFERROR(__xludf.DUMMYFUNCTION("""COMPUTED_VALUE"""),0.0) -> 0 | O73: =IFERROR(__xludf.DUMMYFUNCTION("""COMPUTED_VALUE"""),29524.0) -> 29524 | P73: =IFERROR(__xludf.DUMMYFUNCTION("""COMPUTED_VALUE"""),1476.0) -> 1476 | Q73: =IFERROR(__xludf.DUMMYFUNCTION("""COMPUTED_VALUE"""),"Dine In") -> Dine In | R73: =IFERROR(__xludf.DUMMYFUNCTION("""COMPUTED_VALUE"""),"Kedai") -> Kedai | S73: =IFERROR(__xludf.DUMMYFUNCTION("""COMPUTED_VALUE"""),"Temu Roti") -> Temu Roti | T73: =IFERROR(__xludf.DUMMYFUNCTION("""COMPUTED_VALUE"""),"Owner") -> Owner | X73: =IFERROR(__xludf.DUMMYFUNCTION("""COMPUTED_VALUE"""),"Closed") -> Closed
A74: 29/09/2024 12:52,2-9542,Sale,Minuman,10070,Wedang laut,,,1.000,24762.00,0.00,24762.00,0.00,24762.00,1238.00,Dine In,Kedai,Temu Roti,Owner,,,,Closed | B74: =IFERROR(__xludf.DUMMYFUNCTION("SPLIT(A74,"","",0,0)"),45564.53611111111) -> 45564.536 | C74: =IFERROR(__xludf.DUMMYFUNCTION("""COMPUTED_VALUE"""),2791216.0) -> 2791216 | D74: =IFERROR(__xludf.DUMMYFUNCTION("""COMPUTED_VALUE"""),"Sale") -> Sale | E74: =IFERROR(__xludf.DUMMYFUNCTION("""COMPUTED_VALUE"""),"Minuman") -> Minuman | F74: =IFERROR(__xludf.DUMMYFUNCTION("""COMPUTED_VALUE"""),10070.0) -> 10070 | G74: =IFERROR(__xludf.DUMMYFUNCTION("""COMPUTED_VALUE"""),"Wedang laut") -> Wedang laut | J74: =IFERROR(__xludf.DUMMYFUNCTION("""COMPUTED_VALUE"""),1.0) -> 1 | K74: =IFERROR(__xludf.DUMMYFUNCTION("""COMPUTED_VALUE"""),24762.0) -> 24762 | L74: =IFERROR(__xludf.DUMMYFUNCTION("""COMPUTED_VALUE"""),0.0) -> 0 | M74: =IFERROR(__xludf.DUMMYFUNCTION("""COMPUTED_VALUE"""),24762.0) -> 24762 | N74: =IFERROR(__xludf.DUMMYFUNCTION("""COMPUTED_VALUE"""),0.0) -> 0 | O74: =IFERROR(__xludf.DUMMYFUNCTION("""COMPUTED_VALUE"""),24762.0) -> 24762 | P74: =IFERROR(__xludf.DUMMYFUNCTION("""COMPUTED_VALUE"""),1238.0) -> 1238 | Q74: =IFERROR(__xludf.DUMMYFUNCTION("""COMPUTED_VALUE"""),"Dine In") -> Dine In | R74: =IFERROR(__xludf.DUMMYFUNCTION("""COMPUTED_VALUE"""),"Kedai") -> Kedai | S74: =IFERROR(__xludf.DUMMYFUNCTION("""COMPUTED_VALUE"""),"Temu Roti") -> Temu Roti | T74: =IFERROR(__xludf.DUMMYFUNCTION("""COMPUTED_VALUE"""),"Owner") -> Owner | X74: =IFERROR(__xludf.DUMMYFUNCTION("""COMPUTED_VALUE"""),"Closed") -> Closed
A75: 29/09/2024 12:52,2-9542,Sale,Hidangan Utama,10003,Nasi Goreng Temu,,,1.000,29524.00,0.00,29524.00,0.00,29524.00,1476.00,Dine In,Kedai,Temu Roti,Owner,,,,Closed | B75: =IFERROR(__xludf.DUMMYFUNCTION("SPLIT(A75,"","",0,0)"),45564.53611111111) -> 45564.536 | C75: =IFERROR(__xludf.DUMMYFUNCTION("""COMPUTED_VALUE"""),2791216.0) -> 2791216 | D75: =IFERROR(__xludf.DUMMYFUNCTION("""COMPUTED_VALUE"""),"Sale") -> Sale | E75: =IFERROR(__xludf.DUMMYFUNCTION("""COMPUTED_VALUE"""),"Hidangan Utama") -> Hidangan Utama | F75: =IFERROR(__xludf.DUMMYFUNCTION("""COMPUTED_VALUE"""),10003.0) -> 10003 | G75: =IFERROR(__xludf.DUMMYFUNCTION("""COMPUTED_VALUE"""),"Nasi Goreng Temu") -> Nasi Goreng Temu | J75: =IFERROR(__xludf.DUMMYFUNCTION("""COMPUTED_VALUE"""),1.0) -> 1 | K75: =IFERROR(__xludf.DUMMYFUNCTION("""COMPUTED_VALUE"""),29524.0) -> 29524 | L75: =IFERROR(__xludf.DUMMYFUNCTION("""COMPUTED_VALUE"""),0.0) -> 0 | M75: =IFERROR(__xludf.DUMMYFUNCTION("""COMPUTED_VALUE"""),29524.0) -> 29524 | N75: =IFERROR(__xludf.DUMMYFUNCTION("""COMPUTED_VALUE"""),0.0) -> 0 | O75: =IFERROR(__xludf.DUMMYFUNCTION("""COMPUTED_VALUE"""),29524.0) -> 29524 | P75: =IFERROR(__xludf.DUMMYFUNCTION("""COMPUTED_VALUE"""),1476.0) -> 1476 | Q75: =IFERROR(__xludf.DUMMYFUNCTION("""COMPUTED_VALUE"""),"Dine In") -> Dine In | R75: =IFERROR(__xludf.DUMMYFUNCTION("""COMPUTED_VALUE"""),"Kedai") -> Kedai | S75: =IFERROR(__xludf.DUMMYFUNCTION("""COMPUTED_VALUE"""),"Temu Roti") -> Temu Roti | T75: =IFERROR(__xludf.DUMMYFUNCTION("""COMPUTED_VALUE"""),"Owner") -> Owner | X75: =IFERROR(__xludf.DUMMYFUNCTION("""COMPUTED_VALUE"""),"Closed") -> Closed
A76: 29/09/2024 12:52,2-9542,Sale,Minuman,10118,Teh Tawar Panas,,,1.000,7143.00,0.00,7143.00,0.00,7143.00,357.00,Dine In,Kedai,Temu Roti,Owner,,,,Closed | B76: =IFERROR(__xludf.DUMMYFUNCTION("SPLIT(A76,"","",0,0)"),45564.53611111111) -> 45564.536 | C76: =IFERROR(__xludf.DUMMYFUNCTION("""COMPUTED_VALUE"""),2791216.0) -> 2791216 | D76: =IFERROR(__xludf.DUMMYFUNCTION("""COMPUTED_VALUE"""),"Sale") -> Sale | E76: =IFERROR(__xludf.DUMMYFUNCTION("""COMPUTED_VALUE"""),"Minuman") -> Minuman | F76: =IFERROR(__xludf.DUMMYFUNCTION("""COMPUTED_VALUE"""),10118.0) -> 10118 | G76: =IFERROR(__xludf.DUMMYFUNCTION("""COMPUTED_VALUE"""),"Teh Tawar Panas") -> Teh Tawar Panas | J76: =IFERROR(__xludf.DUMMYFUNCTION("""COMPUTED_VALUE"""),1.0) -> 1 | K76: =IFERROR(__xludf.DUMMYFUNCTION("""COMPUTED_VALUE"""),7143.0) -> 7143 | L76: =IFERROR(__xludf.DUMMYFUNCTION("""COMPUTED_VALUE"""),0.0) -> 0 | M76: =IFERROR(__xludf.DUMMYFUNCTION("""COMPUTED_VALUE"""),7143.0) -> 7143 | N76: =IFERROR(__xludf.DUMMYFUNCTION("""COMPUTED_VALUE"""),0.0) -> 0 | O76: =IFERROR(__xludf.DUMMYFUNCTION("""COMPUTED_VALUE"""),7143.0) -> 7143 | P76: =IFERROR(__xludf.DUMMYFUNCTION("""COMPUTED_VALUE"""),357.0) -> 357 | Q76: =IFERROR(__xludf.DUMMYFUNCTION("""COMPUTED_VALUE"""),"Dine In") -> Dine In | R76: =IFERROR(__xludf.DUMMYFUNCTION("""COMPUTED_VALUE"""),"Kedai") -> Kedai | S76: =IFERROR(__xludf.DUMMYFUNCTION("""COMPUTED_VALUE"""),"Temu Roti") -> Temu Roti | T76: =IFERROR(__xludf.DUMMYFUNCTION("""COMPUTED_VALUE"""),"Owner") -> Owner | X76: =IFERROR(__xludf.DUMMYFUNCTION("""COMPUTED_VALUE"""),"Closed") -> Closed
A77: 29/09/2024 12:47,2-9541,Sale,Roti,10002,Roti Cranberry,,,1.000,18571.00,0.00,18571.00,0.00,18571.00,929.00,Dine In,Kedai,Temu Roti,Owner,,,,Closed | B77: =IFERROR(__xludf.DUMMYFUNCTION("SPLIT(A77,"","",0,0)"),45564.532638888886) -> 45564.533 | C77: =IFERROR(__xludf.DUMMYFUNCTION("""COMPUTED_VALUE"""),2790851.0) -> 2790851 | D77: =IFERROR(__xludf.DUMMYFUNCTION("""COMPUTED_VALUE"""),"Sale") -> Sale | E77: =IFERROR(__xludf.DUMMYFUNCTION("""COMPUTED_VALUE"""),"Roti") -> Roti | F77: =IFERROR(__xludf.DUMMYFUNCTION("""COMPUTED_VALUE"""),10002.0) -> 10002 | G77: =IFERROR(__xludf.DUMMYFUNCTION("""COMPUTED_VALUE"""),"Roti Cranberry") -> Roti Cranberry | J77: =IFERROR(__xludf.DUMMYFUNCTION("""COMPUTED_VALUE"""),1.0) -> 1 | K77: =IFERROR(__xludf.DUMMYFUNCTION("""COMPUTED_VALUE"""),18571.0) -> 18571 | L77: =IFERROR(__xludf.DUMMYFUNCTION("""COMPUTED_VALUE"""),0.0) -> 0 | M77: =IFERROR(__xludf.DUMMYFUNCTION("""COMPUTED_VALUE"""),18571.0) -> 18571 | N77: =IFERROR(__xludf.DUMMYFUNCTION("""COMPUTED_VALUE"""),0.0) -> 0 | O77: =IFERROR(__xludf.DUMMYFUNCTION("""COMPUTED_VALUE"""),18571.0) -> 18571 | P77: =IFERROR(__xludf.DUMMYFUNCTION("""COMPUTED_VALUE"""),929.0) -> 929 | Q77: =IFERROR(__xludf.DUMMYFUNCTION("""COMPUTED_VALUE"""),"Dine In") -> Dine In | R77: =IFERROR(__xludf.DUMMYFUNCTION("""COMPUTED_VALUE"""),"Kedai") -> Kedai | S77: =IFERROR(__xludf.DUMMYFUNCTION("""COMPUTED_VALUE"""),"Temu Roti") -> Temu Roti | T77: =IFERROR(__xludf.DUMMYFUNCTION("""COMPUTED_VALUE"""),"Owner") -> Owner | X77: =IFERROR(__xludf.DUMMYFUNCTION("""COMPUTED_VALUE"""),"Closed") -> Closed
A78: 29/09/2024 12:47,2-9541,Sale,Roti,10005,Roti Gandum Cokelat,,,1.000,19524.00,0.00,19524.00,0.00,19524.00,976.00,Dine In,Kedai,Temu Roti,Owner,,,,Closed | B78: =IFERROR(__xludf.DUMMYFUNCTION("SPLIT(A78,"","",0,0)"),45564.532638888886) -> 45564.533 | C78: =IFERROR(__xludf.DUMMYFUNCTION("""COMPUTED_VALUE"""),2790851.0) -> 2790851 | D78: =IFERROR(__xludf.DUMMYFUNCTION("""COMPUTED_VALUE"""),"Sale") -> Sale | E78: =IFERROR(__xludf.DUMMYFUNCTION("""COMPUTED_VALUE"""),"Roti") -> Roti | F78: =IFERROR(__xludf.DUMMYFUNCTION("""COMPUTED_VALUE"""),10005.0) -> 10005 | G78: =IFERROR(__xludf.DUMMYFUNCTION("""COMPUTED_VALUE"""),"Roti Gandum Cokelat") -> Roti Gandum Cokelat | J78: =IFERROR(__xludf.DUMMYFUNCTION("""COMPUTED_VALUE"""),1.0) -> 1 | K78: =IFERROR(__xludf.DUMMYFUNCTION("""COMPUTED_VALUE"""),19524.0) -> 19524 | L78: =IFERROR(__xludf.DUMMYFUNCTION("""COMPUTED_VALUE"""),0.0) -> 0 | M78: =IFERROR(__xludf.DUMMYFUNCTION("""COMPUTED_VALUE"""),19524.0) -> 19524 | N78: =IFERROR(__xludf.DUMMYFUNCTION("""COMPUTED_VALUE"""),0.0) -> 0 | O78: =IFERROR(__xludf.DUMMYFUNCTION("""COMPUTED_VALUE"""),19524.0) -> 19524 | P78: =IFERROR(__xludf.DUMMYFUNCTION("""COMPUTED_VALUE"""),976.0) -> 976 | Q78: =IFERROR(__xludf.DUMMYFUNCTION("""COMPUTED_VALUE"""),"Dine In") -> Dine In | R78: =IFERROR(__xludf.DUMMYFUNCTION("""COMPUTED_VALUE"""),"Kedai") -> Kedai | S78: =IFERROR(__xludf.DUMMYFUNCTION("""COMPUTED_VALUE"""),"Temu Roti") -> Temu Roti | T78: =IFERROR(__xludf.DUMMYFUNCTION("""COMPUTED_VALUE"""),"Owner") -> Owner | X78: =IFERROR(__xludf.DUMMYFUNCTION("""COMPUTED_VALUE"""),"Closed") -> Closed
A79: 29/09/2024 12:47,2-9541,Sale,Minuman,10128,Es Kopi Susu,,,1.000,23333.00,0.00,23333.00,0.00,23333.00,1166.00,Dine In,Kedai,Temu Roti,Owner,,,,Closed | B79: =IFERROR(__xludf.DUMMYFUNCTION("SPLIT(A79,"","",0,0)"),45564.532638888886) -> 45564.533 | C79: =IFERROR(__xludf.DUMMYFUNCTION("""COMPUTED_VALUE"""),2790851.0) -> 2790851 | D79: =IFERROR(__xludf.DUMMYFUNCTION("""COMPUTED_VALUE"""),"Sale") -> Sale | E79: =IFERROR(__xludf.DUMMYFUNCTION("""COMPUTED_VALUE"""),"Minuman") -> Minuman | F79: =IFERROR(__xludf.DUMMYFUNCTION("""COMPUTED_VALUE"""),10128.0) -> 10128 | G79: =IFERROR(__xludf.DUMMYFUNCTION("""COMPUTED_VALUE"""),"Es Kopi Susu") -> Es Kopi Susu | J79: =IFERROR(__xludf.DUMMYFUNCTION("""COMPUTED_VALUE"""),1.0) -> 1 | K79: =IFERROR(__xludf.DUMMYFUNCTION("""COMPUTED_VALUE"""),23333.0) -> 23333 | L79: =IFERROR(__xludf.DUMMYFUNCTION("""COMPUTED_VALUE"""),0.0) -> 0 | M79: =IFERROR(__xludf.DUMMYFUNCTION("""COMPUTED_VALUE"""),23333.0) -> 23333 | N79: =IFERROR(__xludf.DUMMYFUNCTION("""COMPUTED_VALUE"""),0.0) -> 0 | O79: =IFERROR(__xludf.DUMMYFUNCTION("""COMPUTED_VALUE"""),23333.0) -> 23333 | P79: =IFERROR(__xludf.DUMMYFUNCTION("""COMPUTED_VALUE"""),1166.0) -> 1166 | Q79: =IFERROR(__xludf.DUMMYFUNCTION("""COMPUTED_VALUE"""),"Dine In") -> Dine In | R79: =IFERROR(__xludf.DUMMYFUNCTION("""COMPUTED_VALUE"""),"Kedai") -> Kedai | S79: =IFERROR(__xludf.DUMMYFUNCTION("""COMPUTED_VALUE"""),"Temu Roti") -> Temu Roti | T79: =IFERROR(__xludf.DUMMYFUNCTION("""COMPUTED_VALUE"""),"Owner") -> Owner | X79: =IFERROR(__xludf.DUMMYFUNCTION("""COMPUTED_VALUE"""),"Closed") -> Closed
A80: 29/09/2024 12:47,2-9541,Sale,Minuman,10120,Lemon Tea Panas,,,1.000,19524.00,0.00,19524.00,0.00,19524.00,977.00,Dine In,Kedai,Temu Roti,Owner,,,,Closed | B80: =IFERROR(__xludf.DUMMYFUNCTION("SPLIT(A80,"","",0,0)"),45564.532638888886) -> 45564.533 | C80: =IFERROR(__xludf.DUMMYFUNCTION("""COMPUTED_VALUE"""),2790851.0) -> 2790851 | D80: =IFERROR(__xludf.DUMMYFUNCTION("""COMPUTED_VALUE"""),"Sale") -> Sale | E80: =IFERROR(__xludf.DUMMYFUNCTION("""COMPUTED_VALUE"""),"Minuman") -> Minuman | F80: =IFERROR(__xludf.DUMMYFUNCTION("""COMPUTED_VALUE"""),10120.0) -> 10120 | G80: =IFERROR(__xludf.DUMMYFUNCTION("""COMPUTED_VALUE"""),"Lemon Tea Panas") -> Lemon Tea Panas | J80: =IFERROR(__xludf.DUMMYFUNCTION("""COMPUTED_VALUE"""),1.0) -> 1 | K80: =IFERROR(__xludf.DUMMYFUNCTION("""COMPUTED_VALUE"""),19524.0) -> 19524 | L80: =IFERROR(__xludf.DUMMYFUNCTION("""COMPUTED_VALUE"""),0.0) -> 0 | M80: =IFERROR(__xludf.DUMMYFUNCTION("""COMPUTED_VALUE"""),19524.0) -> 19524 | N80: =IFERROR(__xludf.DUMMYFUNCTION("""COMPUTED_VALUE"""),0.0) -> 0 | O80: =IFERROR(__xludf.DUMMYFUNCTION("""COMPUTED_VALUE"""),19524.0) -> 19524 | P80: =IFERROR(__xludf.DUMMYFUNCTION("""COMPUTED_VALUE"""),977.0) -> 977 | Q80: =IFERROR(__xludf.DUMMYFUNCTION("""COMPUTED_VALUE"""),"Dine In") -> Dine In | R80: =IFERROR(__xludf.DUMMYFUNCTION("""COMPUTED_VALUE"""),"Kedai") -> Kedai | S80: =IFERROR(__xludf.DUMMYFUNCTION("""COMPUTED_VALUE"""),"Temu Roti") -> Temu Roti | T80: =IFERROR(__xludf.DUMMYFUNCTION("""COMPUTED_VALUE"""),"Owner") -> Owner | X80: =IFERROR(__xludf.DUMMYFUNCTION("""COMPUTED_VALUE"""),"Closed") -> Closed
A81: 29/09/2024 12:33,2-9540,Sale,Minuman,10112,Air mineral,,,2.000,13334.00,0.00,13334.00,0.00,13334.00,667.00,Dine In,Kedai,Temu Roti,Owner,,,,Closed | B81: =IFERROR(__xludf.DUMMYFUNCTION("SPLIT(A81,"","",0,0)"),45564.52291666667) -> 45564.523 | C81: =IFERROR(__xludf.DUMMYFUNCTION("""COMPUTED_VALUE"""),2790485.0) -> 2790485 | D81: =IFERROR(__xludf.DUMMYFUNCTION("""COMPUTED_VALUE"""),"Sale") -> Sale | E81: =IFERROR(__xludf.DUMMYFUNCTION("""COMPUTED_VALUE"""),"Minuman") -> Minuman | F81: =IFERROR(__xludf.DUMMYFUNCTION("""COMPUTED_VALUE"""),10112.0) -> 10112 | G81: =IFERROR(__xludf.DUMMYFUNCTION("""COMPUTED_VALUE"""),"Air mineral") -> Air mineral | J81: =IFERROR(__xludf.DUMMYFUNCTION("""COMPUTED_VALUE"""),2.0) -> 2 | K81: =IFERROR(__xludf.DUMMYFUNCTION("""COMPUTED_VALUE"""),13334.0) -> 13334 | L81: =IFERROR(__xludf.DUMMYFUNCTION("""COMPUTED_VALUE"""),0.0) -> 0 | M81: =IFERROR(__xludf.DUMMYFUNCTION("""COMPUTED_VALUE"""),13334.0) -> 13334 | N81: =IFERROR(__xludf.DUMMYFUNCTION("""COMPUTED_VALUE"""),0.0) -> 0 | O81: =IFERROR(__xludf.DUMMYFUNCTION("""COMPUTED_VALUE"""),13334.0) -> 13334 | P81: =IFERROR(__xludf.DUMMYFUNCTION("""COMPUTED_VALUE"""),667.0) -> 667 | Q81: =IFERROR(__xludf.DUMMYFUNCTION("""COMPUTED_VALUE"""),"Dine In") -> Dine In | R81: =IFERROR(__xludf.DUMMYFUNCTION("""COMPUTED_VALUE"""),"Kedai") -> Kedai | S81: =IFERROR(__xludf.DUMMYFUNCTION("""COMPUTED_VALUE"""),"Temu Roti") -> Temu Roti | T81: =IFERROR(__xludf.DUMMYFUNCTION("""COMPUTED_VALUE"""),"Owner") -> Owner | X81: =IFERROR(__xludf.DUMMYFUNCTION("""COMPUTED_VALUE"""),"Closed") -> Closed
A82: 29/09/2024 12:10,2-9539,Sale,Kudapan,10011,Kentang Goreng,,,1.000,25238.00,0.00,25238.00,0.00,25238.00,1262.00,Dine In,Kedai,Temu Roti,Owner,,,,Closed | B82: =IFERROR(__xludf.DUMMYFUNCTION("SPLIT(A82,"","",0,0)"),45564.506944444445) -> 45564.507 | C82: =IFERROR(__xludf.DUMMYFUNCTION("""COMPUTED_VALUE"""),2790120.0) -> 2790120 | D82: =IFERROR(__xludf.DUMMYFUNCTION("""COMPUTED_VALUE"""),"Sale") -> Sale | E82: =IFERROR(__xludf.DUMMYFUNCTION("""COMPUTED_VALUE"""),"Kudapan") -> Kudapan | F82: =IFERROR(__xludf.DUMMYFUNCTION("""COMPUTED_VALUE"""),10011.0) -> 10011 | G82: =IFERROR(__xludf.DUMMYFUNCTION("""COMPUTED_VALUE"""),"Kentang Goreng") -> Kentang Goreng | J82: =IFERROR(__xludf.DUMMYFUNCTION("""COMPUTED_VALUE"""),1.0) -> 1 | K82: =IFERROR(__xludf.DUMMYFUNCTION("""COMPUTED_VALUE"""),25238.0) -> 25238 | L82: =IFERROR(__xludf.DUMMYFUNCTION("""COMPUTED_VALUE"""),0.0) -> 0 | M82: =IFERROR(__xludf.DUMMYFUNCTION("""COMPUTED_VALUE"""),25238.0) -> 25238 | N82: =IFERROR(__xludf.DUMMYFUNCTION("""COMPUTED_VALUE"""),0.0) -> 0 | O82: =IFERROR(__xludf.DUMMYFUNCTION("""COMPUTED_VALUE"""),25238.0) -> 25238 | P82: =IFERROR(__xludf.DUMMYFUNCTION("""COMPUTED_VALUE"""),1262.0) -> 1262 | Q82: =IFERROR(__xludf.DUMMYFUNCTION("""COMPUTED_VALUE"""),"Dine In") -> Dine In | R82: =IFERROR(__xludf.DUMMYFUNCTION("""COMPUTED_VALUE"""),"Kedai") -> Kedai | S82: =IFERROR(__xludf.DUMMYFUNCTION("""COMPUTED_VALUE"""),"Temu Roti") -> Temu Roti | T82: =IFERROR(__xludf.DUMMYFUNCTION("""COMPUTED_VALUE"""),"Owner") -> Owner | X82: =IFERROR(__xludf.DUMMYFUNCTION("""COMPUTED_VALUE"""),"Closed") -> Closed
A83: 29/09/2024 12:10,2-9539,Sale,Kudapan,10010,Pisang Goreng,,,1.000,25238.00,0.00,25238.00,0.00,25238.00,1262.00,Dine In,Kedai,Temu Roti,Owner,,,,Closed | B83: =IFERROR(__xludf.DUMMYFUNCTION("SPLIT(A83,"","",0,0)"),45564.506944444445) -> 45564.507 | C83: =IFERROR(__xludf.DUMMYFUNCTION("""COMPUTED_VALUE"""),2790120.0) -> 2790120 | D83: =IFERROR(__xludf.DUMMYFUNCTION("""COMPUTED_VALUE"""),"Sale") -> Sale | E83: =IFERROR(__xludf.DUMMYFUNCTION("""COMPUTED_VALUE"""),"Kudapan") -> Kudapan | F83: =IFERROR(__xludf.DUMMYFUNCTION("""COMPUTED_VALUE"""),10010.0) -> 10010 | G83: =IFERROR(__xludf.DUMMYFUNCTION("""COMPUTED_VALUE"""),"Pisang Goreng") -> Pisang Goreng | J83: =IFERROR(__xludf.DUMMYFUNCTION("""COMPUTED_VALUE"""),1.0) -> 1 | K83: =IFERROR(__xludf.DUMMYFUNCTION("""COMPUTED_VALUE"""),25238.0) -> 25238 | L83: =IFERROR(__xludf.DUMMYFUNCTION("""COMPUTED_VALUE"""),0.0) -> 0 | M83: =IFERROR(__xludf.DUMMYFUNCTION("""COMPUTED_VALUE"""),25238.0) -> 25238 | N83: =IFERROR(__xludf.DUMMYFUNCTION("""COMPUTED_VALUE"""),0.0) -> 0 | O83: =IFERROR(__xludf.DUMMYFUNCTION("""COMPUTED_VALUE"""),25238.0) -> 25238 | P83: =IFERROR(__xludf.DUMMYFUNCTION("""COMPUTED_VALUE"""),1262.0) -> 1262 | Q83: =IFERROR(__xludf.DUMMYFUNCTION("""COMPUTED_VALUE"""),"Dine In") -> Dine In | R83: =IFERROR(__xludf.DUMMYFUNCTION("""COMPUTED_VALUE"""),"Kedai") -> Kedai | S83: =IFERROR(__xludf.DUMMYFUNCTION("""COMPUTED_VALUE"""),"Temu Roti") -> Temu Roti | T83: =IFERROR(__xludf.DUMMYFUNCTION("""COMPUTED_VALUE"""),"Owner") -> Owner | X83: =IFERROR(__xludf.DUMMYFUNCTION("""COMPUTED_VALUE"""),"Closed") -> Closed
A84: 29/09/2024 12:00,2-9538,Sale,Roti,10000,Roti Bawang Saus Keju,,,1.000,29524.00,0.00,29524.00,0.00,29524.00,1476.00,Take Away,Kedai,Temu Roti,Owner,,,,Closed | B84: =IFERROR(__xludf.DUMMYFUNCTION("SPLIT(A84,"","",0,0)"),45564.5) -> 45564.5 | C84: =IFERROR(__xludf.DUMMYFUNCTION("""COMPUTED_VALUE"""),2789755.0) -> 2789755 | D84: =IFERROR(__xludf.DUMMYFUNCTION("""COMPUTED_VALUE"""),"Sale") -> Sale | E84: =IFERROR(__xludf.DUMMYFUNCTION("""COMPUTED_VALUE"""),"Roti") -> Roti | F84: =IFERROR(__xludf.DUMMYFUNCTION("""COMPUTED_VALUE"""),10000.0) -> 10000 | G84: =IFERROR(__xludf.DUMMYFUNCTION("""COMPUTED_VALUE"""),"Roti Bawang Saus Keju") -> Roti Bawang Saus Keju | J84: =IFERROR(__xludf.DUMMYFUNCTION("""COMPUTED_VALUE"""),1.0) -> 1 | K84: =IFERROR(__xludf.DUMMYFUNCTION("""COMPUTED_VALUE"""),29524.0) -> 29524 | L84: =IFERROR(__xludf.DUMMYFUNCTION("""COMPUTED_VALUE"""),0.0) -> 0 | M84: =IFERROR(__xludf.DUMMYFUNCTION("""COMPUTED_VALUE"""),29524.0) -> 29524 | N84: =IFERROR(__xludf.DUMMYFUNCTION("""COMPUTED_VALUE"""),0.0) -> 0 | O84: =IFERROR(__xludf.DUMMYFUNCTION("""COMPUTED_VALUE"""),29524.0) -> 29524 | P84: =IFERROR(__xludf.DUMMYFUNCTION("""COMPUTED_VALUE"""),1476.0) -> 1476 | Q84: =IFERROR(__xludf.DUMMYFUNCTION("""COMPUTED_VALUE"""),"Take Away") -> Take Away | R84: =IFERROR(__xludf.DUMMYFUNCTION("""COMPUTED_VALUE"""),"Kedai") -> Kedai | S84: =IFERROR(__xludf.DUMMYFUNCTION("""COMPUTED_VALUE"""),"Temu Roti") -> Temu Roti | T84: =IFERROR(__xludf.DUMMYFUNCTION("""COMPUTED_VALUE"""),"Owner") -> Owner | X84: =IFERROR(__xludf.DUMMYFUNCTION("""COMPUTED_VALUE"""),"Closed") -> Closed
A85: 29/09/2024 11:59,2-9537,Sale,Roti,10000,Roti Bawang Saus Keju,,,1.000,29524.00,0.00,29524.00,0.00,29524.00,1476.00,Dine In,Kedai,Temu Roti,Owner,,,,Closed | B85: =IFERROR(__xludf.DUMMYFUNCTION("SPLIT(A85,"","",0,0)"),45564.49930555555) -> 45564.499 | C85: =IFERROR(__xludf.DUMMYFUNCTION("""COMPUTED_VALUE"""),2789390.0) -> 2789390 | D85: =IFERROR(__xludf.DUMMYFUNCTION("""COMPUTED_VALUE"""),"Sale") -> Sale | E85: =IFERROR(__xludf.DUMMYFUNCTION("""COMPUTED_VALUE"""),"Roti") -> Roti | F85: =IFERROR(__xludf.DUMMYFUNCTION("""COMPUTED_VALUE"""),10000.0) -> 10000 | G85: =IFERROR(__xludf.DUMMYFUNCTION("""COMPUTED_VALUE"""),"Roti Bawang Saus Keju") -> Roti Bawang Saus Keju | J85: =IFERROR(__xludf.DUMMYFUNCTION("""COMPUTED_VALUE"""),1.0) -> 1 | K85: =IFERROR(__xludf.DUMMYFUNCTION("""COMPUTED_VALUE"""),29524.0) -> 29524 | L85: =IFERROR(__xludf.DUMMYFUNCTION("""COMPUTED_VALUE"""),0.0) -> 0 | M85: =IFERROR(__xludf.DUMMYFUNCTION("""COMPUTED_VALUE"""),29524.0) -> 29524 | N85: =IFERROR(__xludf.DUMMYFUNCTION("""COMPUTED_VALUE"""),0.0) -> 0 | O85: =IFERROR(__xludf.DUMMYFUNCTION("""COMPUTED_VALUE"""),29524.0) -> 29524 | P85: =IFERROR(__xludf.DUMMYFUNCTION("""COMPUTED_VALUE"""),1476.0) -> 1476 | Q85: =IFERROR(__xludf.DUMMYFUNCTION("""COMPUTED_VALUE"""),"Dine In") -> Dine In | R85: =IFERROR(__xludf.DUMMYFUNCTION("""COMPUTED_VALUE"""),"Kedai") -> Kedai | S85: =IFERROR(__xludf.DUMMYFUNCTION("""COMPUTED_VALUE"""),"Temu Roti") -> Temu Roti | T85: =IFERROR(__xludf.DUMMYFUNCTION("""COMPUTED_VALUE"""),"Owner") -> Owner | X85: =IFERROR(__xludf.DUMMYFUNCTION("""COMPUTED_VALUE"""),"Closed") -> Closed
A86: 29/09/2024 11:58,2-9536,Sale,Minuman,10128,Es Kopi Susu,,,1.000,23333.00,0.00,23333.00,0.00,23333.00,1167.00,Dine In,Kedai,Temu Roti,Owner,,,,Closed | B86: =IFERROR(__xludf.DUMMYFUNCTION("SPLIT(A86,"","",0,0)"),45564.498611111114) -> 45564.499 | C86: =IFERROR(__xludf.DUMMYFUNCTION("""COMPUTED_VALUE"""),2789024.0) -> 2789024 | D86: =IFERROR(__xludf.DUMMYFUNCTION("""COMPUTED_VALUE"""),"Sale") -> Sale | E86: =IFERROR(__xludf.DUMMYFUNCTION("""COMPUTED_VALUE"""),"Minuman") -> Minuman | F86: =IFERROR(__xludf.DUMMYFUNCTION("""COMPUTED_VALUE"""),10128.0) -> 10128 | G86: =IFERROR(__xludf.DUMMYFUNCTION("""COMPUTED_VALUE"""),"Es Kopi Susu") -> Es Kopi Susu | J86: =IFERROR(__xludf.DUMMYFUNCTION("""COMPUTED_VALUE"""),1.0) -> 1 | K86: =IFERROR(__xludf.DUMMYFUNCTION("""COMPUTED_VALUE"""),23333.0) -> 23333 | L86: =IFERROR(__xludf.DUMMYFUNCTION("""COMPUTED_VALUE"""),0.0) -> 0 | M86: =IFERROR(__xludf.DUMMYFUNCTION("""COMPUTED_VALUE"""),23333.0) -> 23333 | N86: =IFERROR(__xludf.DUMMYFUNCTION("""COMPUTED_VALUE"""),0.0) -> 0 | O86: =IFERROR(__xludf.DUMMYFUNCTION("""COMPUTED_VALUE"""),23333.0) -> 23333 | P86: =IFERROR(__xludf.DUMMYFUNCTION("""COMPUTED_VALUE"""),1167.0) -> 1167 | Q86: =IFERROR(__xludf.DUMMYFUNCTION("""COMPUTED_VALUE"""),"Dine In") -> Dine In | R86: =IFERROR(__xludf.DUMMYFUNCTION("""COMPUTED_VALUE"""),"Kedai") -> Kedai | S86: =IFERROR(__xludf.DUMMYFUNCTION("""COMPUTED_VALUE"""),"Temu Roti") -> Temu Roti | T86: =IFERROR(__xludf.DUMMYFUNCTION("""COMPUTED_VALUE"""),"Owner") -> Owner | X86: =IFERROR(__xludf.DUMMYFUNCTION("""COMPUTED_VALUE"""),"Closed") -> Closed
A87: 29/09/2024 11:58,2-9536,Sale,Minuman,10013,Kopi cur,,,1.000,23333.00,0.00,23333.00,0.00,23333.00,1166.00,Dine In,Kedai,Temu Roti,Owner,,,,Closed | B87: =IFERROR(__xludf.DUMMYFUNCTION("SPLIT(A87,"","",0,0)"),45564.498611111114) -> 45564.499 | C87: =IFERROR(__xludf.DUMMYFUNCTION("""COMPUTED_VALUE"""),2789024.0) -> 2789024 | D87: =IFERROR(__xludf.DUMMYFUNCTION("""COMPUTED_VALUE"""),"Sale") -> Sale | E87: =IFERROR(__xludf.DUMMYFUNCTION("""COMPUTED_VALUE"""),"Minuman") -> Minuman | F87: =IFERROR(__xludf.DUMMYFUNCTION("""COMPUTED_VALUE"""),10013.0) -> 10013 | G87: =IFERROR(__xludf.DUMMYFUNCTION("""COMPUTED_VALUE"""),"Kopi cur") -> Kopi cur | J87: =IFERROR(__xludf.DUMMYFUNCTION("""COMPUTED_VALUE"""),1.0) -> 1 | K87: =IFERROR(__xludf.DUMMYFUNCTION("""COMPUTED_VALUE"""),23333.0) -> 23333 | L87: =IFERROR(__xludf.DUMMYFUNCTION("""COMPUTED_VALUE"""),0.0) -> 0 | M87: =IFERROR(__xludf.DUMMYFUNCTION("""COMPUTED_VALUE"""),23333.0) -> 23333 | N87: =IFERROR(__xludf.DUMMYFUNCTION("""COMPUTED_VALUE"""),0.0) -> 0 | O87: =IFERROR(__xludf.DUMMYFUNCTION("""COMPUTED_VALUE"""),23333.0) -> 23333 | P87: =IFERROR(__xludf.DUMMYFUNCTION("""COMPUTED_VALUE"""),1166.0) -> 1166 | Q87: =IFERROR(__xludf.DUMMYFUNCTION("""COMPUTED_VALUE"""),"Dine In") -> Dine In | R87: =IFERROR(__xludf.DUMMYFUNCTION("""COMPUTED_VALUE"""),"Kedai") -> Kedai | S87: =IFERROR(__xludf.DUMMYFUNCTION("""COMPUTED_VALUE"""),"Temu Roti") -> Temu Roti | T87: =IFERROR(__xludf.DUMMYFUNCTION("""COMPUTED_VALUE"""),"Owner") -> Owner | X87: =IFERROR(__xludf.DUMMYFUNCTION("""COMPUTED_VALUE"""),"Closed") -> Closed
A88: 29/09/2024 11:58,2-9536,Sale,Roti,10007,Roti cranberry 2 pcs,,,1.000,33810.00,0.00,33810.00,0.00,33810.00,1691.00,Dine In,Kedai,Temu Roti,Owner,,,,Closed | B88: =IFERROR(__xludf.DUMMYFUNCTION("SPLIT(A88,"","",0,0)"),45564.498611111114) -> 45564.499 | C88: =IFERROR(__xludf.DUMMYFUNCTION("""COMPUTED_VALUE"""),2789024.0) -> 2789024 | D88: =IFERROR(__xludf.DUMMYFUNCTION("""COMPUTED_VALUE"""),"Sale") -> Sale | E88: =IFERROR(__xludf.DUMMYFUNCTION("""COMPUTED_VALUE"""),"Roti") -> Roti | F88: =IFERROR(__xludf.DUMMYFUNCTION("""COMPUTED_VALUE"""),10007.0) -> 10007 | G88: =IFERROR(__xludf.DUMMYFUNCTION("""COMPUTED_VALUE"""),"Roti cranberry 2 pcs") -> Roti cranberry 2 pcs | J88: =IFERROR(__xludf.DUMMYFUNCTION("""COMPUTED_VALUE"""),1.0) -> 1 | K88: =IFERROR(__xludf.DUMMYFUNCTION("""COMPUTED_VALUE"""),33810.0) -> 33810 | L88: =IFERROR(__xludf.DUMMYFUNCTION("""COMPUTED_VALUE"""),0.0) -> 0 | M88: =IFERROR(__xludf.DUMMYFUNCTION("""COMPUTED_VALUE"""),33810.0) -> 33810 | N88: =IFERROR(__xludf.DUMMYFUNCTION("""COMPUTED_VALUE"""),0.0) -> 0 | O88: =IFERROR(__xludf.DUMMYFUNCTION("""COMPUTED_VALUE"""),33810.0) -> 33810 | P88: =IFERROR(__xludf.DUMMYFUNCTION("""COMPUTED_VALUE"""),1691.0) -> 1691 | Q88: =IFERROR(__xludf.DUMMYFUNCTION("""COMPUTED_VALUE"""),"Dine In") -> Dine In | R88: =IFERROR(__xludf.DUMMYFUNCTION("""COMPUTED_VALUE"""),"Kedai") -> Kedai | S88: =IFERROR(__xludf.DUMMYFUNCTION("""COMPUTED_VALUE"""),"Temu Roti") -> Temu Roti | T88: =IFERROR(__xludf.DUMMYFUNCTION("""COMPUTED_VALUE"""),"Owner") -> Owner | X88: =IFERROR(__xludf.DUMMYFUNCTION("""COMPUTED_VALUE"""),"Closed") -> Closed
A89: 29/09/2024 11:58,2-9536,Sale,Minuman,10122,Rempah Madu Panas,,,1.000,21905.00,0.00,21905.00,0.00,21905.00,1095.00,Dine In,Kedai,Temu Roti,Owner,,,,Closed | B89: =IFERROR(__xludf.DUMMYFUNCTION("SPLIT(A89,"","",0,0)"),45564.498611111114) -> 45564.499 | C89: =IFERROR(__xludf.DUMMYFUNCTION("""COMPUTED_VALUE"""),2789024.0) -> 2789024 | D89: =IFERROR(__xludf.DUMMYFUNCTION("""COMPUTED_VALUE"""),"Sale") -> Sale | E89: =IFERROR(__xludf.DUMMYFUNCTION("""COMPUTED_VALUE"""),"Minuman") -> Minuman | F89: =IFERROR(__xludf.DUMMYFUNCTION("""COMPUTED_VALUE"""),10122.0) -> 10122 | G89: =IFERROR(__xludf.DUMMYFUNCTION("""COMPUTED_VALUE"""),"Rempah Madu Panas") -> Rempah Madu Panas | J89: =IFERROR(__xludf.DUMMYFUNCTION("""COMPUTED_VALUE"""),1.0) -> 1 | K89: =IFERROR(__xludf.DUMMYFUNCTION("""COMPUTED_VALUE"""),21905.0) -> 21905 | L89: =IFERROR(__xludf.DUMMYFUNCTION("""COMPUTED_VALUE"""),0.0) -> 0 | M89: =IFERROR(__xludf.DUMMYFUNCTION("""COMPUTED_VALUE"""),21905.0) -> 21905 | N89: =IFERROR(__xludf.DUMMYFUNCTION("""COMPUTED_VALUE"""),0.0) -> 0 | O89: =IFERROR(__xludf.DUMMYFUNCTION("""COMPUTED_VALUE"""),21905.0) -> 21905 | P89: =IFERROR(__xludf.DUMMYFUNCTION("""COMPUTED_VALUE"""),1095.0) -> 1095 | Q89: =IFERROR(__xludf.DUMMYFUNCTION("""COMPUTED_VALUE"""),"Dine In") -> Dine In | R89: =IFERROR(__xludf.DUMMYFUNCTION("""COMPUTED_VALUE"""),"Kedai") -> Kedai | S89: =IFERROR(__xludf.DUMMYFUNCTION("""COMPUTED_VALUE"""),"Temu Roti") -> Temu Roti | T89: =IFERROR(__xludf.DUMMYFUNCTION("""COMPUTED_VALUE"""),"Owner") -> Owner | X89: =IFERROR(__xludf.DUMMYFUNCTION("""COMPUTED_VALUE"""),"Closed") -> Closed
A90: 29/09/2024 11:57,2-9535,Sale,Minuman,10122,Rempah Madu Panas,,,1.000,21905.00,0.00,21905.00,0.00,21905.00,1095.00,Dine In,Kedai,Temu Roti,Owner,,,,Closed | B90: =IFERROR(__xludf.DUMMYFUNCTION("SPLIT(A90,"","",0,0)"),45564.49791666667) -> 45564.498 | C90: =IFERROR(__xludf.DUMMYFUNCTION("""COMPUTED_VALUE"""),2788659.0) -> 2788659 | D90: =IFERROR(__xludf.DUMMYFUNCTION("""COMPUTED_VALUE"""),"Sale") -> Sale | E90: =IFERROR(__xludf.DUMMYFUNCTION("""COMPUTED_VALUE"""),"Minuman") -> Minuman | F90: =IFERROR(__xludf.DUMMYFUNCTION("""COMPUTED_VALUE"""),10122.0) -> 10122 | G90: =IFERROR(__xludf.DUMMYFUNCTION("""COMPUTED_VALUE"""),"Rempah Madu Panas") -> Rempah Madu Panas | J90: =IFERROR(__xludf.DUMMYFUNCTION("""COMPUTED_VALUE"""),1.0) -> 1 | K90: =IFERROR(__xludf.DUMMYFUNCTION("""COMPUTED_VALUE"""),21905.0) -> 21905 | L90: =IFERROR(__xludf.DUMMYFUNCTION("""COMPUTED_VALUE"""),0.0) -> 0 | M90: =IFERROR(__xludf.DUMMYFUNCTION("""COMPUTED_VALUE"""),21905.0) -> 21905 | N90: =IFERROR(__xludf.DUMMYFUNCTION("""COMPUTED_VALUE"""),0.0) -> 0 | O90: =IFERROR(__xludf.DUMMYFUNCTION("""COMPUTED_VALUE"""),21905.0) -> 21905 | P90: =IFERROR(__xludf.DUMMYFUNCTION("""COMPUTED_VALUE"""),1095.0) -> 1095 | Q90: =IFERROR(__xludf.DUMMYFUNCTION("""COMPUTED_VALUE"""),"Dine In") -> Dine In | R90: =IFERROR(__xludf.DUMMYFUNCTION("""COMPUTED_VALUE"""),"Kedai") -> Kedai | S90: =IFERROR(__xludf.DUMMYFUNCTION("""COMPUTED_VALUE"""),"Temu Roti") -> Temu Roti | T90: =IFERROR(__xludf.DUMMYFUNCTION("""COMPUTED_VALUE"""),"Owner") -> Owner | X90: =IFERROR(__xludf.DUMMYFUNCTION("""COMPUTED_VALUE"""),"Closed") -> Closed
A91: 29/09/2024 11:57,2-9535,Sale,Minuman,10128,Es Kopi Susu,,,1.000,23333.00,0.00,23333.00,0.00,23333.00,1167.00,Dine In,Kedai,Temu Roti,Owner,,,,Closed | B91: =IFERROR(__xludf.DUMMYFUNCTION("SPLIT(A91,"","",0,0)"),45564.49791666667) -> 45564.498 | C91: =IFERROR(__xludf.DUMMYFUNCTION("""COMPUTED_VALUE"""),2788659.0) -> 2788659 | D91: =IFERROR(__xludf.DUMMYFUNCTION("""COMPUTED_VALUE"""),"Sale") -> Sale | E91: =IFERROR(__xludf.DUMMYFUNCTION("""COMPUTED_VALUE"""),"Minuman") -> Minuman | F91: =IFERROR(__xludf.DUMMYFUNCTION("""COMPUTED_VALUE"""),10128.0) -> 10128 | G91: =IFERROR(__xludf.DUMMYFUNCTION("""COMPUTED_VALUE"""),"Es Kopi Susu") -> Es Kopi Susu | J91: =IFERROR(__xludf.DUMMYFUNCTION("""COMPUTED_VALUE"""),1.0) -> 1 | K91: =IFERROR(__xludf.DUMMYFUNCTION("""COMPUTED_VALUE"""),23333.0) -> 23333 | L91: =IFERROR(__xludf.DUMMYFUNCTION("""COMPUTED_VALUE"""),0.0) -> 0 | M91: =IFERROR(__xludf.DUMMYFUNCTION("""COMPUTED_VALUE"""),23333.0) -> 23333 | N91: =IFERROR(__xludf.DUMMYFUNCTION("""COMPUTED_VALUE"""),0.0) -> 0 | O91: =IFERROR(__xludf.DUMMYFUNCTION("""COMPUTED_VALUE"""),23333.0) -> 23333 | P91: =IFERROR(__xludf.DUMMYFUNCTION("""COMPUTED_VALUE"""),1167.0) -> 1167 | Q91: =IFERROR(__xludf.DUMMYFUNCTION("""COMPUTED_VALUE"""),"Dine In") -> Dine In | R91: =IFERROR(__xludf.DUMMYFUNCTION("""COMPUTED_VALUE"""),"Kedai") -> Kedai | S91: =IFERROR(__xludf.DUMMYFUNCTION("""COMPUTED_VALUE"""),"Temu Roti") -> Temu Roti | T91: =IFERROR(__xludf.DUMMYFUNCTION("""COMPUTED_VALUE"""),"Owner") -> Owner | X91: =IFERROR(__xludf.DUMMYFUNCTION("""COMPUTED_VALUE"""),"Closed") -> Closed
A92: 29/09/2024 11:57,2-9535,Sale,Minuman,10013,Kopi cur,,,1.000,23333.00,0.00,23333.00,0.00,23333.00,1167.00,Dine In,Kedai,Temu Roti,Owner,,,,Closed | B92: =IFERROR(__xludf.DUMMYFUNCTION("SPLIT(A92,"","",0,0)"),45564.49791666667) -> 45564.498 | C92: =IFERROR(__xludf.DUMMYFUNCTION("""COMPUTED_VALUE"""),2788659.0) -> 2788659 | D92: =IFERROR(__xludf.DUMMYFUNCTION("""COMPUTED_VALUE"""),"Sale") -> Sale | E92: =IFERROR(__xludf.DUMMYFUNCTION("""COMPUTED_VALUE"""),"Minuman") -> Minuman | F92: =IFERROR(__xludf.DUMMYFUNCTION("""COMPUTED_VALUE"""),10013.0) -> 10013 | G92: =IFERROR(__xludf.DUMMYFUNCTION("""COMPUTED_VALUE"""),"Kopi cur") -> Kopi cur | J92: =IFERROR(__xludf.DUMMYFUNCTION("""COMPUTED_VALUE"""),1.0) -> 1 | K92: =IFERROR(__xludf.DUMMYFUNCTION("""COMPUTED_VALUE"""),23333.0) -> 23333 | L92: =IFERROR(__xludf.DUMMYFUNCTION("""COMPUTED_VALUE"""),0.0) -> 0 | M92: =IFERROR(__xludf.DUMMYFUNCTION("""COMPUTED_VALUE"""),23333.0) -> 23333 | N92: =IFERROR(__xludf.DUMMYFUNCTION("""COMPUTED_VALUE"""),0.0) -> 0 | O92: =IFERROR(__xludf.DUMMYFUNCTION("""COMPUTED_VALUE"""),23333.0) -> 23333 | P92: =IFERROR(__xludf.DUMMYFUNCTION("""COMPUTED_VALUE"""),1167.0) -> 1167 | Q92: =IFERROR(__xludf.DUMMYFUNCTION("""COMPUTED_VALUE"""),"Dine In") -> Dine In | R92: =IFERROR(__xludf.DUMMYFUNCTION("""COMPUTED_VALUE"""),"Kedai") -> Kedai | S92: =IFERROR(__xludf.DUMMYFUNCTION("""COMPUTED_VALUE"""),"Temu Roti") -> Temu Roti | T92: =IFERROR(__xludf.DUMMYFUNCTION("""COMPUTED_VALUE"""),"Owner") -> Owner | X92: =IFERROR(__xludf.DUMMYFUNCTION("""COMPUTED_VALUE"""),"Closed") -> Closed
A93: 29/09/2024 11:47,2-9534,Sale,Minuman,10013,Kopi cur,,,1.000,23333.00,0.00,23333.00,0.00,23333.00,1167.00,Take Away,Kedai,Temu Roti,Owner,,,,Closed | B93: =IFERROR(__xludf.DUMMYFUNCTION("SPLIT(A93,"","",0,0)"),45564.49097222222) -> 45564.491 | C93: =IFERROR(__xludf.DUMMYFUNCTION("""COMPUTED_VALUE"""),2788294.0) -> 2788294 | D93: =IFERROR(__xludf.DUMMYFUNCTION("""COMPUTED_VALUE"""),"Sale") -> Sale | E93: =IFERROR(__xludf.DUMMYFUNCTION("""COMPUTED_VALUE"""),"Minuman") -> Minuman | F93: =IFERROR(__xludf.DUMMYFUNCTION("""COMPUTED_VALUE"""),10013.0) -> 10013 | G93: =IFERROR(__xludf.DUMMYFUNCTION("""COMPUTED_VALUE"""),"Kopi cur") -> Kopi cur | J93: =IFERROR(__xludf.DUMMYFUNCTION("""COMPUTED_VALUE"""),1.0) -> 1 | K93: =IFERROR(__xludf.DUMMYFUNCTION("""COMPUTED_VALUE"""),23333.0) -> 23333 | L93: =IFERROR(__xludf.DUMMYFUNCTION("""COMPUTED_VALUE"""),0.0) -> 0 | M93: =IFERROR(__xludf.DUMMYFUNCTION("""COMPUTED_VALUE"""),23333.0) -> 23333 | N93: =IFERROR(__xludf.DUMMYFUNCTION("""COMPUTED_VALUE"""),0.0) -> 0 | O93: =IFERROR(__xludf.DUMMYFUNCTION("""COMPUTED_VALUE"""),23333.0) -> 23333 | P93: =IFERROR(__xludf.DUMMYFUNCTION("""COMPUTED_VALUE"""),1167.0) -> 1167 | Q93: =IFERROR(__xludf.DUMMYFUNCTION("""COMPUTED_VALUE"""),"Take Away") -> Take Away | R93: =IFERROR(__xludf.DUMMYFUNCTION("""COMPUTED_VALUE"""),"Kedai") -> Kedai | S93: =IFERROR(__xludf.DUMMYFUNCTION("""COMPUTED_VALUE"""),"Temu Roti") -> Temu Roti | T93: =IFERROR(__xludf.DUMMYFUNCTION("""COMPUTED_VALUE"""),"Owner") -> Owner | X93: =IFERROR(__xludf.DUMMYFUNCTION("""COMPUTED_VALUE"""),"Closed") -> Closed
A94: 29/09/2024 11:47,2-9534,Sale,Roti,10007,Roti cranberry 2 pcs,,,1.000,33810.00,0.00,33810.00,0.00,33810.00,1690.00,Take Away,Kedai,Temu Roti,Owner,,,,Closed | B94: =IFERROR(__xludf.DUMMYFUNCTION("SPLIT(A94,"","",0,0)"),45564.49097222222) -> 45564.491 | C94: =IFERROR(__xludf.DUMMYFUNCTION("""COMPUTED_VALUE"""),2788294.0) -> 2788294 | D94: =IFERROR(__xludf.DUMMYFUNCTION("""COMPUTED_VALUE"""),"Sale") -> Sale | E94: =IFERROR(__xludf.DUMMYFUNCTION("""COMPUTED_VALUE"""),"Roti") -> Roti | F94: =IFERROR(__xludf.DUMMYFUNCTION("""COMPUTED_VALUE"""),10007.0) -> 10007 | G94: =IFERROR(__xludf.DUMMYFUNCTION("""COMPUTED_VALUE"""),"Roti cranberry 2 pcs") -> Roti cranberry 2 pcs | J94: =IFERROR(__xludf.DUMMYFUNCTION("""COMPUTED_VALUE"""),1.0) -> 1 | K94: =IFERROR(__xludf.DUMMYFUNCTION("""COMPUTED_VALUE"""),33810.0) -> 33810 | L94: =IFERROR(__xludf.DUMMYFUNCTION("""COMPUTED_VALUE"""),0.0) -> 0 | M94: =IFERROR(__xludf.DUMMYFUNCTION("""COMPUTED_VALUE"""),33810.0) -> 33810 | N94: =IFERROR(__xludf.DUMMYFUNCTION("""COMPUTED_VALUE"""),0.0) -> 0 | O94: =IFERROR(__xludf.DUMMYFUNCTION("""COMPUTED_VALUE"""),33810.0) -> 33810 | P94: =IFERROR(__xludf.DUMMYFUNCTION("""COMPUTED_VALUE"""),1690.0) -> 1690 | Q94: =IFERROR(__xludf.DUMMYFUNCTION("""COMPUTED_VALUE"""),"Take Away") -> Take Away | R94: =IFERROR(__xludf.DUMMYFUNCTION("""COMPUTED_VALUE"""),"Kedai") -> Kedai | S94: =IFERROR(__xludf.DUMMYFUNCTION("""COMPUTED_VALUE"""),"Temu Roti") -> Temu Roti | T94: =IFERROR(__xludf.DUMMYFUNCTION("""COMPUTED_VALUE"""),"Owner") -> Owner | X94: =IFERROR(__xludf.DUMMYFUNCTION("""COMPUTED_VALUE"""),"Closed") -> Closed
A95: 29/09/2024 11:47,2-9534,Sale,Roti,10005,Roti Gandum Cokelat,,,1.000,19524.00,0.00,19524.00,0.00,19524.00,976.00,Take Away,Kedai,Temu Roti,Owner,,,,Closed | B95: =IFERROR(__xludf.DUMMYFUNCTION("SPLIT(A95,"","",0,0)"),45564.49097222222) -> 45564.491 | C95: =IFERROR(__xludf.DUMMYFUNCTION("""COMPUTED_VALUE"""),2788294.0) -> 2788294 | D95: =IFERROR(__xludf.DUMMYFUNCTION("""COMPUTED_VALUE"""),"Sale") -> Sale | E95: =IFERROR(__xludf.DUMMYFUNCTION("""COMPUTED_VALUE"""),"Roti") -> Roti | F95: =IFERROR(__xludf.DUMMYFUNCTION("""COMPUTED_VALUE"""),10005.0) -> 10005 | G95: =IFERROR(__xludf.DUMMYFUNCTION("""COMPUTED_VALUE"""),"Roti Gandum Cokelat") -> Roti Gandum Cokelat | J95: =IFERROR(__xludf.DUMMYFUNCTION("""COMPUTED_VALUE"""),1.0) -> 1 | K95: =IFERROR(__xludf.DUMMYFUNCTION("""COMPUTED_VALUE"""),19524.0) -> 19524 | L95: =IFERROR(__xludf.DUMMYFUNCTION("""COMPUTED_VALUE"""),0.0) -> 0 | M95: =IFERROR(__xludf.DUMMYFUNCTION("""COMPUTED_VALUE"""),19524.0) -> 19524 | N95: =IFERROR(__xludf.DUMMYFUNCTION("""COMPUTED_VALUE"""),0.0) -> 0 | O95: =IFERROR(__xludf.DUMMYFUNCTION("""COMPUTED_VALUE"""),19524.0) -> 19524 | P95: =IFERROR(__xludf.DUMMYFUNCTION("""COMPUTED_VALUE"""),976.0) -> 976 | Q95: =IFERROR(__xludf.DUMMYFUNCTION("""COMPUTED_VALUE"""),"Take Away") -> Take Away | R95: =IFERROR(__xludf.DUMMYFUNCTION("""COMPUTED_VALUE"""),"Kedai") -> Kedai | S95: =IFERROR(__xludf.DUMMYFUNCTION("""COMPUTED_VALUE"""),"Temu Roti") -> Temu Roti | T95: =IFERROR(__xludf.DUMMYFUNCTION("""COMPUTED_VALUE"""),"Owner") -> Owner | X95: =IFERROR(__xludf.DUMMYFUNCTION("""COMPUTED_VALUE"""),"Closed") -> Closed
A96: 29/09/2024 11:47,2-9534,Sale,Kudapan,10004,Tahu walik,,,1.000,25238.00,0.00,25238.00,0.00,25238.00,1262.00,Take Away,Kedai,Temu Roti,Owner,,,,Closed | B96: =IFERROR(__xludf.DUMMYFUNCTION("SPLIT(A96,"","",0,0)"),45564.49097222222) -> 45564.491 | C96: =IFERROR(__xludf.DUMMYFUNCTION("""COMPUTED_VALUE"""),2788294.0) -> 2788294 | D96: =IFERROR(__xludf.DUMMYFUNCTION("""COMPUTED_VALUE"""),"Sale") -> Sale | E96: =IFERROR(__xludf.DUMMYFUNCTION("""COMPUTED_VALUE"""),"Kudapan") -> Kudapan | F96: =IFERROR(__xludf.DUMMYFUNCTION("""COMPUTED_VALUE"""),10004.0) -> 10004 | G96: =IFERROR(__xludf.DUMMYFUNCTION("""COMPUTED_VALUE"""),"Tahu walik") -> Tahu walik | J96: =IFERROR(__xludf.DUMMYFUNCTION("""COMPUTED_VALUE"""),1.0) -> 1 | K96: =IFERROR(__xludf.DUMMYFUNCTION("""COMPUTED_VALUE"""),25238.0) -> 25238 | L96: =IFERROR(__xludf.DUMMYFUNCTION("""COMPUTED_VALUE"""),0.0) -> 0 | M96: =IFERROR(__xludf.DUMMYFUNCTION("""COMPUTED_VALUE"""),25238.0) -> 25238 | N96: =IFERROR(__xludf.DUMMYFUNCTION("""COMPUTED_VALUE"""),0.0) -> 0 | O96: =IFERROR(__xludf.DUMMYFUNCTION("""COMPUTED_VALUE"""),25238.0) -> 25238 | P96: =IFERROR(__xludf.DUMMYFUNCTION("""COMPUTED_VALUE"""),1262.0) -> 1262 | Q96: =IFERROR(__xludf.DUMMYFUNCTION("""COMPUTED_VALUE"""),"Take Away") -> Take Away | R96: =IFERROR(__xludf.DUMMYFUNCTION("""COMPUTED_VALUE"""),"Kedai") -> Kedai | S96: =IFERROR(__xludf.DUMMYFUNCTION("""COMPUTED_VALUE"""),"Temu Roti") -> Temu Roti | T96: =IFERROR(__xludf.DUMMYFUNCTION("""COMPUTED_VALUE"""),"Owner") -> Owner | X96: =IFERROR(__xludf.DUMMYFUNCTION("""COMPUTED_VALUE"""),"Closed") -> Closed
A97: 29/09/2024 11:45,2-9533,Sale,Roti,10007,Roti cranberry 2 pcs,,,1.000,33810.00,0.00,33810.00,0.00,33810.00,1691.00,Take Away,Kedai,Temu Roti,Owner,,,,Closed | B97: =IFERROR(__xludf.DUMMYFUNCTION("SPLIT(A97,"","",0,0)"),45564.489583333336) -> 45564.49 | C97: =IFERROR(__xludf.DUMMYFUNCTION("""COMPUTED_VALUE"""),2787929.0) -> 2787929 | D97: =IFERROR(__xludf.DUMMYFUNCTION("""COMPUTED_VALUE"""),"Sale") -> Sale | E97: =IFERROR(__xludf.DUMMYFUNCTION("""COMPUTED_VALUE"""),"Roti") -> Roti | F97: =IFERROR(__xludf.DUMMYFUNCTION("""COMPUTED_VALUE"""),10007.0) -> 10007 | G97: =IFERROR(__xludf.DUMMYFUNCTION("""COMPUTED_VALUE"""),"Roti cranberry 2 pcs") -> Roti cranberry 2 pcs | J97: =IFERROR(__xludf.DUMMYFUNCTION("""COMPUTED_VALUE"""),1.0) -> 1 | K97: =IFERROR(__xludf.DUMMYFUNCTION("""COMPUTED_VALUE"""),33810.0) -> 33810 | L97: =IFERROR(__xludf.DUMMYFUNCTION("""COMPUTED_VALUE"""),0.0) -> 0 | M97: =IFERROR(__xludf.DUMMYFUNCTION("""COMPUTED_VALUE"""),33810.0) -> 33810 | N97: =IFERROR(__xludf.DUMMYFUNCTION("""COMPUTED_VALUE"""),0.0) -> 0 | O97: =IFERROR(__xludf.DUMMYFUNCTION("""COMPUTED_VALUE"""),33810.0) -> 33810 | P97: =IFERROR(__xludf.DUMMYFUNCTION("""COMPUTED_VALUE"""),1691.0) -> 1691 | Q97: =IFERROR(__xludf.DUMMYFUNCTION("""COMPUTED_VALUE"""),"Take Away") -> Take Away | R97: =IFERROR(__xludf.DUMMYFUNCTION("""COMPUTED_VALUE"""),"Kedai") -> Kedai | S97: =IFERROR(__xludf.DUMMYFUNCTION("""COMPUTED_VALUE"""),"Temu Roti") -> Temu Roti | T97: =IFERROR(__xludf.DUMMYFUNCTION("""COMPUTED_VALUE"""),"Owner") -> Owner | X97: =IFERROR(__xludf.DUMMYFUNCTION("""COMPUTED_VALUE"""),"Closed") -> Closed
A98: 29/09/2024 11:45,2-9533,Sale,Roti,10005,Roti Gandum Cokelat,,,1.000,19524.00,0.00,19524.00,0.00,19524.00,976.00,Take Away,Kedai,Temu Roti,Owner,,,,Closed | B98: =IFERROR(__xludf.DUMMYFUNCTION("SPLIT(A98,"","",0,0)"),45564.489583333336) -> 45564.49 | C98: =IFERROR(__xludf.DUMMYFUNCTION("""COMPUTED_VALUE"""),2787929.0) -> 2787929 | D98: =IFERROR(__xludf.DUMMYFUNCTION("""COMPUTED_VALUE"""),"Sale") -> Sale | E98: =IFERROR(__xludf.DUMMYFUNCTION("""COMPUTED_VALUE"""),"Roti") -> Roti | F98: =IFERROR(__xludf.DUMMYFUNCTION("""COMPUTED_VALUE"""),10005.0) -> 10005 | G98: =IFERROR(__xludf.DUMMYFUNCTION("""COMPUTED_VALUE"""),"Roti Gandum Cokelat") -> Roti Gandum Cokelat | J98: =IFERROR(__xludf.DUMMYFUNCTION("""COMPUTED_VALUE"""),1.0) -> 1 | K98: =IFERROR(__xludf.DUMMYFUNCTION("""COMPUTED_VALUE"""),19524.0) -> 19524 | L98: =IFERROR(__xludf.DUMMYFUNCTION("""COMPUTED_VALUE"""),0.0) -> 0 | M98: =IFERROR(__xludf.DUMMYFUNCTION("""COMPUTED_VALUE"""),19524.0) -> 19524 | N98: =IFERROR(__xludf.DUMMYFUNCTION("""COMPUTED_VALUE"""),0.0) -> 0 | O98: =IFERROR(__xludf.DUMMYFUNCTION("""COMPUTED_VALUE"""),19524.0) -> 19524 | P98: =IFERROR(__xludf.DUMMYFUNCTION("""COMPUTED_VALUE"""),976.0) -> 976 | Q98: =IFERROR(__xludf.DUMMYFUNCTION("""COMPUTED_VALUE"""),"Take Away") -> Take Away | R98: =IFERROR(__xludf.DUMMYFUNCTION("""COMPUTED_VALUE"""),"Kedai") -> Kedai | S98: =IFERROR(__xludf.DUMMYFUNCTION("""COMPUTED_VALUE"""),"Temu Roti") -> Temu Roti | T98: =IFERROR(__xludf.DUMMYFUNCTION("""COMPUTED_VALUE"""),"Owner") -> Owner | X98: =IFERROR(__xludf.DUMMYFUNCTION("""COMPUTED_VALUE"""),"Closed") -> Closed
A99: 29/09/2024 11:45,2-9533,Sale,Minuman,10013,Kopi cur,,,1.000,23333.00,0.00,23333.00,0.00,23333.00,1166.00,Take Away,Kedai,Temu Roti,Owner,,,,Closed | B99: =IFERROR(__xludf.DUMMYFUNCTION("SPLIT(A99,"","",0,0)"),45564.489583333336) -> 45564.49 | C99: =IFERROR(__xludf.DUMMYFUNCTION("""COMPUTED_VALUE"""),2787929.0) -> 2787929 | D99: =IFERROR(__xludf.DUMMYFUNCTION("""COMPUTED_VALUE"""),"Sale") -> Sale | E99: =IFERROR(__xludf.DUMMYFUNCTION("""COMPUTED_VALUE"""),"Minuman") -> Minuman | F99: =IFERROR(__xludf.DUMMYFUNCTION("""COMPUTED_VALUE"""),10013.0) -> 10013 | G99: =IFERROR(__xludf.DUMMYFUNCTION("""COMPUTED_VALUE"""),"Kopi cur") -> Kopi cur | J99: =IFERROR(__xludf.DUMMYFUNCTION("""COMPUTED_VALUE"""),1.0) -> 1 | K99: =IFERROR(__xludf.DUMMYFUNCTION("""COMPUTED_VALUE"""),23333.0) -> 23333 | L99: =IFERROR(__xludf.DUMMYFUNCTION("""COMPUTED_VALUE"""),0.0) -> 0 | M99: =IFERROR(__xludf.DUMMYFUNCTION("""COMPUTED_VALUE"""),23333.0) -> 23333 | N99: =IFERROR(__xludf.DUMMYFUNCTION("""COMPUTED_VALUE"""),0.0) -> 0 | O99: =IFERROR(__xludf.DUMMYFUNCTION("""COMPUTED_VALUE"""),23333.0) -> 23333 | P99: =IFERROR(__xludf.DUMMYFUNCTION("""COMPUTED_VALUE"""),1166.0) -> 1166 | Q99: =IFERROR(__xludf.DUMMYFUNCTION("""COMPUTED_VALUE"""),"Take Away") -> Take Away | R99: =IFERROR(__xludf.DUMMYFUNCTION("""COMPUTED_VALUE"""),"Kedai") -> Kedai | S99: =IFERROR(__xludf.DUMMYFUNCTION("""COMPUTED_VALUE"""),"Temu Roti") -> Temu Roti | T99: =IFERROR(__xludf.DUMMYFUNCTION("""COMPUTED_VALUE"""),"Owner") -> Owner | X99: =IFERROR(__xludf.DUMMYFUNCTION("""COMPUTED_VALUE"""),"Closed") -> Closed
A100: 29/09/2024 10:55,2-9532,Sale,Minuman,10026,Es Kopi Lemon,,,1.000,21905.00,0.00,21905.00,0.00,21905.00,1095.00,Dine In,Kedai,Temu Roti,Owner,,,,Closed | B100: =IFERROR(__xludf.DUMMYFUNCTION("SPLIT(A100,"","",0,0)"),45564.45486111111) -> 45564.455 | C100: =IFERROR(__xludf.DUMMYFUNCTION("""COMPUTED_VALUE"""),2787563.0) -> 2787563 | D100: =IFERROR(__xludf.DUMMYFUNCTION("""COMPUTED_VALUE"""),"Sale") -> Sale | E100: =IFERROR(__xludf.DUMMYFUNCTION("""COMPUTED_VALUE"""),"Minuman") -> Minuman | F100: =IFERROR(__xludf.DUMMYFUNCTION("""COMPUTED_VALUE"""),10026.0) -> 10026 | G100: =IFERROR(__xludf.DUMMYFUNCTION("""COMPUTED_VALUE"""),"Es Kopi Lemon") -> Es Kopi Lemon | J100: =IFERROR(__xludf.DUMMYFUNCTION("""COMPUTED_VALUE"""),1.0) -> 1 | K100: =IFERROR(__xludf.DUMMYFUNCTION("""COMPUTED_VALUE"""),21905.0) -> 21905 | L100: =IFERROR(__xludf.DUMMYFUNCTION("""COMPUTED_VALUE"""),0.0) -> 0 | M100: =IFERROR(__xludf.DUMMYFUNCTION("""COMPUTED_VALUE"""),21905.0) -> 21905 | N100: =IFERROR(__xludf.DUMMYFUNCTION("""COMPUTED_VALUE"""),0.0) -> 0 | O100: =IFERROR(__xludf.DUMMYFUNCTION("""COMPUTED_VALUE"""),21905.0) -> 21905 | P100: =IFERROR(__xludf.DUMMYFUNCTION("""COMPUTED_VALUE"""),1095.0) -> 1095 | Q100: =IFERROR(__xludf.DUMMYFUNCTION("""COMPUTED_VALUE"""),"Dine In") -> Dine In | R100: =IFERROR(__xludf.DUMMYFUNCTION("""COMPUTED_VALUE"""),"Kedai") -> Kedai | S100: =IFERROR(__xludf.DUMMYFUNCTION("""COMPUTED_VALUE"""),"Temu Roti") -> Temu Roti | T100: =IFERROR(__xludf.DUMMYFUNCTION("""COMPUTED_VALUE"""),"Owner") -> Owner | X100: =IFERROR(__xludf.DUMMYFUNCTION("""COMPUTED_VALUE"""),"Closed") -> Closed
...

Sheet Data
A1: Date | B1: Receipt number | C1: Receipt type | D1: Category | E1: SKU | F1: Item | G1: Variant | H1: Modifiers applied | I1: Quantity | J1: Gross sales | K1: Discounts | L1: Net sales | M1: Cost of goods | N1: Gross profit | O1: Taxes | P1: Dining option | Q1: POS | R1: Store | S1: Cashier name | T1: Customer name | U1: Customer contacts | V1: Comment | W1: Status
A2: 45564.851 | B2: 2801443 | C2: Refund | D2: Roti | E2: 10000 | F2: Roti Bawang Saus Keju | I2: -1 | J2: -29524 | K2: 0 | L2: -29524 | M2: 0 | N2: -29524 | O2: -1476 | P2: Take Away | Q2: Kedai | R2: Temu Roti | S2: Owner | W2: Closed
A3: 45564.85 | B3: 2801078 | C3: Refund | D3: Minuman | E3: 10112 | F3: Air mineral | I3: -2 | J3: -13334 | K3: 0 | L3: -13334 | M3: 0 | N3: -13334 | O3: -667 | P3: Dine In | Q3: Kedai | R3: Temu Roti | S3: Owner | W3: Closed
A4: 45564.844 | B4: 2800712 | C4: Sale | D4: Roti | E4: 10002 | F4: Roti Cranberry | I4: 1 | J4: 18571 | K4: 0 | L4: 18571 | M4: 0 | N4: 18571 | O4: 929 | P4: Dine In | Q4: Kedai | R4: Temu Roti | S4: Owner | W4: Closed
A5: 45564.778 | B5: 2800347 | C5: Sale | D5: Minuman | E5: 10122 | F5: Rempah Madu Panas | I5: 2 | J5: 43810 | K5: 0 | L5: 43810 | M5: 0 | N5: 43810 | O5: 2191 | P5: Dine In | Q5: Kedai | R5: Temu Roti | S5: Owner | W5: Closed
A6: 45564.778 | B6: 2800347 | C6: Sale | D6: Kudapan | E6: 10051 | F6: Tahu baso | I6: 1 | J6: 25238 | K6: 0 | L6: 25238 | M6: 0 | N6: 25238 | O6: 1261 | P6: Dine In | Q6: Kedai | R6: Temu Roti | S6: Owner | W6: Closed
A7: 45564.778 | B7: 2799982 | C7: Refund | D7: Minuman | E7: 10122 | F7: Rempah Madu Panas | I7: -1 | J7: -21905 | K7: 0 | L7: -21905 | M7: 0 | N7: -21905 | O7: -1095 | P7: Dine In | Q7: Kedai | R7: Temu Roti | S7: Owner | W7: Closed
A8: 45564.778 | B8: 2799982 | C8: Refund | D8: Kudapan | E8: 10051 | F8: Tahu baso | I8: -2 | J8: -50476 | K8: 0 | L8: -50476 | M8: 0 | N8: -50476 | O8: -2524 | P8: Dine In | Q8: Kedai | R8: Temu Roti | S8: Owner | W8: Closed
A9: 45564.778 | B9: 2799982 | C9: Refund | D9: Minuman | E9: 10122 | F9: Rempah Madu Panas | I9: -1 | J9: -21905 | K9: 0 | L9: -21905 | M9: 0 | N9: -21905 | O9: -1095 | P9: Dine In | Q9: Kedai | R9: Temu Roti | S9: Owner | W9: Closed
A10: 45564.775 | B10: 2799617 | C10: Sale | D10: Minuman | E10: 10122 | F10: Rempah Madu Panas | I10: 1 | J10: 21905 | K10: 0 | L10: 21905 | M10: 0 | N10: 21905 | O10: 1095 | P10: Dine In | Q10: Kedai | R10: Temu Roti | S10: Owner | W10: Closed
A11: 45564.775 | B11: 2799617 | C11: Sale | D11: Kudapan | E11: 10051 | F11: Tahu baso | I11: 2 | J11: 50476 | K11: 0 | L11: 50476 | M11: 0 | N11: 50476 | O11: 2524 | P11: Dine In | Q11: Kedai | R11: Temu Roti | S11: Owner | W11: Closed
A12: 45564.775 | B12: 2799617 | C12: Sale | D12: Minuman | E12: 10122 | F12: Rempah Madu Panas | I12: 1 | J12: 21905 | K12: 0 | L12: 21905 | M12: 0 | N12: 21905 | O12: 1095 | P12: Dine In | Q12: Kedai | R12: Temu Roti | S12: Owner | W12: Closed
A13: 45564.772 | B13: 2799251 | C13: Sale | D13: Hidangan Utama | E13: 10104 | F13: Chicken Claypot Rice | I13: 1 | J13: 34762 | K13: 0 | L13: 34762 | M13: 0 | N13: 34762 | O13: 1738 | P13: Dine In | Q13: Kedai | R13: Temu Roti | S13: Owner | W13: Closed
... A355: 45557.561 | B355: 2752135 | C355: Sale | D355: Roti | E355: 10002 | F355: Roti Cranberry | I355: 1 | J355: 18571 | K355: 0 | L355: 18571 | M355: 0 | N355: 18571 | O355: 928 | P355: Dine In | Q355: Kedai | R355: Temu Roti | S355: Owner | W355: Closed
A356: 45557.561 | B356: 2752135 | C356: Sale | D356: Minuman | E356: 10057 | F356: Susu murni strawberry | I356: 1 | J356: 19524 | K356: 0 | L356: 19524 | M356: 0 | N356: 19524 | O356: 977 | P356: Dine In | Q356: Kedai | R356: Temu Roti | S356: Owner | V356: Dingin | W356: Closed
A357: 45557.548 | B357: 2751770 | C357: Sale | D357: Roti | E357: 10007 | F357: Roti cranberry 2 pcs | I357: 1 | J357: 33810 | K357: 0 | L357: 33810 | M357: 0 | N357: 33810 | O357: 1691 | P357: Dine In | Q357: Kedai | R357: Temu Roti | S357: Owner | W357: Closed
A358: 45557.548 | B358: 2751770 | C358: Sale | D358: Roti | E358: 10055 | F358: Roti Gandum Cokelat 2 pcs | I358: 1 | J358: 34762 | K358: 0 | L358: 34762 | M358: 0 | N358: 34762 | O358: 1738 | P358: Dine In | Q358: Kedai | R358: Temu Roti | S358: Owner | W358: Closed
A359: 45557.548 | B359: 2751770 | C359: Sale | D359: Roti | E359: 10000 | F359: Roti Bawang Saus Keju | I359: 1 | J359: 29524 | K359: 0 | L359: 29524 | M359: 0 | N359: 29524 | O359: 1476 | P359: Dine In | Q359: Kedai | R359: Temu Roti | S359: Owner | W359: Closed
A360: 45557.548 | B360: 2751770 | C360: Sale | D360: Minuman | E360: 10128 | F360: Es Kopi Susu | I360: 2 | J360: 46666 | K360: 0 | L360: 46666 | M360: 0 | N360: 46666 | O360: 2333 | P360: Dine In | Q360: Kedai | R360: Temu Roti | S360: Owner | W360: Closed
A361: 45557.548 | B361: 2751770 | C361: Sale | D361: Minuman | E361: 10107 | F361: Korean Mango Fresh Milk | I361: 1 | J361: 26667 | K361: 0 | L361: 26667 | M361: 0 | N361: 26667 | O361: 1333 | P361: Dine In | Q361: Kedai | R361: Temu Roti | S361: Owner | W361: Closed
A362: 45557.544 | B362: 2751405 | C362: Sale | D362: Roti | E362: 10000 | F362: Roti Bawang Saus Keju | I362: 1 | J362: 29524 | K362: 0 | L362: 29524 | M362: 0 | N362: 29524 | O362: 1476 | P362: Dine In | Q362: Kedai | R362: Temu Roti | S362: Owner | W362: Closed
A363: 45557.544 | B363: 2751405 | C363: Sale | D363: Roti | E363: 10055 | F363: Roti Gandum Cokelat 2 pcs | I363: 1 | J363: 34762 | K363: 0 | L363: 34762 | M363: 0 | N363: 34762 | O363: 1738 | P363: Dine In | Q363: Kedai | R363: Temu Roti | S363: Owner | W363: Closed
A364: 45557.497 | B364: 2751039 | C364: Sale | D364: Roti | E364: 10007 | F364: Roti cranberry 2 pcs | I364: 1 | J364: 33810 | K364: 0 | L364: 33810 | M364: 0 | N364: 33810 | O364: 1691 | P364: Dine In | Q364: Kedai | R364: Temu Roti | S364: Owner | W364: Closed
A365: 45557.466 | B365: 2750674 | C365: Sale | D365: Minuman | E365: 10128 | F365: Es Kopi Susu | I365: 1 | J365: 23333 | K365: 0 | L365: 23333 | M365: 0 | N365: 23333 | O365: 1167 | P365: Dine In | Q365: Kedai | R365: Temu Roti | S365: Owner | W365: Closed
A366: 45557.466 | B366: 2750674 | C366: Sale | D366: Minuman | E366: 10107 | F366: Korean Mango Fresh Milk | I366: 1 | J366: 26667 | K366: 0 | L366: 26667 | M366: 0 | N366: 26667 | O366: 1333 | P366: Dine In | Q366: Kedai | R366: Temu Roti | S366: Owner | W366: Closed
A367: 45557.466 | B367: 2750674 | C367: Sale | D367: Kudapan | E367: 10004 | F367: Tahu walik | I367: 1 | J367: 25238 | K367: 0 | L367: 25238 | M367: 0 | N367: 25238 | O367: 1262 | P367: Dine In | Q367: Kedai | R367: Temu Roti | S367: Owner | W367: Closed
A368: 45557.463 | B368: 2750309 | C368: Sale | D368: Minuman | E368: 10058 | F368: Susu murni ori | I368: 1 | J368: 19524 | K368: 0 | L368: 19524 | M368: 0 | N368: 19524 | O368: 976 | P368: Dine In | Q368: Kedai | R368: Temu Roti | S368: Owner | W368: Closed
... A1355: 45538.866 | B1355: 2606769 | C1355: Sale | D1355: Hidangan Utama | E1355: 10012 | F1355: Mie joglo | I1355: 1 | J1355: 29524 | K1355: 0 | L1355: 29524 | M1355: 0 | N1355: 29524 | O1355: 1476 | P1355: Dine In | Q1355: Kedai | R1355: Temu Roti | S1355: Owner | W1355: Closed
A1356: 45538.866 | B1356: 2606403 | C1356: Refund | D1356: Roti | E1356: 10033 | F1356: Roti panggang sarikaya | I1356: -1 | J1356: -21905 | K1356: 0 | L1356: -21905 | M1356: 0 | N1356: -21905 | O1356: -1095 | P1356: Dine In | Q1356: Kedai | R1356: Temu Roti | S1356: Owner | V1356: Sarikaya sedikit | W1356: Closed
A1357: 45538.866 | B1357: 2606403 | C1357: Refund | D1357: Kudapan | E1357: 10004 | F1357: Tahu walik | I1357: -1 | J1357: -25238 | K1357: 0 | L1357: -25238 | M1357: 0 | N1357: -25238 | O1357: -1262 | P1357: Dine In | Q1357: Kedai | R1357: Temu Roti | S1357: Owner | W1357: Closed
A1358: 45538.866 | B1358: 2606403 | C1358: Refund | D1358: Hidangan Utama | E1358: 10012 | F1358: Mie joglo | I1358: -1 | J1358: -29524 | K1358: 0 | L1358: -29524 | M1358: 0 | N1358: -29524 | O1358: -1476 | P1358: Dine In | Q1358: Kedai | R1358: Temu Roti | S1358: Owner | V1358: Manis pedas | W1358: Closed
A1359: 45538.866 | B1359: 2606403 | C1359: Refund | D1359: Roti | E1359: 10007 | F1359: Roti cranberry 2 pcs | I1359: -1 | J1359: -33810 | K1359: 0 | L1359: -33810 | M1359: 0 | N1359: -33810 | O1359: -1691 | P1359: Dine In | Q1359: Kedai | R1359: Temu Roti | S1359: Owner | W1359: Closed
A1360: 45538.865 | B1360: 2606038 | C1360: Sale | D1360: Roti | E1360: 10000 | F1360: Roti Bawang Saus Keju | I1360: 1 | J1360: 29524 | K1360: 0 | L1360: 29524 | M1360: 0 | N1360: 29524 | O1360: 1476 | P1360: Dine In | Q1360: Kedai | R1360: Temu Roti | S1360: Owner | W1360: Closed
A1361: 45538.865 | B1361: 2606038 | C1361: Sale | D1361: Minuman | E1361: 10128 | F1361: Es Kopi Susu | I1361: 1 | J1361: 23333 | K1361: 0 | L1361: 23333 | M1361: 0 | N1361: 23333 | O1361: 1167 | P1361: Dine In | Q1361: Kedai | R1361: Temu Roti | S1361: Owner | W1361: Closed
A1362: 45538.865 | B1362: 2606038 | C1362: Sale | D1362: Kudapan | E1362: 10009 | F1362: Jamur Enoki Krispi | I1362: 1 | J1362: 26667 | K1362: 0 | L1362: 26667 | M1362: 0 | N1362: 26667 | O1362: 1333 | P1362: Dine In | Q1362: Kedai | R1362: Temu Roti | S1362: Owner | W1362: Closed
A1363: 45538.865 | B1363: 2605673 | C1363: Refund | D1363: Minuman | E1363: 10128 | F1363: Es Kopi Susu | I1363: -1 | J1363: -23333 | K1363: 0 | L1363: -23333 | M1363: 0 | N1363: -23333 | O1363: -1167 | P1363: Dine In | Q1363: Kedai | R1363: Temu Roti | S1363: Owner | W1363: Closed
A1364: 45538.865 | B1364: 2605673 | C1364: Refund | D1364: Kudapan | E1364: 10009 | F1364: Jamur Enoki Krispi | I1364: -1 | J1364: -26667 | K1364: 0 | L1364: -26667 | M1364: 0 | N1364: -26667 | O1364: -1333 | P1364: Dine In | Q1364: Kedai | R1364: Temu Roti | S1364: Owner | W1364: Closed
A1365: 45538.865 | B1365: 2605673 | C1365: Refund | D1365: Roti | E1365: 10000 | F1365: Roti Bawang Saus Keju | I1365: -1 | J1365: -29524 | K1365: 0 | L1365: -29524 | M1365: 0 | N1365: -29524 | O1365: -1476 | P1365: Dine In | Q1365: Kedai | R1365: Temu Roti | S1365: Owner | W1365: Closed
A1366: 45538.84 | B1366: 2605308 | C1366: Sale | D1366: Roti | E1366: 10007 | F1366: Roti cranberry 2 pcs | I1366: 1 | J1366: 33810 | K1366: 0 | L1366: 33810 | M1366: 0 | N1366: 33810 | O1366: 1691 | P1366: Take Away | Q1366: Kedai | R1366: Temu Roti | S1366: Owner | W1366: Closed
A1367: 45538.84 | B1367: 2605308 | C1367: Sale | D1367: Roti | E1367: 10002 | F1367: Roti Cranberry | I1367: 1 | J1367: 18571 | K1367: 0 | L1367: 18571 | M1367: 0 | N1367: 18571 | O1367: 928 | P1367: Take Away | Q1367: Kedai | R1367: Temu Roti | S1367: Owner | W1367: Closed
A1368: 45538.84 | B1368: 2605308 | C1368: Sale | D1368: Minuman | E1368: 10107 | F1368: Korean Mango Fresh Milk | I1368: 1 | J1368: 26667 | K1368: 0 | L1368: 26667 | M1368: 0 | N1368: 26667 | O1368: 1333 | P1368: Take Away | Q1368: Kedai | R1368: Temu Roti | S1368: Owner | W1368: Closed
A1369: 45538.837 | B1369: 2604942 | C1369: Sale | D1369: Roti | E1369: 10007 | F1369: Roti cranberry 2 pcs | I1369: 1 | J1369: 33810 | K1369: 0 | L1369: 33810 | M1369: 0 | N1369: 33810 | O1369: 1691 | P1369: Dine In | Q1369: Kedai | R1369: Temu Roti | S1369: Owner | W1369: Closed
A1370: 45538.832 | B1370: 2604577 | C1370: Sale | D1370: Minuman | E1370: 10128 | F1370: Es Kopi Susu | I1370: 1 | J1370: 23333 | K1370: 0 | L1370: 23333 | M1370: 0 | N1370: 23333 | O1370: 1167 | P1370: Dine In | Q1370: Kedai | R1370: Temu Roti | S1370: Owner | W1370: Closed
... A1372: 45538.832 | B1372: 2604577 | C1372: Sale | D1372: Roti | E1372: 10000 | F1372: Roti Bawang Saus Keju | I1372: 1 | J1372: 29524 | K1372: 0 | L1372: 29524 | M1372: 0 | N1372: 29524 | O1372: 1476 | P1372: Dine In | Q1372: Kedai | R1372: Temu Roti | S1372: Owner | W1372: Closed
A1373: 45538.83 | B1373: 2604212 | C1373: Sale | D1373: Roti | E1373: 10033 | F1373: Roti panggang sarikaya | I1373: 1 | J1373: 21905 | K1373: 0 | L1373: 21905 | M1373: 0 | N1373: 21905 | O1373: 1095 | P1373: Dine In | Q1373: Kedai | R1373: Temu Roti | S1373: Owner | V1373: Sarikaya sedikit | W1373: Closed
A1374: 45538.83 | B1374: 2604212 | C1374: Sale | D1374: Kudapan | E1374: 10004 | F1374: Tahu walik | I1374: 1 | J1374: 25238 | K1374: 0 | L1374: 25238 | M1374: 0 | N1374: 25238 | O1374: 1262 | P1374: Dine In | Q1374: Kedai | R1374: Temu Roti | S1374: Owner | W1374: Closed
A1375: 45538.83 | B1375: 2604212 | C1375: Sale | D1375: Hidangan Utama | E1375: 10012 | F1375: Mie joglo | I1375: 1 | J1375: 29524 | K1375: 0 | L1375: 29524 | M1375: 0 | N1375: 29524 | O1375: 1476 | P1375: Dine In | Q1375: Kedai | R1375: Temu Roti | S1375: Owner | V1375: Manis pedas | W1375: Closed
A1376: 45538.83 | B1376: 2604212 | C1376: Sale | D1376: Roti | E1376: 10007 | F1376: Roti cranberry 2 pcs | I1376: 1 | J1376: 33810 | K1376: 0 | L1376: 33810 | M1376: 0 | N1376: 33810 | O1376: 1691 | P1376: Dine In | Q1376: Kedai | R1376: Temu Roti | S1376: Owner | W1376: Closed
A1377: 45538.819 | B1377: 2603847 | C1377: Sale | D1377: Kudapan | E1377: 10004 | F1377: Tahu walik | I1377: 1 | J1377: 25238 | K1377: 0 | L1377: 25238 | M1377: 0 | N1377: 25238 | O1377: 1262 | P1377: Dine In | Q1377: Kedai | R1377: Temu Roti | S1377: Owner | W1377: Closed
A1378: 45538.819 | B1378: 2603847 | C1378: Sale | D1378: Minuman | E1378: 10112 | F1378: Air mineral | I1378: 1 | J1378: 6667 | K1378: 0 | L1378: 6667 | M1378: 0 | N1378: 6667 | O1378: 333 | P1378: Dine In | Q1378: Kedai | R1378: Temu Roti | S1378: Owner | W1378: Closed
A1379: 45538.819 | B1379: 2603847 | C1379: Sale | D1379: Kudapan | E1379: 10015 | F1379: Tahu Lada Garam | I1379: 1 | J1379: 25238 | K1379: 0 | L1379: 25238 | M1379: 0 | N1379: 25238 | O1379: 1262 | P1379: Dine In | Q1379: Kedai | R1379: Temu Roti | S1379: Owner | W1379: Closed
A1380: 45538.819 | B1380: 2603847 | C1380: Sale | D1380: Kudapan | E1380: 10051 | F1380: Tahu baso | I1380: 1 | J1380: 25238 | K1380: 0 | L1380: 25238 | M1380: 0 | N1380: 25238 | O1380: 1262 | P1380: Dine In | Q1380: Kedai | R1380: Temu Roti | S1380: Owner | W1380: Closed
A1381: 45538.818 | B1381: 2603481 | C1381: Sale | D1381: Roti | E1381: 10002 | F1381: Roti Cranberry | I1381: 1 | J1381: 18571 | K1381: 0 | L1381: 18571 | M1381: 0 | N1381: 18571 | O1381: 929 | P1381: Dine In | Q1381: Kedai | R1381: Temu Roti | S1381: Owner | W1381: Closed
A1382: 45538.818 | B1382: 2603481 | C1382: Sale | D1382: Roti | E1382: 10005 | F1382: Roti Gandum Cokelat | I1382: 1 | J1382: 19524 | K1382: 0 | L1382: 19524 | M1382: 0 | N1382: 19524 | O1382: 976 | P1382: Dine In | Q1382: Kedai | R1382: Temu Roti | S1382: Owner | W1382: Closed
A1383: 45538.806 | B1383: 2603116 | C1383: Sale | D1383: Roti | E1383: 10034 | F1383: Roti panggang coklat | I1383: 1 | J1383: 21905 | K1383: 0 | L1383: 21905 | M1383: 0 | N1383: 21905 | O1383: 1095 | P1383: Dine In | Q1383: Kedai | R1383: Temu Roti | S1383: Owner | W1383: Closed
A1384: 45538.806 | B1384: 2603116 | C1384: Sale | D1384: Minuman | E1384: 10122 | F1384: Rempah Madu Panas | I1384: 1 | J1384: 21905 | K1384: 0 | L1384: 21905 | M1384: 0 | N1384: 21905 | O1384: 1096 | P1384: Dine In | Q1384: Kedai | R1384: Temu Roti | S1384: Owner | W1384: Closed
A1385: 45538.806 | B1385: 2603116 | C1385: Sale | D1385: Kudapan | E1385: 10014 | F1385: Tempe Mendoan | I1385: 1 | J1385: 25238 | K1385: 0 | L1385: 25238 | M1385: 0 | N1385: 25238 | O1385: 1261 | P1385: Dine In | Q1385: Kedai | R1385: Temu Roti | S1385: Owner | W1385: Closed
A1386: 45538.806 | B1386: 2603116 | C1386: Sale | D1386: Minuman | E1386: 10112 | F1386: Air mineral | I1386: 1 | J1386: 6667 | K1386: 0 | L1386: 6667 | M1386: 0 | N1386: 6667 | O1386: 334 | P1386: Dine In | Q1386: Kedai | R1386: Temu Roti | S1386: Owner | W1386: Closed
A1387: 45538.804 | B1387: 2602751 | C1387: Sale | D1387: Minuman | E1387: 10128 | F1387: Es Kopi Susu | I1387: 1 | J1387: 23333 | K1387: 0 | L1387: 23333 | M1387: 0 | N1387: 23333 | O1387: 1167 | P1387: Dine In | Q1387: Kedai | R1387: Temu Roti | S1387: Owner | W1387: Closed
... A1530: 45536.402 | B1530: 2583028 | C1530: Sale | D1530: Roti | E1530: 10033 | F1530: Roti panggang sarikaya | I1530: 1 | J1530: 21905 | K1530: 0 | L1530: 21905 | M1530: 0 | N1530: 21905 | O1530: 1095 | P1530: Dine In | Q1530: Kedai | R1530: Temu Roti | S1530: Owner | W1530: Closed

Sheet Processing 1
A1: {=Data!A:A} -> Date | B1: Split | D1: Hour | E1: Day | F1: Month | G1: Year | H1: Text join | I1: {=Data!F:F} -> Item | J1: Item replace | K1: Quantity | L1: days | M1: Date | N1: Days Number | O1: Week
A2: 45564.851 | B2: =IFERROR(__xludf.DUMMYFUNCTION("SPLIT(A2,"" "")"),45564.0) -> 45564 | C2: =IFERROR(__xludf.DUMMYFUNCTION("""COMPUTED_VALUE"""),0.8506944444444444) -> 0.85069444 | D2: =HOUR(C2) -> 20 | E2: =IFERROR(__xludf.DUMMYFUNCTION("SPLIT(B2,""/"")"),29.0) -> 29 | F2: =IFERROR(__xludf.DUMMYFUNCTION("""COMPUTED_VALUE"""),9.0) -> 9 | G2: =IFERROR(__xludf.DUMMYFUNCTION("""COMPUTED_VALUE"""),2024.0) -> 2024 | H2: =TEXTJOIN("/",1,G2,F2,E2) -> 2024/9/29 | I2: Roti Bawang Saus Keju | J2: =IFERROR(ifs(I2="Roti cranberry 2 pcs","Roti Cranberry",I2="Roti Gandum Cokelat 2 pcs","Roti Gandum Cokelat"),I2) -> Roti Bawang Saus Keju | K2: =if(RIGHT(I2,5)="2 pcs",2,Data!I2) -> -1 | L2: =TEXT(B2,"dddd") -> Sunday | M2: =TEXT(H2,"d") -> 29 | N2: =VLOOKUP(L2,'Data Info'!$A$1:$B$8,2,0) -> 7 | O2: =VLOOKUP(L2,'Data Info'!$A$1:$C$8,3,0) -> Weekend
A3: 45564.85 | B3: =IFERROR(__xludf.DUMMYFUNCTION("SPLIT(A3,"" "")"),45564.0) -> 45564 | C3: =IFERROR(__xludf.DUMMYFUNCTION("""COMPUTED_VALUE"""),0.85) -> 0.85 | D3: =HOUR(C3) -> 20 | E3: =IFERROR(__xludf.DUMMYFUNCTION("SPLIT(B3,""/"")"),29.0) -> 29 | F3: =IFERROR(__xludf.DUMMYFUNCTION("""COMPUTED_VALUE"""),9.0) -> 9 | G3: =IFERROR(__xludf.DUMMYFUNCTION("""COMPUTED_VALUE"""),2024.0) -> 2024 | H3: =TEXTJOIN("/",1,G3,F3,E3) -> 2024/9/29 | I3: Air mineral | J3: =IFERROR(ifs(I3="Roti cranberry 2 pcs","Roti Cranberry",I3="Roti Gandum Cokelat 2 pcs","Roti Gandum Cokelat"),I3) -> Air mineral | K3: =if(RIGHT(I3,5)="2 pcs",2,Data!I3) -> -2 | L3: =TEXT(B3,"dddd") -> Sunday | M3: =TEXT(H3,"d") -> 29 | N3: =VLOOKUP(L3,'Data Info'!$A$1:$B$8,2,0) -> 7 | O3: =VLOOKUP(L3,'Data Info'!$A$1:$C$8,3,0) -> Weekend
A4: 45564.844 | B4: =IFERROR(__xludf.DUMMYFUNCTION("SPLIT(A4,"" "")"),45564.0) -> 45564 | C4: =IFERROR(__xludf.DUMMYFUNCTION("""COMPUTED_VALUE"""),0.8444444444444444) -> 0.84444444 | D4: =HOUR(C4) -> 20 | E4: =IFERROR(__xludf.DUMMYFUNCTION("SPLIT(B4,""/"")"),29.0) -> 29 | F4: =IFERROR(__xludf.DUMMYFUNCTION("""COMPUTED_VALUE"""),9.0) -> 9 | G4: =IFERROR(__xludf.DUMMYFUNCTION("""COMPUTED_VALUE"""),2024.0) -> 2024 | H4: =TEXTJOIN("/",1,G4,F4,E4) -> 2024/9/29 | I4: Roti Cranberry | J4: =IFERROR(ifs(I4="Roti cranberry 2 pcs","Roti Cranberry",I4="Roti Gandum Cokelat 2 pcs","Roti Gandum Cokelat"),I4) -> Roti Cranberry | K4: =if(RIGHT(I4,5)="2 pcs",2,Data!I4) -> 1 | L4: =TEXT(B4,"dddd") -> Sunday | M4: =TEXT(H4,"d") -> 29 | N4: =VLOOKUP(L4,'Data Info'!$A$1:$B$8,2,0) -> 7 | O4: =VLOOKUP(L4,'Data Info'!$A$1:$C$8,3,0) -> Weekend
A5: 45564.778 | B5: =IFERROR(__xludf.DUMMYFUNCTION("SPLIT(A5,"" "")"),45564.0) -> 45564 | C5: =IFERROR(__xludf.DUMMYFUNCTION("""COMPUTED_VALUE"""),0.7777777777777778) -> 0.77777778 | D5: =HOUR(C5) -> 18 | E5: =IFERROR(__xludf.DUMMYFUNCTION("SPLIT(B5,""/"")"),29.0) -> 29 | F5: =IFERROR(__xludf.DUMMYFUNCTION("""COMPUTED_VALUE"""),9.0) -> 9 | G5: =IFERROR(__xludf.DUMMYFUNCTION("""COMPUTED_VALUE"""),2024.0) -> 2024 | H5: =TEXTJOIN("/",1,G5,F5,E5) -> 2024/9/29 | I5: Rempah Madu Panas | J5: =IFERROR(ifs(I5="Roti cranberry 2 pcs","Roti Cranberry",I5="Roti Gandum Cokelat 2 pcs","Roti Gandum Cokelat"),I5) -> Rempah Madu Panas | K5: =if(RIGHT(I5,5)="2 pcs",2,Data!I5) -> 2 | L5: =TEXT(B5,"dddd") -> Sunday | M5: =TEXT(H5,"d") -> 29 | N5: =VLOOKUP(L5,'Data Info'!$A$1:$B$8,2,0) -> 7 | O5: =VLOOKUP(L5,'Data Info'!$A$1:$C$8,3,0) -> Weekend
A6: 45564.778 | B6: =IFERROR(__xludf.DUMMYFUNCTION("SPLIT(A6,"" "")"),45564.0) -> 45564 | C6: =IFERROR(__xludf.DUMMYFUNCTION("""COMPUTED_VALUE"""),0.7777777777777778) -> 0.77777778 | D6: =HOUR(C6) -> 18 | E6: =IFERROR(__xludf.DUMMYFUNCTION("SPLIT(B6,""/"")"),29.0) -> 29 | F6: =IFERROR(__xludf.DUMMYFUNCTION("""COMPUTED_VALUE"""),9.0) -> 9 | G6: =IFERROR(__xludf.DUMMYFUNCTION("""COMPUTED_VALUE"""),2024.0) -> 2024 | H6: =TEXTJOIN("/",1,G6,F6,E6) -> 2024/9/29 | I6: Tahu baso | J6: =IFERROR(ifs(I6="Roti cranberry 2 pcs","Roti Cranberry",I6="Roti Gandum Cokelat 2 pcs","Roti Gandum Cokelat"),I6) -> Tahu baso | K6: =if(RIGHT(I6,5)="2 pcs",2,Data!I6) -> 1 | L6: =TEXT(B6,"dddd") -> Sunday | M6: =TEXT(H6,"d") -> 29 | N6: =VLOOKUP(L6,'Data Info'!$A$1:$B$8,2,0) -> 7 | O6: =VLOOKUP(L6,'Data Info'!$A$1:$C$8,3,0) -> Weekend
A7: 45564.778 | B7: =IFERROR(__xludf.DUMMYFUNCTION("SPLIT(A7,"" "")"),45564.0) -> 45564 | C7: =IFERROR(__xludf.DUMMYFUNCTION("""COMPUTED_VALUE"""),0.7777777777777778) -> 0.77777778 | D7: =HOUR(C7) -> 18 | E7: =IFERROR(__xludf.DUMMYFUNCTION("SPLIT(B7,""/"")"),29.0) -> 29 | F7: =IFERROR(__xludf.DUMMYFUNCTION("""COMPUTED_VALUE"""),9.0) -> 9 | G7: =IFERROR(__xludf.DUMMYFUNCTION("""COMPUTED_VALUE"""),2024.0) -> 2024 | H7: =TEXTJOIN("/",1,G7,F7,E7) -> 2024/9/29 | I7: Rempah Madu Panas | J7: =IFERROR(ifs(I7="Roti cranberry 2 pcs","Roti Cranberry",I7="Roti Gandum Cokelat 2 pcs","Roti Gandum Cokelat"),I7) -> Rempah Madu Panas | K7: =if(RIGHT(I7,5)="2 pcs",2,Data!I7) -> -1 | L7: =TEXT(B7,"dddd") -> Sunday | M7: =TEXT(H7,"d") -> 29 | N7: =VLOOKUP(L7,'Data Info'!$A$1:$B$8,2,0) -> 7 | O7: =VLOOKUP(L7,'Data Info'!$A$1:$C$8,3,0) -> Weekend
A8: 45564.778 | B8: =IFERROR(__xludf.DUMMYFUNCTION("SPLIT(A8,"" "")"),45564.0) -> 45564 | C8: =IFERROR(__xludf.DUMMYFUNCTION("""COMPUTED_VALUE"""),0.7777777777777778) -> 0.77777778 | D8: =HOUR(C8) -> 18 | E8: =IFERROR(__xludf.DUMMYFUNCTION("SPLIT(B8,""/"")"),29.0) -> 29 | F8: =IFERROR(__xludf.DUMMYFUNCTION("""COMPUTED_VALUE"""),9.0) -> 9 | G8: =IFERROR(__xludf.DUMMYFUNCTION("""COMPUTED_VALUE"""),2024.0) -> 2024 | H8: =TEXTJOIN("/",1,G8,F8,E8) -> 2024/9/29 | I8: Tahu baso | J8: =IFERROR(ifs(I8="Roti cranberry 2 pcs","Roti Cranberry",I8="Roti Gandum Cokelat 2 pcs","Roti Gandum Cokelat"),I8) -> Tahu baso | K8: =if(RIGHT(I8,5)="2 pcs",2,Data!I8) -> -2 | L8: =TEXT(B8,"dddd") -> Sunday | M8: =TEXT(H8,"d") -> 29 | N8: =VLOOKUP(L8,'Data Info'!$A$1:$B$8,2,0) -> 7 | O8: =VLOOKUP(L8,'Data Info'!$A$1:$C$8,3,0) -> Weekend
A9: 45564.778 | B9: =IFERROR(__xludf.DUMMYFUNCTION("SPLIT(A9,"" "")"),45564.0) -> 45564 | C9: =IFERROR(__xludf.DUMMYFUNCTION("""COMPUTED_VALUE"""),0.7777777777777778) -> 0.77777778 | D9: =HOUR(C9) -> 18 | E9: =IFERROR(__xludf.DUMMYFUNCTION("SPLIT(B9,""/"")"),29.0) -> 29 | F9: =IFERROR(__xludf.DUMMYFUNCTION("""COMPUTED_VALUE"""),9.0) -> 9 | G9: =IFERROR(__xludf.DUMMYFUNCTION("""COMPUTED_VALUE"""),2024.0) -> 2024 | H9: =TEXTJOIN("/",1,G9,F9,E9) -> 2024/9/29 | I9: Rempah Madu Panas | J9: =IFERROR(ifs(I9="Roti cranberry 2 pcs","Roti Cranberry",I9="Roti Gandum Cokelat 2 pcs","Roti Gandum Cokelat"),I9) -> Rempah Madu Panas | K9: =if(RIGHT(I9,5)="2 pcs",2,Data!I9) -> -1 | L9: =TEXT(B9,"dddd") -> Sunday | M9: =TEXT(H9,"d") -> 29 | N9: =VLOOKUP(L9,'Data Info'!$A$1:$B$8,2,0) -> 7 | O9: =VLOOKUP(L9,'Data Info'!$A$1:$C$8,3,0) -> Weekend
A10: 45564.775 | B10: =IFERROR(__xludf.DUMMYFUNCTION("SPLIT(A10,"" "")"),45564.0) -> 45564 | C10: =IFERROR(__xludf.DUMMYFUNCTION("""COMPUTED_VALUE"""),0.775) -> 0.775 | D10: =HOUR(C10) -> 18 | E10: =IFERROR(__xludf.DUMMYFUNCTION("SPLIT(B10,""/"")"),29.0) -> 29 | F10: =IFERROR(__xludf.DUMMYFUNCTION("""COMPUTED_VALUE"""),9.0) -> 9 | G10: =IFERROR(__xludf.DUMMYFUNCTION("""COMPUTED_VALUE"""),2024.0) -> 2024 | H10: =TEXTJOIN("/",1,G10,F10,E10) -> 2024/9/29 | I10: Rempah Madu Panas | J10: =IFERROR(ifs(I10="Roti cranberry 2 pcs","Roti Cranberry",I10="Roti Gandum Cokelat 2 pcs","Roti Gandum Cokelat"),I10) -> Rempah Madu Panas | K10: =if(RIGHT(I10,5)="2 pcs",2,Data!I10) -> 1 | L10: =TEXT(B10,"dddd") -> Sunday | M10: =TEXT(H10,"d") -> 29 | N10: =VLOOKUP(L10,'Data Info'!$A$1:$B$8,2,0) -> 7 | O10: =VLOOKUP(L10,'Data Info'!$A$1:$C$8,3,0) -> Weekend
A11: 45564.775 | B11: =IFERROR(__xludf.DUMMYFUNCTION("SPLIT(A11,"" "")"),45564.0) -> 45564 | C11: =IFERROR(__xludf.DUMMYFUNCTION("""COMPUTED_VALUE"""),0.775) -> 0.775 | D11: =HOUR(C11) -> 18 | E11: =IFERROR(__xludf.DUMMYFUNCTION("SPLIT(B11,""/"")"),29.0) -> 29 | F11: =IFERROR(__xludf.DUMMYFUNCTION("""COMPUTED_VALUE"""),9.0) -> 9 | G11: =IFERROR(__xludf.DUMMYFUNCTION("""COMPUTED_VALUE"""),2024.0) -> 2024 | H11: =TEXTJOIN("/",1,G11,F11,E11) -> 2024/9/29 | I11: Tahu baso | J11: =IFERROR(ifs(I11="Roti cranberry 2 pcs","Roti Cranberry",I11="Roti Gandum Cokelat 2 pcs","Roti Gandum Cokelat"),I11) -> Tahu baso | K11: =if(RIGHT(I11,5)="2 pcs",2,Data!I11) -> 2 | L11: =TEXT(B11,"dddd") -> Sunday | M11: =TEXT(H11,"d") -> 29 | N11: =VLOOKUP(L11,'Data Info'!$A$1:$B$8,2,0) -> 7 | O11: =VLOOKUP(L11,'Data Info'!$A$1:$C$8,3,0) -> Weekend
A12: 45564.775 | B12: =IFERROR(__xludf.DUMMYFUNCTION("SPLIT(A12,"" "")"),45564.0) -> 45564 | C12: =IFERROR(__xludf.DUMMYFUNCTION("""COMPUTED_VALUE"""),0.775) -> 0.775 | D12: =HOUR(C12) -> 18 | E12: =IFERROR(__xludf.DUMMYFUNCTION("SPLIT(B12,""/"")"),29.0) -> 29 | F12: =IFERROR(__xludf.DUMMYFUNCTION("""COMPUTED_VALUE"""),9.0) -> 9 | G12: =IFERROR(__xludf.DUMMYFUNCTION("""COMPUTED_VALUE"""),2024.0) -> 2024 | H12: =TEXTJOIN("/",1,G12,F12,E12) -> 2024/9/29 | I12: Rempah Madu Panas | J12: =IFERROR(ifs(I12="Roti cranberry 2 pcs","Roti Cranberry",I12="Roti Gandum Cokelat 2 pcs","Roti Gandum Cokelat"),I12) -> Rempah Madu Panas | K12: =if(RIGHT(I12,5)="2 pcs",2,Data!I12) -> 1 | L12: =TEXT(B12,"dddd") -> Sunday | M12: =TEXT(H12,"d") -> 29 | N12: =VLOOKUP(L12,'Data Info'!$A$1:$B$8,2,0) -> 7 | O12: =VLOOKUP(L12,'Data Info'!$A$1:$C$8,3,0) -> Weekend
A13: 45564.772 | B13: =IFERROR(__xludf.DUMMYFUNCTION("SPLIT(A13,"" "")"),45564.0) -> 45564 | C13: =IFERROR(__xludf.DUMMYFUNCTION("""COMPUTED_VALUE"""),0.7722222222222223) -> 0.77222222 | D13: =HOUR(C13) -> 18 | E13: =IFERROR(__xludf.DUMMYFUNCTION("SPLIT(B13,""/"")"),29.0) -> 29 | F13: =IFERROR(__xludf.DUMMYFUNCTION("""COMPUTED_VALUE"""),9.0) -> 9 | G13: =IFERROR(__xludf.DUMMYFUNCTION("""COMPUTED_VALUE"""),2024.0) -> 2024 | H13: =TEXTJOIN("/",1,G13,F13,E13) -> 2024/9/29 | I13: Chicken Claypot Rice | J13: =IFERROR(ifs(I13="Roti cranberry 2 pcs","Roti Cranberry",I13="Roti Gandum Cokelat 2 pcs","Roti Gandum Cokelat"),I13) -> Chicken Claypot Rice | K13: =if(RIGHT(I13,5)="2 pcs",2,Data!I13) -> 1 | L13: =TEXT(B13,"dddd") -> Sunday | M13: =TEXT(H13,"d") -> 29 | N13: =VLOOKUP(L13,'Data Info'!$A$1:$B$8,2,0) -> 7 | O13: =VLOOKUP(L13,'Data Info'!$A$1:$C$8,3,0) -> Weekend
A14: 45564.772 | B14: =IFERROR(__xludf.DUMMYFUNCTION("SPLIT(A14,"" "")"),45564.0) -> 45564 | C14: =IFERROR(__xludf.DUMMYFUNCTION("""COMPUTED_VALUE"""),0.7722222222222223) -> 0.77222222 | D14: =HOUR(C14) -> 18 | E14: =IFERROR(__xludf.DUMMYFUNCTION("SPLIT(B14,""/"")"),29.0) -> 29 | F14: =IFERROR(__xludf.DUMMYFUNCTION("""COMPUTED_VALUE"""),9.0) -> 9 | G14: =IFERROR(__xludf.DUMMYFUNCTION("""COMPUTED_VALUE"""),2024.0) -> 2024 | H14: =TEXTJOIN("/",1,G14,F14,E14) -> 2024/9/29 | I14: Teh Tawar Dingin | J14: =IFERROR(ifs(I14="Roti cranberry 2 pcs","Roti Cranberry",I14="Roti Gandum Cokelat 2 pcs","Roti Gandum Cokelat"),I14) -> Teh Tawar Dingin | K14: =if(RIGHT(I14,5)="2 pcs",2,Data!I14) -> 1 | L14: =TEXT(B14,"dddd") -> Sunday | M14: =TEXT(H14,"d") -> 29 | N14: =VLOOKUP(L14,'Data Info'!$A$1:$B$8,2,0) -> 7 | O14: =VLOOKUP(L14,'Data Info'!$A$1:$C$8,3,0) -> Weekend
A15: 45564.761 | B15: =IFERROR(__xludf.DUMMYFUNCTION("SPLIT(A15,"" "")"),45564.0) -> 45564 | C15: =IFERROR(__xludf.DUMMYFUNCTION("""COMPUTED_VALUE"""),0.7611111111111111) -> 0.76111111 | D15: =HOUR(C15) -> 18 | E15: =IFERROR(__xludf.DUMMYFUNCTION("SPLIT(B15,""/"")"),29.0) -> 29 | F15: =IFERROR(__xludf.DUMMYFUNCTION("""COMPUTED_VALUE"""),9.0) -> 9 | G15: =IFERROR(__xludf.DUMMYFUNCTION("""COMPUTED_VALUE"""),2024.0) -> 2024 | H15: =TEXTJOIN("/",1,G15,F15,E15) -> 2024/9/29 | I15: Es Kopi Lemon | J15: =IFERROR(ifs(I15="Roti cranberry 2 pcs","Roti Cranberry",I15="Roti Gandum Cokelat 2 pcs","Roti Gandum Cokelat"),I15) -> Es Kopi Lemon | K15: =if(RIGHT(I15,5)="2 pcs",2,Data!I15) -> 1 | L15: =TEXT(B15,"dddd") -> Sunday | M15: =TEXT(H15,"d") -> 29 | N15: =VLOOKUP(L15,'Data Info'!$A$1:$B$8,2,0) -> 7 | O15: =VLOOKUP(L15,'Data Info'!$A$1:$C$8,3,0) -> Weekend
A16: 45564.761 | B16: =IFERROR(__xludf.DUMMYFUNCTION("SPLIT(A16,"" "")"),45564.0) -> 45564 | C16: =IFERROR(__xludf.DUMMYFUNCTION("""COMPUTED_VALUE"""),0.7611111111111111) -> 0.76111111 | D16: =HOUR(C16) -> 18 | E16: =IFERROR(__xludf.DUMMYFUNCTION("SPLIT(B16,""/"")"),29.0) -> 29 | F16: =IFERROR(__xludf.DUMMYFUNCTION("""COMPUTED_VALUE"""),9.0) -> 9 | G16: =IFERROR(__xludf.DUMMYFUNCTION("""COMPUTED_VALUE"""),2024.0) -> 2024 | H16: =TEXTJOIN("/",1,G16,F16,E16) -> 2024/9/29 | I16: Korean Mango Fresh Milk | J16: =IFERROR(ifs(I16="Roti cranberry 2 pcs","Roti Cranberry",I16="Roti Gandum Cokelat 2 pcs","Roti Gandum Cokelat"),I16) -> Korean Mango Fresh Milk | K16: =if(RIGHT(I16,5)="2 pcs",2,Data!I16) -> 1 | L16: =TEXT(B16,"dddd") -> Sunday | M16: =TEXT(H16,"d") -> 29 | N16: =VLOOKUP(L16,'Data Info'!$A$1:$B$8,2,0) -> 7 | O16: =VLOOKUP(L16,'Data Info'!$A$1:$C$8,3,0) -> Weekend
A17: 45564.758 | B17: =IFERROR(__xludf.DUMMYFUNCTION("SPLIT(A17,"" "")"),45564.0) -> 45564 | C17: =IFERROR(__xludf.DUMMYFUNCTION("""COMPUTED_VALUE"""),0.7583333333333333) -> 0.75833333 | D17: =HOUR(C17) -> 18 | E17: =IFERROR(__xludf.DUMMYFUNCTION("SPLIT(B17,""/"")"),29.0) -> 29 | F17: =IFERROR(__xludf.DUMMYFUNCTION("""COMPUTED_VALUE"""),9.0) -> 9 | G17: =IFERROR(__xludf.DUMMYFUNCTION("""COMPUTED_VALUE"""),2024.0) -> 2024 | H17: =TEXTJOIN("/",1,G17,F17,E17) -> 2024/9/29 | I17: Susu murni moca | J17: =IFERROR(ifs(I17="Roti cranberry 2 pcs","Roti Cranberry",I17="Roti Gandum Cokelat 2 pcs","Roti Gandum Cokelat"),I17) -> Susu murni moca | K17: =if(RIGHT(I17,5)="2 pcs",2,Data!I17) -> 1 | L17: =TEXT(B17,"dddd") -> Sunday | M17: =TEXT(H17,"d") -> 29 | N17: =VLOOKUP(L17,'Data Info'!$A$1:$B$8,2,0) -> 7 | O17: =VLOOKUP(L17,'Data Info'!$A$1:$C$8,3,0) -> Weekend
A18: 45564.749 | B18: =IFERROR(__xludf.DUMMYFUNCTION("SPLIT(A18,"" "")"),45564.0) -> 45564 | C18: =IFERROR(__xludf.DUMMYFUNCTION("""COMPUTED_VALUE"""),0.7493055555555556) -> 0.74930556 | D18: =HOUR(C18) -> 17 | E18: =IFERROR(__xludf.DUMMYFUNCTION("SPLIT(B18,""/"")"),29.0) -> 29 | F18: =IFERROR(__xludf.DUMMYFUNCTION("""COMPUTED_VALUE"""),9.0) -> 9 | G18: =IFERROR(__xludf.DUMMYFUNCTION("""COMPUTED_VALUE"""),2024.0) -> 2024 | H18: =TEXTJOIN("/",1,G18,F18,E18) -> 2024/9/29 | I18: Jamur Enoki Krispi | J18: =IFERROR(ifs(I18="Roti cranberry 2 pcs","Roti Cranberry",I18="Roti Gandum Cokelat 2 pcs","Roti Gandum Cokelat"),I18) -> Jamur Enoki Krispi | K18: =if(RIGHT(I18,5)="2 pcs",2,Data!I18) -> 1 | L18: =TEXT(B18,"dddd") -> Sunday | M18: =TEXT(H18,"d") -> 29 | N18: =VLOOKUP(L18,'Data Info'!$A$1:$B$8,2,0) -> 7 | O18: =VLOOKUP(L18,'Data Info'!$A$1:$C$8,3,0) -> Weekend
A19: 45564.745 | B19: =IFERROR(__xludf.DUMMYFUNCTION("SPLIT(A19,"" "")"),45564.0) -> 45564 | C19: =IFERROR(__xludf.DUMMYFUNCTION("""COMPUTED_VALUE"""),0.7451388888888889) -> 0.74513889 | D19: =HOUR(C19) -> 17 | E19: =IFERROR(__xludf.DUMMYFUNCTION("SPLIT(B19,""/"")"),29.0) -> 29 | F19: =IFERROR(__xludf.DUMMYFUNCTION("""COMPUTED_VALUE"""),9.0) -> 9 | G19: =IFERROR(__xludf.DUMMYFUNCTION("""COMPUTED_VALUE"""),2024.0) -> 2024 | H19: =TEXTJOIN("/",1,G19,F19,E19) -> 2024/9/29 | I19: Chicken Claypot Rice | J19: =IFERROR(ifs(I19="Roti cranberry 2 pcs","Roti Cranberry",I19="Roti Gandum Cokelat 2 pcs","Roti Gandum Cokelat"),I19) -> Chicken Claypot Rice | K19: =if(RIGHT(I19,5)="2 pcs",2,Data!I19) -> 1 | L19: =TEXT(B19,"dddd") -> Sunday | M19: =TEXT(H19,"d") -> 29 | N19: =VLOOKUP(L19,'Data Info'!$A$1:$B$8,2,0) -> 7 | O19: =VLOOKUP(L19,'Data Info'!$A$1:$C$8,3,0) -> Weekend
A20: 45564.739 | B20: =IFERROR(__xludf.DUMMYFUNCTION("SPLIT(A20,"" "")"),45564.0) -> 45564 | C20: =IFERROR(__xludf.DUMMYFUNCTION("""COMPUTED_VALUE"""),0.7388888888888889) -> 0.73888889 | D20: =HOUR(C20) -> 17 | E20: =IFERROR(__xludf.DUMMYFUNCTION("SPLIT(B20,""/"")"),29.0) -> 29 | F20: =IFERROR(__xludf.DUMMYFUNCTION("""COMPUTED_VALUE"""),9.0) -> 9 | G20: =IFERROR(__xludf.DUMMYFUNCTION("""COMPUTED_VALUE"""),2024.0) -> 2024 | H20: =TEXTJOIN("/",1,G20,F20,E20) -> 2024/9/29 | I20: Tahu Lada Garam | J20: =IFERROR(ifs(I20="Roti cranberry 2 pcs","Roti Cranberry",I20="Roti Gandum Cokelat 2 pcs","Roti Gandum Cokelat"),I20) -> Tahu Lada Garam | K20: =if(RIGHT(I20,5)="2 pcs",2,Data!I20) -> 1 | L20: =TEXT(B20,"dddd") -> Sunday | M20: =TEXT(H20,"d") -> 29 | N20: =VLOOKUP(L20,'Data Info'!$A$1:$B$8,2,0) -> 7 | O20: =VLOOKUP(L20,'Data Info'!$A$1:$C$8,3,0) -> Weekend
A21: 45564.736 | B21: =IFERROR(__xludf.DUMMYFUNCTION("SPLIT(A21,"" "")"),45564.0) -> 45564 | C21: =IFERROR(__xludf.DUMMYFUNCTION("""COMPUTED_VALUE"""),0.7361111111111112) -> 0.73611111 | D21: =HOUR(C21) -> 17 | E21: =IFERROR(__xludf.DUMMYFUNCTION("SPLIT(B21,""/"")"),29.0) -> 29 | F21: =IFERROR(__xludf.DUMMYFUNCTION("""COMPUTED_VALUE"""),9.0) -> 9 | G21: =IFERROR(__xludf.DUMMYFUNCTION("""COMPUTED_VALUE"""),2024.0) -> 2024 | H21: =TEXTJOIN("/",1,G21,F21,E21) -> 2024/9/29 | I21: Es Kopi Susu | J21: =IFERROR(ifs(I21="Roti cranberry 2 pcs","Roti Cranberry",I21="Roti Gandum Cokelat 2 pcs","Roti Gandum Cokelat"),I21) -> Es Kopi Susu | K21: =if(RIGHT(I21,5)="2 pcs",2,Data!I21) -> 1 | L21: =TEXT(B21,"dddd") -> Sunday | M21: =TEXT(H21,"d") -> 29 | N21: =VLOOKUP(L21,'Data Info'!$A$1:$B$8,2,0) -> 7 | O21: =VLOOKUP(L21,'Data Info'!$A$1:$C$8,3,0) -> Weekend
A22: 45564.736 | B22: =IFERROR(__xludf.DUMMYFUNCTION("SPLIT(A22,"" "")"),45564.0) -> 45564 | C22: =IFERROR(__xludf.DUMMYFUNCTION("""COMPUTED_VALUE"""),0.7361111111111112) -> 0.73611111 | D22: =HOUR(C22) -> 17 | E22: =IFERROR(__xludf.DUMMYFUNCTION("SPLIT(B22,""/"")"),29.0) -> 29 | F22: =IFERROR(__xludf.DUMMYFUNCTION("""COMPUTED_VALUE"""),9.0) -> 9 | G22: =IFERROR(__xludf.DUMMYFUNCTION("""COMPUTED_VALUE"""),2024.0) -> 2024 | H22: =TEXTJOIN("/",1,G22,F22,E22) -> 2024/9/29 | I22: Roti Bawang Saus Keju | J22: =IFERROR(ifs(I22="Roti cranberry 2 pcs","Roti Cranberry",I22="Roti Gandum Cokelat 2 pcs","Roti Gandum Cokelat"),I22) -> Roti Bawang Saus Keju | K22: =if(RIGHT(I22,5)="2 pcs",2,Data!I22) -> 1 | L22: =TEXT(B22,"dddd") -> Sunday | M22: =TEXT(H22,"d") -> 29 | N22: =VLOOKUP(L22,'Data Info'!$A$1:$B$8,2,0) -> 7 | O22: =VLOOKUP(L22,'Data Info'!$A$1:$C$8,3,0) -> Weekend
A23: 45564.736 | B23: =IFERROR(__xludf.DUMMYFUNCTION("SPLIT(A23,"" "")"),45564.0) -> 45564 | C23: =IFERROR(__xludf.DUMMYFUNCTION("""COMPUTED_VALUE"""),0.7361111111111112) -> 0.73611111 | D23: =HOUR(C23) -> 17 | E23: =IFERROR(__xludf.DUMMYFUNCTION("SPLIT(B23,""/"")"),29.0) -> 29 | F23: =IFERROR(__xludf.DUMMYFUNCTION("""COMPUTED_VALUE"""),9.0) -> 9 | G23: =IFERROR(__xludf.DUMMYFUNCTION("""COMPUTED_VALUE"""),2024.0) -> 2024 | H23: =TEXTJOIN("/",1,G23,F23,E23) -> 2024/9/29 | I23: Teh Manis Dingin | J23: =IFERROR(ifs(I23="Roti cranberry 2 pcs","Roti Cranberry",I23="Roti Gandum Cokelat 2 pcs","Roti Gandum Cokelat"),I23) -> Teh Manis Dingin | K23: =if(RIGHT(I23,5)="2 pcs",2,Data!I23) -> 1 | L23: =TEXT(B23,"dddd") -> Sunday | M23: =TEXT(H23,"d") -> 29 | N23: =VLOOKUP(L23,'Data Info'!$A$1:$B$8,2,0) -> 7 | O23: =VLOOKUP(L23,'Data Info'!$A$1:$C$8,3,0) -> Weekend
A24: 45564.732 | B24: =IFERROR(__xludf.DUMMYFUNCTION("SPLIT(A24,"" "")"),45564.0) -> 45564 | C24: =IFERROR(__xludf.DUMMYFUNCTION("""COMPUTED_VALUE"""),0.7319444444444444) -> 0.73194444 | D24: =HOUR(C24) -> 17 | E24: =IFERROR(__xludf.DUMMYFUNCTION("SPLIT(B24,""/"")"),29.0) -> 29 | F24: =IFERROR(__xludf.DUMMYFUNCTION("""COMPUTED_VALUE"""),9.0) -> 9 | G24: =IFERROR(__xludf.DUMMYFUNCTION("""COMPUTED_VALUE"""),2024.0) -> 2024 | H24: =TEXTJOIN("/",1,G24,F24,E24) -> 2024/9/29 | I24: Roti Bawang Saus Keju | J24: =IFERROR(ifs(I24="Roti cranberry 2 pcs","Roti Cranberry",I24="Roti Gandum Cokelat 2 pcs","Roti Gandum Cokelat"),I24) -> Roti Bawang Saus Keju | K24: =if(RIGHT(I24,5)="2 pcs",2,Data!I24) -> 1 | L24: =TEXT(B24,"dddd") -> Sunday | M24: =TEXT(H24,"d") -> 29 | N24: =VLOOKUP(L24,'Data Info'!$A$1:$B$8,2,0) -> 7 | O24: =VLOOKUP(L24,'Data Info'!$A$1:$C$8,3,0) -> Weekend
A25: 45564.732 | B25: =IFERROR(__xludf.DUMMYFUNCTION("SPLIT(A25,"" "")"),45564.0) -> 45564 | C25: =IFERROR(__xludf.DUMMYFUNCTION("""COMPUTED_VALUE"""),0.7319444444444444) -> 0.73194444 | D25: =HOUR(C25) -> 17 | E25: =IFERROR(__xludf.DUMMYFUNCTION("SPLIT(B25,""/"")"),29.0) -> 29 | F25: =IFERROR(__xludf.DUMMYFUNCTION("""COMPUTED_VALUE"""),9.0) -> 9 | G25: =IFERROR(__xludf.DUMMYFUNCTION("""COMPUTED_VALUE"""),2024.0) -> 2024 | H25: =TEXTJOIN("/",1,G25,F25,E25) -> 2024/9/29 | I25: Lemon Tea Panas | J25: =IFERROR(ifs(I25="Roti cranberry 2 pcs","Roti Cranberry",I25="Roti Gandum Cokelat 2 pcs","Roti Gandum Cokelat"),I25) -> Lemon Tea Panas | K25: =if(RIGHT(I25,5)="2 pcs",2,Data!I25) -> 1 | L25: =TEXT(B25,"dddd") -> Sunday | M25: =TEXT(H25,"d") -> 29 | N25: =VLOOKUP(L25,'Data Info'!$A$1:$B$8,2,0) -> 7 | O25: =VLOOKUP(L25,'Data Info'!$A$1:$C$8,3,0) -> Weekend
A26: 45564.732 | B26: =IFERROR(__xludf.DUMMYFUNCTION("SPLIT(A26,"" "")"),45564.0) -> 45564 | C26: =IFERROR(__xludf.DUMMYFUNCTION("""COMPUTED_VALUE"""),0.7319444444444444) -> 0.73194444 | D26: =HOUR(C26) -> 17 | E26: =IFERROR(__xludf.DUMMYFUNCTION("SPLIT(B26,""/"")"),29.0) -> 29 | F26: =IFERROR(__xludf.DUMMYFUNCTION("""COMPUTED_VALUE"""),9.0) -> 9 | G26: =IFERROR(__xludf.DUMMYFUNCTION("""COMPUTED_VALUE"""),2024.0) -> 2024 | H26: =TEXTJOIN("/",1,G26,F26,E26) -> 2024/9/29 | I26: Rempah Madu Panas | J26: =IFERROR(ifs(I26="Roti cranberry 2 pcs","Roti Cranberry",I26="Roti Gandum Cokelat 2 pcs","Roti Gandum Cokelat"),I26) -> Rempah Madu Panas | K26: =if(RIGHT(I26,5)="2 pcs",2,Data!I26) -> 1 | L26: =TEXT(B26,"dddd") -> Sunday | M26: =TEXT(H26,"d") -> 29 | N26: =VLOOKUP(L26,'Data Info'!$A$1:$B$8,2,0) -> 7 | O26: =VLOOKUP(L26,'Data Info'!$A$1:$C$8,3,0) -> Weekend
A27: 45564.729 | B27: =IFERROR(__xludf.DUMMYFUNCTION("SPLIT(A27,"" "")"),45564.0) -> 45564 | C27: =IFERROR(__xludf.DUMMYFUNCTION("""COMPUTED_VALUE"""),0.7291666666666666) -> 0.72916667 | D27: =HOUR(C27) -> 17 | E27: =IFERROR(__xludf.DUMMYFUNCTION("SPLIT(B27,""/"")"),29.0) -> 29 | F27: =IFERROR(__xludf.DUMMYFUNCTION("""COMPUTED_VALUE"""),9.0) -> 9 | G27: =IFERROR(__xludf.DUMMYFUNCTION("""COMPUTED_VALUE"""),2024.0) -> 2024 | H27: =TEXTJOIN("/",1,G27,F27,E27) -> 2024/9/29 | I27: Es Kopi Susu | J27: =IFERROR(ifs(I27="Roti cranberry 2 pcs","Roti Cranberry",I27="Roti Gandum Cokelat 2 pcs","Roti Gandum Cokelat"),I27) -> Es Kopi Susu | K27: =if(RIGHT(I27,5)="2 pcs",2,Data!I27) -> 1 | L27: =TEXT(B27,"dddd") -> Sunday | M27: =TEXT(H27,"d") -> 29 | N27: =VLOOKUP(L27,'Data Info'!$A$1:$B$8,2,0) -> 7 | O27: =VLOOKUP(L27,'Data Info'!$A$1:$C$8,3,0) -> Weekend
